Workbook
Name s3target: [1]ActivityList!$AW$8
Name s4target: [1]ActivityList!$AW$7
Name s5target: [1]ActivityList!$AW$6

Sheet ReadMe
A1: UKRAINE 2026 Humanitarain Needs & Response Plan
A2: People Affected, PIN & Severity Estimates | Activities, Response Targets & People Prioritized
A4: This data is shared for humanitarian purposes and should only be unsed in accordance with the Ukraine Infromation Sharing Proctol, May 2023.
A6: Notes:
A7: 1) The dataset is produced by the United Nations for the Coordination of Humanitarian Affairs (OCHA) in collaboration with humanitarian partners. It presents the number of people in need (PiN), the severity of those needs, the activities of the planned response, and the number of people to be reached with humanitarian assistance in Ukraine in 2026.
A8: 2) The data provided herein should be interpreted and used according to the Ukraine 2026 Humanitarian Needs and Response Plan (HNRP), which explains the strategic priorities and the basis for the selected response activities, planned reach and people to be prioritized. | B8: Link
A9: 3) The data sources and methodology for the derivation of the PIN and severity of needs is explained in Annex 4.3 of the Ukraine 2026 HNRP, "Analysis Methodology & Data Sources", which desribes the baseline and affected population estimates, and the analytical methodology tailored to the strategic priority framework. | B9: Link
A10: 4) Abreviations List: SP = Strategic Priority ED = Education (Cluster) FL = Food Security & Livelihoods (Cluster) FS = Food Security (part of Cluster) LI = Livelihoods (part of Cluster) HE = Health (Cluster) PR = Protection (Cluster) GP = Protection (part of Cluster) CP = Child Protection (part of Cluster) GB = Gender-Based Violence (part of Cluster) SN = Shelter & NFIs (Cluster) WA = WASH (Cluster) CW = Cash Working Group UC = Unified Cash Transfer AoR = Area of Responsbility IDP = Internally-Displaced People WAND = War-Affected Non-Displaced People PiN = People in Need
A11: 5) Contact: UN-OCHA Ukraine IMU, ocha-ukr-im@un.org

Sheet ActivityList
A1: UKRAINE 2026 HNRP
A2: List of Activities and Requirements for Government Controlled Areas
A3: Release Date: 13 January 2026
A5: # | B5: Cluster | C5: Cluster Code | D5: Activity Name | E5: Strategic Objective | F5: Activity Code | G5: Modality | H5: Type of Needs | I5: Recipient | J5: Strategic Priority | K5: Activity Unit | L5: Target (individuals to be reached) | O5: Activity | P5: Prioritized Target | S5: Prioritized Activity
L6: IDPs | M6: WAND | N6: Overall | O6: Cost (USD) | P6: IDPs | Q6: WAND | R6: Overall | S6: Cost (USD)
A7: # | B7: sector | C7: sector_short | D7: activity | E7: so | F7: ActFullCode | G7: modality_group | H7: needs | I7: recipient | J7: sp | K7: act_unit | L7: target_idp | M7: target_ndp | N7: target_overall | O7: cost_total | P7: targetPr_idp | Q7: targetPr_ndp | R7: targetPr_overall | S7: costPr_total
A8: 1 | B8: Education | C8: EDU | D8: Provision of social emotional learning support to children affected by war | E8: SO1 | F8: SP1_ED101_IK | G8: In-kind / Service | H8: Specific | I8: Individual | J8: SP1 | K8: Individual | L8: 80567 | M8: 111497 | N8: 192064 | O8: 8930976 | P8: 80566 | Q8: 111497 | R8: 192063 | S8: 8930976
A9: 2 | B9: Education | C9: EDU | D9: Support schools with emergency learning shelters and quick repair and rehabilitation of education institutions damaged by strikes | E9: SO1 | F9: SP1_ED102_IK | G9: In-kind / Service | H9: Specific | I9: Individual | J9: SP1 | K9: Individual | L9: 14520 | M9: 23908 | N9: 38428 | O9: 14602640 | P9: 14520 | Q9: 23908 | R9: 38428 | S9: 14602640
A10: 3 | B10: Education | C10: EDU | D10: Provision of rapid catch-up learning for children whose education was disrupted by the war | E10: SO2 | F10: SP1_ED203_IK | G10: In-kind / Service | H10: Specific | I10: Individual | J10: SP1 | K10: Individual | L10: 26857 | M10: 47777 | N10: 74634 | O10: 4104870 | P10: 26857 | Q10: 47777 | R10: 74634 | S10: 4104870
A11: 4 | B11: Education | C11: EDU | D11: Provision of rapid catch-up learning for children whose education was disrupted by the war | E11: SO2 | F11: SP2_ED203_IK | G11: In-kind / Service | H11: Specific | I11: Individual | J11: SP2 | K11: Individual | N11: 11093 | O11: 610129.86 | R11: 11093 | S11: 610115
A12: 5 | B12: Education | C12: EDU | D12: Provision of social emotional learning support to children affected by war | E12: SO1 | F12: SP3_ED101_IK | G12: In-kind / Service | H12: Specific | I12: Individual | J12: SP3 | K12: Individual | N12: 141506 | O12: 6580011.1 | R12: 82597 | S12: 3840781.4
A13: 6 | B13: Education | C13: EDU | D13: Support schools with emergency learning shelters and quick repair and rehabilitation of education institutions damaged by strikes | E13: SO1 | F13: SP3_ED102_IK | G13: In-kind / Service | H13: Specific | I13: Individual | J13: SP3 | K13: Individual | N13: 3538 | O13: 1344303.3 | R13: 2065 | S13: 784675.77
A14: 7 | B14: Education | C14: EDU | D14: Provision of rapid catch-up learning for children whose education was disrupted by the war | E14: SO2 | F14: SP3_ED203_IK | G14: In-kind / Service | H14: Specific | I14: Individual | J14: SP3 | K14: Individual | N14: 88441 | O14: 4864255.5 | R14: 51623 | S14: 2839287.3
A15: 8 | B15: Education | C15: EDU | D15: Provision of social emotional learning support to children affected by war | E15: SO1 | F15: SP4_ED101_IK | G15: In-kind / Service | H15: Specific | I15: Individual | J15: SP4 | K15: Individual | L15: 192725 | N15: 192725 | O15: 8961712.5 | P15: 111817 | R15: 111817 | S15: 5199490.5
A16: 9 | B16: Education | C16: EDU | D16: Provision of rapid catch-up learning for children whose education was disrupted by the war | E16: SO2 | F16: SP4_ED203_IK | G16: In-kind / Service | H16: Specific | I16: Individual | J16: SP4 | K16: Individual | L16: 151738 | N16: 151738 | O16: 8345590 | P16: 88037 | R16: 88037 | S16: 4842022.8
A17: 10 | B17: Food Security | C17: FSL_FS | D17: Distribution of recurrent emergency life-saving food assistance | E17: SO1 | F17: SP1_FS102_CV | G17: Cash / Voucher | H17: Generic | I17: Individual | J17: SP1 | K17: Individual | L17: 17173 | M17: 60118 | N17: 77291 | O17: 14254274 | P17: 17168 | Q17: 58634 | R17: 75802 | S17: 13979830
A18: 11 | B18: Food Security | C18: FSL_FS | D18: Distribution of recurrent emergency life-saving food assistance | E18: SO1 | F18: SP1_FS101_IK | G18: In-kind / Service | H18: Generic | I18: Individual | J18: SP1 | K18: Individual | L18: 154555 | M18: 541059 | N18: 695614 | O18: 1.1191737e+08 | P18: 154513 | Q18: 527707 | R18: 682220 | S18: 1.0976257e+08
A19: 12 | B19: Food Security | C19: FSL_FS | D19: Ready to Eat Kits (Survival Kit) | E19: SO1 | F19: SP1_FS104_IK | G19: In-kind / Service | H19: Generic | I19: Individual | J19: SP1 | K19: Individual | L19: 2348 | M19: 14868 | N19: 17216 | O19: 275457.23 | P19: 2348 | Q19: 14501 | R19: 16849 | S19: 269577.08
A20: 13 | B20: Food Security | C20: FSL_FS | D20: Hot Meals | E20: SO1 | F20: SP2_FS105_IK | G20: In-kind / Service | H20: Generic | I20: Individual | J20: SP2 | K20: Individual | N20: 126060 | O20: 756359.44 | R20: 126060 | S20: 756359.44
A21: 14 | B21: Food Security | C21: FSL_FS | D21: Ready to Eat Kits | E21: SO1 | F21: SP2_FS103_IK | G21: In-kind / Service | H21: Generic | I21: Individual | J21: SP2 | K21: Individual | N21: 126060 | O21: 1008479.2 | R21: 126060 | S21: 1008479.2
A22: 15 | B22: Food Security | C22: FSL_FS | D22: Hot Meals | E22: SO1 | F22: SP3_FS105_IK | G22: In-kind / Service | H22: Generic | I22: Individual | J22: SP3 | K22: Individual | N22: 377501 | O22: 2265007.1 | R22: 340124 | S22: 2040746.2
A23: 16 | B23: Food Security | C23: FSL_FS | D23: Ready to Eat Kits | E23: SO1 | F23: SP3_FS103_IK | G23: In-kind / Service | H23: Generic | I23: Individual | J23: SP3 | K23: Individual | N23: 330780 | O23: 2646241.9 | R23: 298029 | S23: 2384234.5
A24: 17 | B24: Food Security | C24: FSL_FS | D24: Distribution of recurrent emergency life-saving food assistance | E24: SO1 | F24: SP4_FS102_CV | G24: Cash / Voucher | H24: Generic | I24: Individual | J24: SP4 | K24: Individual | L24: 46000 | N24: 46000 | O24: 9691733.6 | P24: 34356 | R24: 34356 | S24: 7238376.6
A25: 18 | B25: Food Security | C25: FSL_FS | D25: Distribution of recurrent emergency life-saving food assistance | E25: SO1 | F25: SP4_FS101_IK | G25: In-kind / Service | H25: Generic | I25: Individual | J25: SP4 | K25: Individual | L25: 184001 | N25: 184001 | O25: 19872152 | P25: 137424 | R25: 137424 | S25: 14841733
A26: 19 | B26: Livelihoods | C26: FSL_LI | D26: Emergency Livestock Relocation | E26: SO1 | F26: SP2_LI105_CV | G26: Cash / Voucher | H26: Specific | I26: Individual | J26: SP2 | K26: Individual | N26: 16473 | O26: 13661496 | R26: 16473 | S26: 13661496
A27: 20 | B27: Livelihoods | C27: FSL_LI | D27: Household Income Protection Kit | E27: SO2 | F27: SP2_LI206_CV | G27: Cash / Voucher | H27: Specific | I27: Individual | J27: SP2 | K27: Individual | N27: 23527 | O27: 8306053.9 | R27: 23527 | S27: 8306053.9
A28: 21 | B28: Livelihoods | C28: FSL_LI | D28: Household Income Protection Kit | E28: SO2 | F28: SP3_LI206_CV | G28: Cash / Voucher | H28: Specific | I28: Individual | J28: SP3 | K28: Individual | N28: 29992 | O28: 10304745 | R28: 17317 | S28: 5949821.1
A29: 22 | B29: Livelihoods | C29: FSL_LI | D29: Emergency food production kit (crop) | E29: SO2 | F29: SP4_LI207_CV | G29: Cash / Voucher | H29: Specific | I29: Individual | J29: SP4 | K29: Individual | L29: 20242 | M29: 11462 | N29: 31704 | O29: 5634352.2 | P29: 13546 | Q29: 11012 | R29: 24558 | S29: 4364309.9
A30: 23 | B30: Livelihoods | C30: FSL_LI | D30: Emergency food production kit (crop) | E30: SO2 | F30: SP4_LI207_IK | G30: In-kind / Service | H30: Specific | I30: Individual | J30: SP4 | K30: Individual | L30: 50616 | M30: 45838 | N30: 96454 | O30: 17389158 | P30: 33872 | Q30: 44037 | R30: 77909 | S30: 14045798
A31: 24 | B31: Livelihoods | C31: FSL_LI | D31: Emergency food production kit (livestock and animal health) | E31: SO2 | F31: SP4_LI208_IK | G31: In-kind / Service | H31: Specific | I31: Individual | J31: SP4 | K31: Individual | L31: 12097 | M31: 13416 | N31: 25513 | O31: 3190819.5 | P31: 8095 | Q31: 12889 | R31: 20984 | S31: 2624411.4
A32: 25 | B32: Livelihoods | C32: FSL_LI | D32: Emergency food production kit (livestock and animal health) | E32: SO2 | F32: SP4_LI208_CV | G32: Cash / Voucher | H32: Specific | I32: Individual | J32: SP4 | K32: Individual | L32: 50123 | M32: 63520 | N32: 113643 | O32: 13988484 | P32: 33542 | Q32: 61024 | R32: 94566 | S32: 11639693
A33: 26 | B33: Livelihoods | C33: FSL_LI | D33: Emergency food production kit (mixed) | E33: SO2 | F33: SP4_LI209_IK | G33: In-kind / Service | H33: Specific | I33: Individual | J33: SP4 | K33: Individual | L33: 18865 | M33: 24220 | N33: 43085 | O33: 10262917 | P33: 12625 | Q33: 23268 | R33: 35893 | S33: 8549709.8
A34: 27 | B34: Livelihoods | C34: FSL_LI | D34: Emergency food production kit (mixed) | E34: SO2 | F34: SP4_LI209_CV | G34: Cash / Voucher | H34: Specific | I34: Individual | J34: SP4 | K34: Individual | L34: 66183 | M34: 44654 | N34: 110837 | O34: 25970941 | P34: 44289 | Q34: 42899 | R34: 87188 | S34: 20428742
A35: 28 | B35: Livelihoods | C35: FSL_LI | D35: Household Income Protection Kit | E35: SO2 | F35: SP4_LI206_CV | G35: Cash / Voucher | H35: Specific | I35: Individual | J35: SP4 | K35: Individual | L35: 50256 | M35: 35841 | N35: 86097 | O35: 29581806 | P35: 33631 | Q35: 34433 | R35: 68064 | S35: 23385911
A36: 29 | B36: Health | C36: HEA | D36: HE101 - Improve access to lifesaving integrated quality and integrated healthcare including MHPSS and nutrition | E36: SO1 | F36: SP1_HE101_IK | G36: In-kind / Service | H36: Specific | I36: Individual | J36: SP1 | K36: Individual | L36: 137605 | M36: 237037 | N36: 374642 | O36: 26457257 | P36: 137605 | Q36: 191363 | R36: 328968 | S36: 23231812
A37: 30 | B37: Health | C37: HEA | D37: HE102 - Provide financial support for health care related costs - cash or vouchers | E37: SO1 | F37: SP1_HE102_CV | G37: Cash / Voucher | H37: Specific | I37: Individual | J37: SP1 | K37: Individual | L37: 3023 | M37: 5970 | N37: 8993 | O37: 962241.15 | P37: 3023 | Q37: 4819 | R37: 7842 | S37: 839163.93
A38: 31 | B38: Health | C38: HEA | D38: HE103 - Support risk communication and community engagement and provision of Information Education and Communication (IEC) to improve health outcomes for patients, caregivers and health care providers | E38: SO1 | F38: SP1_HE103_IK | G38: In-kind / Service | H38: Specific | I38: Individual | J38: SP1 | K38: Individual | L38: 6372 | M38: 10440 | N38: 16812 | O38: 28592.702 | P38: 6372 | Q38: 8428 | R38: 14800 | S38: 25171.557
A39: 32 | B39: Health | C39: HEA | D39: HE104 - Procure, preposition and distribute essential medications, medical equipment and medical commodities to health facilities (PHC and Secondary/tertiary level) | E39: SO1 | F39: SP1_HE104_IK | G39: In-kind / Service | H39: Specific | I39: Individual | J39: SP1 | K39: Individual | L39: 213399 | M39: 481515 | N39: 694914 | O39: 20819623 | P39: 213399 | Q39: 388733 | R39: 602132 | S39: 18039918
A40: 33 | B40: Health | C40: HEA | D40: HE105 - Engage in capacity building for health care providers and first responders and other community members to improve their ability to respond to the needs of vulnerable populations | E40: SO1 | F40: SP1_HE105_IK | G40: In-kind / Service | H40: Specific | I40: Individual | J40: SP1 | K40: Individual | L40: 1501 | M40: 470 | N40: 1971 | O40: 843874.47 | P40: 1501 | Q40: 380 | R40: 1881 | S40: 805102.39
A41: 34 | B41: Health | C41: HEA | D41: HE201 - Provide support to improve readiness, preparedness, and response to all hazards, including outbreaks of disease | E41: SO2 | F41: SP1_HE206_IK | G41: In-kind / Service | H41: Generic | I41: Institution | J41: SP1 | K41: Individual | L41: 46651 | M41: 46659 | N41: 93310 | O41: 2595892.5 | P41: 46651 | Q41: 37669 | R41: 84320 | S41: 2345780.9
A42: 35 | B42: Health | C42: HEA | D42: HE101 - Improve access to lifesaving integrated quality and integrated healthcare including MHPSS and nutrition | E42: SO1 | F42: SP2_HE101_IK | G42: In-kind / Service | H42: Specific | I42: Individual | J42: SP2 | K42: Individual | N42: 149643 | O42: 10567760 | R42: 149642 | S42: 10567751
A43: 36 | B43: Health | C43: HEA | D43: HE103 - Support risk communication and community engagement and provision of Information Education and Communication (IEC) to improve health outcomes for patients, caregivers and health care providers | E43: SO1 | F43: SP2_HE103_IK | G43: In-kind / Service | H43: Specific | I43: Individual | J43: SP2 | K43: Individual | N43: 6513 | O43: 11077.593 | R43: 6513 | S43: 11077.582
A44: 37 | B44: Health | C44: HEA | D44: HE201 - Provide support to improve readiness, preparedness, and response to all hazards, including outbreaks of disease | E44: SO2 | F44: SP2_HE206_IK | G44: In-kind / Service | H44: Generic | I44: Institution | J44: SP2 | K44: Individual | N44: 57448 | O44: 1598211.7 | R44: 57448 | S44: 1598210.2
A45: 38 | B45: Health | C45: HEA | D45: HE101 - Improve access to lifesaving integrated quality and integrated healthcare including MHPSS and nutrition | E45: SO1 | F45: SP3_HE101_IK | G45: In-kind / Service | H45: Specific | I45: Individual | J45: SP3 | K45: Individual | N45: 123408 | O45: 8715056.2 | R45: 123408 | S45: 8715056.2
A46: 39 | B46: Health | C46: HEA | D46: HE103 - Support risk communication and community engagement and provision of Information Education and Communication (IEC) to improve health outcomes for patients, caregivers and health care providers | E46: SO1 | F46: SP3_HE103_IK | G46: In-kind / Service | H46: Specific | I46: Individual | J46: SP3 | K46: Individual | N46: 5311 | O46: 9032.2208 | R46: 5311 | S46: 9032.2208
A47: 40 | B47: Health | C47: HEA | D47: HE104 - Procure, preposition and distribute essential medications, medical equipment and medical commodities to health facilities (PHC and Secondary/tertiary level) | E47: SO1 | F47: SP3_HE104_IK | G47: In-kind / Service | H47: Specific | I47: Individual | J47: SP3 | K47: Individual | N47: 237542 | O47: 7116769.7 | R47: 237542 | S47: 7116769.7
A48: 41 | B48: Health | C48: HEA | D48: HE105 - Engage in capacity building for health care providers and first responders and other community members to improve their ability to respond to the needs of vulnerable populations | E48: SO1 | F48: SP3_HE105_IK | G48: In-kind / Service | H48: Specific | I48: Individual | J48: SP3 | K48: Individual | N48: 310 | O48: 132677.27 | R48: 310 | S48: 132677.27
A49: 42 | B49: Health | C49: HEA | D49: HE201 - Provide support to improve readiness, preparedness, and response to all hazards, including outbreaks of disease | E49: SO2 | F49: SP3_HE206_IK | G49: In-kind / Service | H49: Generic | I49: Institution | J49: SP3 | K49: Individual | N49: 11309 | O49: 314617.48 | R49: 11309 | S49: 314617.48
A50: 43 | B50: Health | C50: HEA | D50: HE101 - Improve access to lifesaving integrated quality and integrated healthcare including MHPSS and nutrition | E50: SO1 | F50: SP4_HE101_IK | G50: In-kind / Service | H50: Specific | I50: Individual | J50: SP4 | K50: Individual | L50: 59966 | N50: 59966 | O50: 4234766.7 | P50: 47004 | R50: 47004 | S50: 3319403
A51: 44 | B51: Health | C51: HEA | D51: HE102 - Provide financial support for health care related costs - cash or vouchers | E51: SO1 | F51: SP4_HE102_CV | G51: Cash / Voucher | H51: Specific | I51: Individual | J51: SP4 | K51: Individual | L51: 1492 | N51: 1492 | O51: 159633.25 | P51: 1169 | R51: 1169 | S51: 125127.81
A52: 45 | B52: Health | C52: HEA | D52: HE104 - Procure, preposition and distribute essential medications, medical equipment and medical commodities to health facilities (PHC and Secondary/tertiary level) | E52: SO1 | F52: SP4_HE104_IK | G52: In-kind / Service | H52: Specific | I52: Individual | J52: SP4 | K52: Individual | L52: 105306 | N52: 105306 | O52: 3154976.9 | P52: 82544 | R52: 82544 | S52: 2473014.6
A53: 46 | B53: Protection | C53: P1_PRT | D53: Deliver targeted life-saving information and provide critical guidance that supports improved protection outcomes | E53: SO1 | F53: SP1_PR116_IK | G53: In-kind / Service | H53: Specific | I53: Individual | J53: SP1 | K53: Individual | L53: 100462 | M53: 187885 | N53: 288347 | O53: 2883470.3 | P53: 100462 | Q53: 187885 | R53: 288347 | S53: 2883470.3
A54: 47 | B54: Protection | C54: P1_PRT | D54: Implement and support case manegement actions | E54: SO1 | F54: SP1_PR111_IK | G54: In-kind / Service | H54: Specific | I54: Individual | J54: SP1 | K54: Individual | L54: 15456 | M54: 18182 | N54: 33638 | O54: 13455372 | P54: 15456 | Q54: 18182 | R54: 33638 | S54: 13455372
A55: 48 | B55: Protection | C55: P1_PRT | D55: Implement referral actions to respond to critical protection risks | E55: SO1 | F55: SP1_PR119_IK | G55: In-kind / Service | H55: Specific | I55: Individual | J55: SP1 | K55: Individual | L55: 3864 | M55: 6061 | N55: 9925 | O55: 297741.9 | P55: 3864 | Q55: 6061 | R55: 9925 | S55: 297741.9
A56: 49 | B56: Protection | C56: P1_PRT | D56: Monitoring and consultation activities, including incidents, protection, human rights violations or displacement | E56: SO1 | F56: SP1_PR126_IK | G56: In-kind / Service | H56: Specific | I56: Individual | J56: SP1 | K56: Individual | L56: 5796 | M56: 9091 | N56: 14887 | O56: 238193.52 | P56: 5796 | Q56: 9091 | R56: 14887 | S56: 238193.52
A57: 50 | B57: Protection | C57: P1_PRT | D57: Provide psychosocial and Social-Emotional Support Activities for Men, Women, Children, Adolescents, and Caregivers | E57: SO1 | F57: SP1_PR118_IK | G57: In-kind / Service | H57: Specific | I57: Individual | J57: SP1 | K57: Individual | L57: 92734 | M57: 139399 | N57: 232133 | O57: 17409953 | P57: 92734 | Q57: 139399 | R57: 232133 | S57: 17409953
A58: 51 | B58: Protection | C58: P1_PRT | D58: Provide specific support through transportation and provision of essential protection-related kits or items | E58: SO1 | F58: SP1_PR114_IK | G58: In-kind / Service | H58: Specific | I58: Individual | J58: SP1 | K58: Individual | L58: 112054 | M58: 163642 | N58: 275696 | O58: 19298688 | P58: 112054 | Q58: 163642 | R58: 275696 | S58: 19298688
A59: 52 | B59: Protection | C59: P1_PRT | D59: Provision of financial, cash and voucher / CVA assistance for protection outcomes | E59: SO1 | F59: SP1_PR113_CV | G59: Cash / Voucher | H59: Specific | I59: Individual | J59: SP1 | K59: Individual | L59: 1932 | M59: 3030 | N59: 4962 | O59: 1984946 | P59: 1932 | Q59: 3030 | R59: 4962 | S59: 1984946
A60: 53 | B60: Protection | C60: P1_PRT | D60: Provision of legal assistance, including on legal identity and HLP | E60: SO1 | F60: SP1_PR115_IK | G60: In-kind / Service | H60: Specific | I60: Individual | J60: SP1 | K60: Individual | L60: 30911 | M60: 39395 | N60: 70306 | O60: 8788328.1 | P60: 30911 | Q60: 39395 | R60: 70306 | S60: 8788328.1
A61: 54 | B61: Protection | C61: P1_PRT | D61: Reinforce or establish community mechanisms, including local structures and networks | E61: SO1 | F61: SP1_PR112_IK | G61: In-kind / Service | H61: Specific | I61: Individual | J61: SP1 | K61: Individual | L61: 15456 | M61: 24243 | N61: 39699 | O61: 6351827.2 | P61: 15456 | Q61: 24243 | R61: 39699 | S61: 6351827.2
A62: 55 | B62: Protection | C62: P1_PRT | D62: Support to localization, quality programming and complementarity with Government | E62: SO1 | F62: SP1_PR124_IK | G62: In-kind / Service | H62: Specific | I62: Individual | J62: SP1 | K62: Individual | L62: 7728 | M62: 15152 | N62: 22880 | O62: 4575973 | P62: 7728 | Q62: 15152 | R62: 22880 | S62: 4575973
A63: 56 | B63: Protection | C63: P1_PRT | D63: Carry out advocacy actions on protection | E63: SO2 | F63: SP1_PR222_IK | G63: In-kind / Service | H63: Specific | I63: Institution | J63: SP1 | K63: Intervention | L63: 1 | M63: 1 | N63: 2 | O63: 2000000 | P63: 1 | Q63: 1 | R63: 2 | S63: 2000000
A64: 57 | B64: Protection | C64: P1_PRT | D64: Deliver targeted life-saving information and provide critical guidance that supports improved protection outcomes | E64: SO1 | F64: SP2_PR116_IK | G64: In-kind / Service | H64: Specific | I64: Individual | J64: SP2 | K64: Individual | N64: 138667 | O64: 1386670 | R64: 138667 | S64: 1386670
A65: 58 | B65: Protection | C65: P1_PRT | D65: Implement and support case manegement actions | E65: SO1 | F65: SP2_PR111_IK | G65: In-kind / Service | H65: Specific | I65: Individual | J65: SP2 | K65: Individual | N65: 15127 | O65: 6050800 | R65: 15127 | S65: 6050800
A66: 59 | B66: Protection | C66: P1_PRT | D66: Implement referral actions to respond to critical protection risks | E66: SO1 | F66: SP2_PR119_IK | G66: In-kind / Service | H66: Specific | I66: Individual | J66: SP2 | K66: Individual | N66: 5042 | O66: 151260 | R66: 5042 | S66: 151260
A67: 60 | B67: Protection | C67: P1_PRT | D67: Monitoring and consultation activities, including incidents, protection, human rights violations or displacement | E67: SO1 | F67: SP2_PR126_IK | G67: In-kind / Service | H67: Specific | I67: Individual | J67: SP2 | K67: Individual | N67: 5042 | O67: 80672 | R67: 5042 | S67: 80672
A68: 61 | B68: Protection | C68: P1_PRT | D68: Provide psychosocial and Social-Emotional Support Activities for Men, Women, Children, Adolescents, and Caregivers | E68: SO1 | F68: SP2_PR118_IK | G68: In-kind / Service | H68: Specific | I68: Individual | J68: SP2 | K68: Individual | N68: 70594 | O68: 5294550 | R68: 70594 | S68: 5294550
A69: 62 | B69: Protection | C69: P1_PRT | D69: Provide specific support through transportation and provision of essential protection-related kits or items | E69: SO1 | F69: SP2_PR114_IK | G69: In-kind / Service | H69: Specific | I69: Individual | J69: SP2 | K69: Individual | N69: 141187 | O69: 9883090 | R69: 141187 | S69: 9883090
A70: 63 | B70: Protection | C70: P1_PRT | D70: Provision of financial, cash and voucher / CVA assistance for protection outcomes | E70: SO1 | F70: SP2_PR113_CV | G70: Cash / Voucher | H70: Specific | I70: Individual | J70: SP2 | K70: Individual | N70: 2521 | O70: 1008400 | R70: 2521 | S70: 1008400
A71: 64 | B71: Protection | C71: P1_PRT | D71: Provision of legal assistance, including on legal identity and HLP | E71: SO1 | F71: SP2_PR115_IK | G71: In-kind / Service | H71: Specific | I71: Individual | J71: SP2 | K71: Individual | N71: 15127 | O71: 1890875 | R71: 15127 | S71: 1890875
A72: 65 | B72: Protection | C72: P1_PRT | D72: Provision of site management services in CS & TC | E72: SO1 | F72: SP2_PR121_IK | G72: In-kind / Service | H72: Specific | I72: Individual | J72: SP2 | K72: Individual | N72: 85721 | O72: 1714420 | R72: 85721 | S72: 1714420
A73: 66 | B73: Protection | C73: P1_PRT | D73: Reinforce or establish community mechanisms, including local structures and networks | E73: SO1 | F73: SP2_PR112_IK | G73: In-kind / Service | H73: Specific | I73: Individual | J73: SP2 | K73: Individual | N73: 10085 | O73: 1613600 | R73: 10085 | S73: 1613600
A74: 67 | B74: Protection | C74: P1_PRT | D74: Support to localization, quality programming and complementarity with Government | E74: SO1 | F74: SP2_PR124_IK | G74: In-kind / Service | H74: Specific | I74: Individual | J74: SP2 | K74: Individual | N74: 5042 | O74: 1008400 | R74: 5042 | S74: 1008400
A75: 68 | B75: Protection | C75: P1_PRT | D75: Carry out advocacy actions on protection | E75: SO2 | F75: SP2_PR222_IK | G75: In-kind / Service | H75: Specific | I75: Institution | J75: SP2 | K75: Intervention | N75: 1 | O75: 1000000 | R75: 1 | S75: 1000000
... A86: 79 | B86: Protection | C86: P1_PRT | D86: Support to localization, quality programming and complementarity with Government | E86: SO1 | F86: SP3_PR124_IK | G86: In-kind / Service | H86: Specific | I86: Individual | J86: SP3 | K86: Individual | N86: 17688 | O86: 3537600 | R86: 10239 | S86: 2047830.9
A87: 80 | B87: Protection | C87: P1_PRT | D87: Carry out advocacy actions on protection | E87: SO1 | F87: SP4_PR122_IK | G87: In-kind / Service | H87: Specific | I87: Institution | J87: SP4 | K87: Intervention | L87: 1 | N87: 1 | O87: 1000000 | P87: 1 | R87: 1 | S87: 879462.3
A88: 81 | B88: Protection | C88: P1_PRT | D88: Deliver targeted life-saving information and provide critical guidance that supports improved protection outcomes | E88: SO1 | F88: SP4_PR116_IK | G88: In-kind / Service | H88: Specific | I88: Individual | J88: SP4 | K88: Individual | L88: 214754 | N88: 214754 | O88: 2147540 | P88: 188868 | R88: 188868 | S88: 1888680.5
A89: 82 | B89: Protection | C89: P1_PRT | D89: Implement and support case manegement actions | E89: SO1 | F89: SP4_PR111_IK | G89: In-kind / Service | H89: Specific | I89: Individual | J89: SP4 | K89: Individual | L89: 65518 | N89: 65518 | O89: 26207200 | P89: 57621 | R89: 57621 | S89: 23048244
A90: 83 | B90: Protection | C90: P1_PRT | D90: Implement referral actions to respond to critical protection risks | E90: SO1 | F90: SP4_PR119_IK | G90: In-kind / Service | H90: Specific | I90: Individual | J90: SP4 | K90: Individual | L90: 7280 | N90: 7280 | O90: 218400 | P90: 6402 | R90: 6402 | S90: 192074.57
A91: 84 | B91: Protection | C91: P1_PRT | D91: Monitoring and consultation activities, including incidents, protection, human rights violations or displacement | E91: SO1 | F91: SP4_PR126_IK | G91: In-kind / Service | H91: Specific | I91: Individual | J91: SP4 | K91: Individual | L91: 7280 | N91: 7280 | O91: 116480 | P91: 6402 | R91: 6402 | S91: 102439.77
A92: 85 | B92: Protection | C92: P1_PRT | D92: Provide psychosocial and Social-Emotional Support Activities for Men, Women, Children, Adolescents, and Caregivers | E92: SO1 | F92: SP4_PR118_IK | G92: In-kind / Service | H92: Specific | I92: Individual | J92: SP4 | K92: Individual | L92: 163800 | N92: 163800 | O92: 12285000 | P92: 144056 | R92: 144056 | S92: 10804194
A93: 86 | B93: Protection | C93: P1_PRT | D93: Provide specific support through transportation and provision of essential protection-related kits or items | E93: SO1 | F93: SP4_PR114_IK | G93: In-kind / Service | H93: Specific | I93: Individual | J93: SP4 | K93: Individual | L93: 54598 | N93: 54598 | O93: 3821860 | P93: 48017 | R93: 48017 | S93: 3361181.8
A94: 87 | B94: Protection | C94: P1_PRT | D94: Provision of financial, cash and voucher / CVA assistance for protection outcomes | E94: SO1 | F94: SP4_PR113_CV | G94: Cash / Voucher | H94: Specific | I94: Individual | J94: SP4 | K94: Individual | L94: 3641 | N94: 3641 | O94: 1456400 | P94: 3202 | R94: 3202 | S94: 1280848.9
A95: 88 | B95: Protection | C95: P1_PRT | D95: Provision of legal assistance, including on legal identity and HLP | E95: SO1 | F95: SP4_PR115_IK | G95: In-kind / Service | H95: Specific | I95: Individual | J95: SP4 | K95: Individual | L95: 87360 | N95: 87360 | O95: 10920000 | P95: 76830 | R95: 76830 | S95: 9603728.3
A96: 89 | B96: Protection | C96: P1_PRT | D96: Provision of site management services in CS & TC | E96: SO1 | F96: SP4_PR121_IK | G96: In-kind / Service | H96: Specific | I96: Individual | J96: SP4 | K96: Individual | L96: 65518 | N96: 65518 | O96: 1310360 | P96: 57621 | R96: 57621 | S96: 1152412.2
A97: 90 | B97: Protection | C97: P1_PRT | D97: Reinforce or establish community mechanisms, including local structures and networks | E97: SO1 | F97: SP4_PR112_IK | G97: In-kind / Service | H97: Specific | I97: Individual | J97: SP4 | K97: Individual | L97: 36401 | N97: 36401 | O97: 5824160 | P97: 32013 | R97: 32013 | S97: 5122129.2
A98: 91 | B98: Protection | C98: P1_PRT | D98: Support to localization, quality programming and complementarity with Government | E98: SO1 | F98: SP4_PR124_IK | G98: In-kind / Service | H98: Specific | I98: Individual | J98: SP4 | K98: Individual | L98: 14560 | N98: 14560 | O98: 2912000 | P98: 12805 | R98: 12805 | S98: 2560994.2
A99: 92 | B99: Protection | C99: P1_PRT | D99: Support dignified, voluntary, and informed transitions from displacement sites by creating conditions that reduce vulnerabilities, promoting safe relocations where necessary, and ensuring coordinated, protection-sensitive site closure processes | E99: SO2 | F99: SP4_PR225_IK | G99: In-kind / Service | H99: Specific | I99: Individual | J99: SP4 | K99: Individual | L99: 7280 | N99: 7280 | O99: 728000 | P99: 6402 | R99: 6402 | S99: 640248.56
A100: 93 | B100: Child Protection | C100: P2_CP | D100: Deliver targeted life-saving information and provide critical guidance that supports improved protection outcomes | E100: SO1 | F100: SP1_CP142_IK | G100: In-kind / Service | H100: Specific | I100: Individual | J100: SP1 | K100: Individual | L100: 54279 | M100: 162820 | N100: 217099 | O100: 1736792 | P100: 54279 | Q100: 156552 | R100: 210831 | S100: 1686653.4
A101: 94 | B101: Child Protection | C101: P2_CP | D101: Implement and support case manegement actions | E101: SO1 | F101: SP1_CP124_IK | G101: In-kind / Service | H101: Specific | I101: Individual | J101: SP1 | K101: Individual | L101: 7416 | M101: 22200 | N101: 29616 | O101: 11846400 | P101: 7416 | Q101: 21346 | R101: 28762 | S101: 11504588
A102: 95 | B102: Child Protection | C102: P2_CP | D102: Implement referral actions to respond to critical protection risks | E102: SO1 | F102: SP1_CP114_IK | G102: In-kind / Service | H102: Specific | I102: Individual | J102: SP1 | K102: Individual | L102: 368 | M102: 1110 | N102: 1478 | O102: 44340 | P102: 368 | Q102: 1068 | R102: 1436 | S102: 43058.205
A103: 96 | B103: Child Protection | C103: P2_CP | D103: Provide mental health and psychosocial Support Activities for Men, Women, Children, Adolescents, and Caregivers | E103: SO1 | F103: SP1_CP126_IK | G103: In-kind / Service | H103: Specific | I103: Individual | J103: SP1 | K103: Individual | L103: 88830 | M103: 265600 | N103: 354430 | O103: 26582250 | P103: 88830 | Q103: 255376 | R103: 344206 | S103: 25815483
A104: 97 | B104: Child Protection | C104: P2_CP | D104: Provide specific support through transportation (evacuations and access to services) and provision of essential protection-related kits or items | E104: SO1 | F104: SP1_CP129_IK | G104: In-kind / Service | H104: Generic | I104: Individual | J104: SP1 | K104: Individual | L104: 8854 | M104: 26570 | N104: 35424 | O104: 2302560 | P104: 8854 | Q104: 25547 | R104: 34401 | S104: 2236081.8
A105: 98 | B105: Child Protection | C105: P2_CP | D105: Provision of financial, cash and voucher / CVA assistance for protection outcomes | E105: SO1 | F105: SP1_CP128_CV | G105: Cash / Voucher | H105: Specific | I105: Individual | J105: SP1 | K105: Individual | L105: 1169 | M105: 3512 | N105: 4681 | O105: 1872400 | P105: 1169 | Q105: 3377 | R105: 4546 | S105: 1818326
A106: 99 | B106: Child Protection | C106: P2_CP | D106: Provision of legal assistance, including on legal identity and HLP | E106: SO1 | F106: SP1_CP112_IK | G106: In-kind / Service | H106: Specific | I106: Individual | J106: SP1 | K106: Individual | L106: 252 | M106: 770 | N106: 1022 | O106: 127750 | P106: 252 | Q106: 740 | R106: 992 | S106: 124045.11
A107: 100 | B107: Child Protection | C107: P2_CP | D107: Service for children and caregivers affected by explosive ordnance (EO)/victim assistance | E107: SO1 | F107: SP1_CP102_IK | G107: In-kind / Service | H107: Specific | I107: Individual | J107: SP1 | K107: Individual | L107: 1203 | M107: 3620 | N107: 4823 | O107: 2773225 | P107: 1203 | Q107: 3481 | R107: 4684 | S107: 2693103.2
A108: 101 | B108: Child Protection | C108: P2_CP | D108: Support family tracing and reunification | E108: SO1 | F108: SP1_CP127_IK | G108: In-kind / Service | H108: Specific | I108: Individual | J108: SP1 | K108: Individual | L108: 43 | M108: 126 | N108: 169 | O108: 19435 | P108: 43 | Q108: 121 | R108: 164 | S108: 18877.246
A109: 102 | B109: Child Protection | C109: P2_CP | D109: Supporting unaccompanied children or children at risk in alternative family-based care | E109: SO1 | F109: SP1_CP107_IK | G109: In-kind / Service | H109: Specific | I109: Individual | J109: SP1 | K109: Individual | L109: 88 | M109: 267 | N109: 355 | O109: 106500 | P109: 88 | Q109: 257 | R109: 345 | S109: 103416.76
A110: 103 | B110: Child Protection | C110: P2_CP | D110: Provide training and capacity building of non-protection humanitarian actors on service provision | E110: SO2 | F110: SP1_CP257_IK | G110: In-kind / Service | H110: Specific | I110: Individual | J110: SP1 | K110: Individual | L110: 1695 | M110: 5070 | N110: 6765 | O110: 405900 | P110: 1695 | Q110: 4875 | R110: 6570 | S110: 394190.63
A111: 104 | B111: Child Protection | C111: P2_CP | D111: Reinforce or establish community mechanisms, including local structures and networks | E111: SO2 | F111: SP1_CP233_IK | G111: In-kind / Service | H111: Specific | I111: Individual | J111: SP1 | K111: Individual | L111: 2250 | M111: 6750 | N111: 9000 | O111: 1440000 | P111: 2250 | Q111: 6490 | R111: 8740 | S111: 1398428.3
...

Sheet Overall by Cluster
A1: UKRAINE 2026 HNRP
A2: Overall PiN, Target and Prioritized Target by Cluster
A3: =ActivityList!A3 -> Release Date: 13 January 2026
D4: Internally Displaced People | AP4: War-Affected Non-Displaced | CB4: Overall
D5: # People in Need (IDP) | J5: Protection AoRs | M5: FSL AoRs | O5: Joint PiN | P5: # Target (IDP) | V5: Protection AoRs | Y5: FSL AoRs | AB5: Joint Target | AC5: # Prioritized Target (IDP) | AI5: Protection AoRs | AL5: FSL AoRs | AO5: Joint Target | AP5: # People in Need (WAND) | AV5: Protection AoRs | AY5: FSL AoRs | BA5: Joint PiN | BB5: # Target (WAND) | BH5: Protection AoRs | BK5: FSL AoRs | BN5: Joint Target | BO5: # Prioritized Target (WAND) | BU5: Protection AoRs | BX5: FSL AoRs | CA5: Joint Target | CB5: # People in Need (Overall) | CH5: Protection AoRs | CK5: FSL AoRs | CM5: Joint PiN | CN5: # Target (Overall) | CT5: Protection AoRs | CW5: FSL AoRs | CZ5: Joint Target | DA5: # Prioritized Target (Overall) | DG5: Protection AoRs | DJ5: FSL AoRs | DM5: Joint Target
A6: Geographical Zone | B6: Swath | C6: Code | D6: ED | E6: FS | F6: HE | G6: PR | H6: SN | I6: WA | J6: GP | K6: CP | L6: GB | M6: FD | N6: LI | P6: ED | Q6: FS | R6: HE | S6: PR | T6: SN | U6: WA | V6: GP | W6: CP | X6: GB | Y6: FD | Z6: LI | AA6: CW | AC6: ED | AD6: FS | AE6: HE | AF6: PR | AG6: SN | AH6: WA | AI6: GP | AJ6: CP | AK6: GB | AL6: FD | AM6: LI | AN6: CW | AP6: ED | AQ6: FS | AR6: HE | AS6: PR | AT6: SN | AU6: WA | AV6: GP | AW6: CP | AX6: GB | AY6: FD | AZ6: LI | BB6: ED | BC6: FS | BD6: HE | BE6: PR | BF6: SN | BG6: WA | BH6: GP | BI6: CP | BJ6: GB | BK6: FD | BL6: LI | BM6: CW | BO6: ED | BP6: FS | BQ6: HE | BR6: PR | BS6: SN | BT6: WA | BU6: GP | BV6: CP | BW6: GB | BX6: FD | BY6: LI | BZ6: CW | CB6: ED | CC6: FS | CD6: HE | CE6: PR | CF6: SN | CG6: WA | CH6: GP | CI6: CP | CJ6: GB | CK6: FD | CL6: LI | CN6: ED | CO6: FS | CP6: HE | CQ6: PR | CR6: SN | CS6: WA | CT6: GP | CU6: CP | CV6: GB | CW6: FD | CX6: LI | CY6: CW | DA6: ED | DB6: FS | DC6: HE | DD6: PR | DE6: SN | DF6: WA | DG6: GP | DH6: CP | DI6: GB | DJ6: FD | DK6: LI | DL6: CW
A7: geo_zone | B7: swath | C7: code | D7: spAll_idp_pin_ed | E7: spAll_idp_pin_fl | F7: spAll_idp_pin_he | G7: spAll_idp_pin_pr | H7: spAll_idp_pin_sn | I7: spAll_idp_pin_wa | J7: spAll_idp_pin_gp | K7: spAll_idp_pin_cp | L7: spAll_idp_pin_gb | M7: spAll_idp_pin_fs | N7: spAll_idp_pin_li | O7: spAll_idp_pin_adopted | P7: spAll_idp_target_ed | Q7: spAll_idp_target_fl | R7: spAll_idp_target_he | S7: spAll_idp_target_pr | T7: spAll_idp_target_sn | U7: spAll_idp_target_wa | V7: spAll_idp_target_gp | W7: spAll_idp_target_cp | X7: spAll_idp_target_gb | Y7: spAll_idp_target_fs | Z7: spAll_idp_target_li | AA7: spAll_idp_target_cw | AB7: spAll_idp_target_joint | AC7: spAll_idp_targetPr_ed | AD7: spAll_idp_targetPr_fl | AE7: spAll_idp_targetPr_he | AF7: spAll_idp_targetPr_pr | AG7: spAll_idp_targetPr_sn | AH7: spAll_idp_targetPr_wa | AI7: spAll_idp_targetPr_gp | AJ7: spAll_idp_targetPr_cp | AK7: spAll_idp_targetPr_gb | AL7: spAll_idp_targetPr_fs | AM7: spAll_idp_targetPr_li | AN7: spAll_idp_targetPr_cw | AO7: spAll_idp_targetPr_joint | AP7: spAll_ndp_pin_ed | AQ7: spAll_ndp_pin_fl | AR7: spAll_ndp_pin_he | AS7: spAll_ndp_pin_pr | AT7: spAll_ndp_pin_sn | AU7: spAll_ndp_pin_wa | AV7: spAll_ndp_pin_gp | AW7: spAll_ndp_pin_cp | AX7: spAll_ndp_pin_gb | AY7: spAll_ndp_pin_fs | AZ7: spAll_ndp_pin_li | BA7: spAll_ndp_pin_adopted | BB7: spAll_ndp_target_ed | BC7: spAll_ndp_target_fl | BD7: spAll_ndp_target_he | BE7: spAll_ndp_target_pr | BF7: spAll_ndp_target_sn | BG7: spAll_ndp_target_wa | BH7: spAll_ndp_target_gp | BI7: spAll_ndp_target_cp | BJ7: spAll_ndp_target_gb | BK7: spAll_ndp_target_fs | BL7: spAll_ndp_target_li | BM7: spAll_ndp_target_cw | BN7: spAll_ndp_target_joint | BO7: spAll_ndp_targetPr_ed | BP7: spAll_ndp_targetPr_fl | BQ7: spAll_ndp_targetPr_he | BR7: spAll_ndp_targetPr_pr | BS7: spAll_ndp_targetPr_sn | BT7: spAll_ndp_targetPr_wa | BU7: spAll_ndp_targetPr_gp | BV7: spAll_ndp_targetPr_cp | BW7: spAll_ndp_targetPr_gb | BX7: spAll_ndp_targetPr_fs | BY7: spAll_ndp_targetPr_li | BZ7: spAll_ndp_targetPr_cw | CA7: spAll_ndp_targetPr_joint | CB7: spAll_overall_pin_ed | CC7: spAll_overall_pin_fl | CD7: spAll_overall_pin_he | CE7: spAll_overall_pin_pr | CF7: spAll_overall_pin_sn | CG7: spAll_overall_pin_wa | CH7: spAll_overall_pin_gp | CI7: spAll_overall_pin_cp | CJ7: spAll_overall_pin_gb | CK7: spAll_overall_pin_fs | CL7: spAll_overall_pin_li | CM7: spAll_overall_pin_adopted | CN7: spAll_overall_target_ed | CO7: spAll_overall_target_fl | CP7: spAll_overall_target_he | CQ7: spAll_overall_target_pr | CR7: spAll_overall_target_sn | CS7: spAll_overall_target_wa | CT7: spAll_overall_target_gp | CU7: spAll_overall_target_cp | CV7: spAll_overall_target_gb | CW7: spAll_overall_target_fs | CX7: spAll_overall_target_li | CY7: spAll_overall_target_cw | CZ7: spAll_overall_target_joint | DA7: spAll_overall_targetPr_ed | DB7: spAll_overall_targetPr_fl | DC7: spAll_overall_targetPr_he | DD7: spAll_overall_targetPr_pr | DE7: spAll_overall_targetPr_sn | DF7: spAll_overall_targetPr_wa | DG7: spAll_overall_targetPr_gp | DH7: spAll_overall_targetPr_cp | DI7: spAll_overall_targetPr_gb | DJ7: spAll_overall_targetPr_fs | DK7: spAll_overall_targetPr_li | DL7: spAll_overall_targetPr_cw | DM7: spAll_overall_targetPr_joint
A8: GCA 0-20 km | B8: 0-20km | C8: UAGC_U20A | D8: 25705 | E8: 49022 | F8: 119279 | G8: 121128 | H8: 116780 | I8: 133730 | J8: 120312 | K8: 68716 | L8: 67782 | M8: 49022 | N8: 49022 | O8: 142420 | P8: 23136 | Q8: 49022 | R8: 88579 | S8: 90235 | T8: 93425 | U8: 133730 | V8: 90235 | W8: 39370 | X8: 3389 | Y8: 49022 | Z8: 10589 | AA8: 99278 | AB8: 137706 | AC8: 23136 | AD8: 49022 | AE8: 88579 | AF8: 90235 | AG8: 93425 | AH8: 133730 | AI8: 90235 | AJ8: 39370 | AK8: 3389 | AL8: 49022 | AM8: 10589 | AN8: 99278 | AO8: 137706 | AP8: 62304 | AQ8: 328817 | AR8: 856878 | AS8: 836056 | AT8: 827141 | AU8: 970508 | AV8: 836056 | AW8: 283388 | AX8: 478226 | AY8: 328817 | AZ8: 328817 | BA8: 1004983 | BB8: 56073 | BC8: 328817 | BD8: 436464 | BE8: 504240 | BF8: 452105 | BG8: 970508 | BH8: 504240 | BI8: 254460 | BJ8: 75636 | BK8: 328817 | BL8: 182126 | BM8: 544495 | BN8: 982830 | BO8: 56073 | BP8: 328817 | BQ8: 384116 | BR8: 504240 | BS8: 452105 | BT8: 970508 | BU8: 504240 | BV8: 254460 | BW8: 75636 | BX8: 328817 | BY8: 182126 | BZ8: 544495 | CA8: 982830 | CB8: 88009 | CC8: 377839 | CD8: 976157 | CE8: 957184 | CF8: 943921 | CG8: 1104238 | CH8: 956368 | CI8: 352104 | CJ8: 546008 | CK8: 377839 | CL8: 377839 | CM8: 1147403 | CN8: 79209 | CO8: 377839 | CP8: 525043 | CQ8: 594475 | CR8: 545530 | CS8: 1104238 | CT8: 594475 | CU8: 293830 | CV8: 79025 | CW8: 377839 | CX8: 192715 | CY8: 643773 | CZ8: 1120536 | DA8: 79209 | DB8: 377839 | DC8: 472695 | DD8: 594475 | DE8: 545530 | DF8: 1104238 | DG8: 594475 | DH8: 293830 | DI8: 79025 | DJ8: 377839 | DK8: 192715 | DL8: 643773 | DM8: 1120536
A9: GCA 21-50 km | B9: 20-50km | C9: UAGC_U50A | D9: 109967 | E9: 258749 | F9: 383749 | G9: 394874 | H9: 301187 | I9: 373618 | J9: 394874 | K9: 224186 | L9: 195004 | M9: 258749 | N9: 258749 | O9: 416154 | P9: 98971 | Q9: 250425 | R9: 319975 | S9: 296157 | T9: 235579 | U9: 352843 | V9: 296157 | W9: 128241 | X9: 97990 | Y9: 250393 | Z9: 114643 | AA9: 117319 | AB9: 366777 | AC9: 98971 | AD9: 250378 | AE9: 319975 | AF9: 296157 | AG9: 235579 | AH9: 352642 | AI9: 296157 | AJ9: 128241 | AK9: 97943 | AL9: 250346 | AM9: 114643 | AN9: 117065 | AO9: 366777 | AP9: 91342 | AQ9: 361628 | AR9: 1101659 | AS9: 1193210 | AT9: 997094 | AU9: 1239824 | AV9: 1193210 | AW9: 368486 | AX9: 466264 | AY9: 361628 | AZ9: 361628 | BA9: 1378554 | BB9: 79232 | BC9: 361628 | BD9: 466245 | BE9: 468750 | BF9: 319451 | BG9: 1058910 | BH9: 372983 | BI9: 301836 | BJ9: 211189 | BK9: 361628 | BL9: 109133 | BM9: 135137 | BN9: 1193605 | BO9: 79232 | BP9: 346288 | BQ9: 359407 | BR9: 468749 | BS9: 315978 | BT9: 1033223 | BU9: 372983 | BV9: 282274 | BW9: 204569 | BX9: 346288 | BY9: 99743 | BZ9: 129066 | CA9: 1180627 | CB9: 201309 | CC9: 620377 | CD9: 1485408 | CE9: 1588084 | CF9: 1298281 | CG9: 1613442 | CH9: 1588084 | CI9: 592672 | CJ9: 661268 | CK9: 620377 | CL9: 620377 | CM9: 1794708 | CN9: 178203 | CO9: 612053 | CP9: 786220 | CQ9: 764907 | CR9: 555030 | CS9: 1411753 | CT9: 669140 | CU9: 430077 | CV9: 309179 | CW9: 612021 | CX9: 223776 | CY9: 252456 | CZ9: 1560382 | DA9: 178203 | DB9: 596666 | DC9: 679382 | DD9: 764906 | DE9: 551557 | DF9: 1385865 | DG9: 669140 | DH9: 410515 | DI9: 302512 | DJ9: 596634 | DK9: 214386 | DL9: 246131 | DM9: 1547404
A10: GCA 51+ km | B10: 50+ | C10: UAGC_U51P | D10: 303146 | E10: 495429 | F10: 1518221 | G10: 1847162 | H10: 1207226 | I10: 1567847 | J10: 1844728 | K10: 878160 | L10: 629704 | M10: 495429 | N10: 495429 | O10: 1870245 | P10: 160213 | Q10: 255296 | R10: 102657 | S10: 634704 | T10: 91537 | U10: 417091 | V10: 595491 | W10: 290902 | X10: 129880 | Y10: 110306 | Z10: 146904 | AA10: 93271 | AB10: 705031 | AC10: 72083 | AD10: 94491.8 | AE10: 66134 | AF10: 505637 | AG10: 43384 | AH10: 123624 | AI10: 496317 | AJ10: 157109 | AK10: 66831 | AL10: 47570 | AM10: 56593 | AN10: 31456 | AO10: 563131 | AP10: 164313 | AQ10: 41078 | AR10: 0 | AS10: 1643127 | AT10: 1643127 | AU10: 1643127 | AV10: 1643127 | AW10: 575094 | AX10: 575094 | AY10: 41078 | AZ10: 41078 | BA10: 5048344.3 | BB10: 65726 | BC10: 41078 | BD10: 0 | BE10: 432427 | BF10: 228177 | BG10: 410782 | BH10: 164313 | BI10: 243467 | BJ10: 24647 | BK10: 41078 | BL10: 13930 | BM10: 67420 | BN10: 432427 | BO10: 13145 | BP10: 8215 | BQ10: 0 | BR10: 86485 | BS10: 45635 | BT10: 82156 | BU10: 32863 | BV10: 48693 | BW10: 4930 | BX10: 8215 | BY10: 2786 | BZ10: 13484 | CA10: 86485 | CB10: 467459 | CC10: 536507 | CD10: 1518221 | CE10: 3490289 | CF10: 2850353 | CG10: 3210974 | CH10: 3487855 | CI10: 1453254 | CJ10: 1204798 | CK10: 536507 | CL10: 536507 | CM10: 6918589.3 | CN10: 225939 | CO10: 296374 | CP10: 102657 | CQ10: 1067131 | CR10: 319714 | CS10: 827873 | CT10: 759804 | CU10: 534369 | CV10: 154527 | CW10: 151384 | CX10: 160834 | CY10: 160691 | CZ10: 1137458 | DA10: 85228 | DB10: 102706.8 | DC10: 66134 | DD10: 592122 | DE10: 89019 | DF10: 205780 | DG10: 529180 | DH10: 205802 | DI10: 71761 | DJ10: 55785 | DK10: 59379 | DL10: 44940 | DM10: 649616
A11: OT 0-20 km | B11: 0-20km | C11: UAOT_O20A | O11: 7414 | AB11: 4236 | AO11: 4236 | BA11: 224914 | BN11: 128460 | CA11: 128460 | CM11: 232328 | CZ11: 132696 | DM11: 132696
A12: OT 21-50 km | B12: 20-50km | C12: UAOT_O50A | O12: 10647 | AB12: 5182 | AO12: 5182 | BA12: 225310 | BN12: 155189 | CA12: 155189 | CM12: 235957 | CZ12: 160371 | DM12: 160371
A13: 51+ km (occupied after 2022) | B13: 50+ | C13: UAOT_O51N | O13: 15802 | AB13: 1507 | AO13: 1507 | BA13: 304427 | BN13: 3028 | CA13: 3028 | CM13: 320229 | CZ13: 4535 | DM13: 4535
A14: 51+ km (occupied before 2022) | B14: 50+ | C14: UAOT_O51O | O14: 9893 | AB14: 2028 | AO14: 406 | BA14: 190590 | BN14: 948 | CA14: 189 | CM14: 200483 | CZ14: 2976 | DM14: 595
A15: Total | O15: =SUBTOTAL(109,Overall[spAll_idp_pin_adopted]) -> 2472575 | AB15: =SUBTOTAL(109,Overall[spAll_idp_target_joint]) -> 1222467 | AO15: =SUBTOTAL(109,Overall[spAll_idp_targetPr_joint]) -> 1078945 | BA15: =SUBTOTAL(109,Overall[spAll_ndp_pin_adopted]) -> 8377122.3 | BN15: =SUBTOTAL(109,Overall[spAll_ndp_target_joint]) -> 2896487 | CA15: =SUBTOTAL(109,Overall[spAll_ndp_targetPr_joint]) -> 2536808 | CM15: =SUBTOTAL(109,Overall[spAll_overall_pin_adopted]) -> 10849697 | CZ15: =SUBTOTAL(109,Overall[spAll_overall_target_joint]) -> 4118954 | DM15: =SUBTOTAL(109,Overall[spAll_overall_targetPr_joint]) -> 3615753

Sheet Overall by SP and UoA
A1: UKRAINE 2026 HNRP
A2: Overall Affected, PiN, Target and Prioritized Target by Strategic Priority
A3: =ActivityList!A3 -> Release Date: 13 January 2026
M4: ed | N4: fs | O4: he | P4: pr | Q4: sn | R4: wa
A5: Oblast | C5: Analysis Zones | F5: Baseline | G5: # Affected Overall | M5: # People in Need (Individuals) | S5: Severity Phase | X5: # Target (Individuals) | AC5: # Prioritized Target (Individuals)
A6: Name (English) | B6: Pcode | C6: Geo Zone | D6: Swath | E6: Code | F6: Population | G6: SP1 | H6: SP2 | I6: SP3 | J6: SP4 | K6: WAND 50+ | L6: Overall | M6: SP1 | N6: SP2 | O6: SP3 | P6: SP4 | Q6: WAND 50+ | R6: Overall | S6: SP1 | T6: SP2 | U6: SP3 | V6: SP4 | W6: Overall | X6: SP1 | Y6: SP2 | Z6: SP3 | AA6: SP4 | AB6: Overall | AC6: SP1 | AD6: SP2 | AE6: SP3 | AF6: SP4 | AG6: Overall
A7: ADM1_EN | B7: ADM1_PCODE | C7: geo_zone | D7: swath | E7: UoA_code | F7: overall_all_total_joint | G7: overall_aff_sp1_joint | H7: overall_aff_sp2_joint | I7: overall_aff_sp3_joint | J7: overall_aff_sp4_joint | K7: overall_aff_sp5_joint | L7: overall_aff_total_joint | M7: overall_pin_sp1_joint | N7: overall_pin_sp2_joint | O7: overall_pin_sp3_joint | P7: overall_pin_sp4_joint | Q7: overall_pin_sp5_joint | R7: overall_pin_total_joint | S7: overall_sev_sp1_joint | T7: overall_sev_sp2_joint | U7: overall_sev_sp3_joint | V7: overall_sev_sp4_joint | W7: overall_sev_total_joint | X7: overall_target_sp1_joint | Y7: overall_target_sp2_joint | Z7: overall_target_sp3_joint | AA7: overall_target_sp4_joint | AB7: overall_target_total_joint | AC7: overall_targetPr_sp1_joint | AD7: overall_targetPr_sp2_joint | AE7: overall_targetPr_sp3_joint | AF7: overall_targetPr_sp4_joint | AG7: overall_targetPr_total_joint
A8: Vinnytska | B8: UA05 | C8: All oblast | D8: 50+ | E8: UA05_UALL | F8: 1346645 | G8: 0 | H8: 0 | I8: 0 | J8: 88646 | K8: 0 | L8: 0 | M8: 0 | N8: 0 | O8: 0 | P8: 71599 | Q8: 0 | R8: 0 | S8: 0 | T8: 0 | U8: 3 | V8: 3 | W8: 3 | X8: 0 | Y8: 0 | Z8: 0 | AA8: 34095 | AB8: 0 | AC8: 0 | AD8: 0 | AE8: 0 | AF8: 34095 | AG8: 0
A9: Volynska | B9: UA07 | C9: All oblast | D9: 50+ | E9: UA07_UALL | F9: 915568 | G9: 0 | H9: 0 | I9: 0 | J9: 31262 | K9: 0 | L9: 0 | M9: 0 | N9: 0 | O9: 0 | P9: 26453 | Q9: 0 | R9: 0 | S9: 0 | T9: 0 | U9: 3 | V9: 3 | W9: 3 | X9: 0 | Y9: 0 | Z9: 0 | AA9: 11761 | AB9: 0 | AC9: 0 | AD9: 0 | AE9: 0 | AF9: 11761 | AG9: 0
A10: Dnipropetrovska | B10: UA12 | C10: 0-20 km | D10: 0-20km | E10: UA12_U20A | F10: 228268 | G10: 228268 | H10: 0 | I10: 0 | J10: 228268 | K10: 0 | L10: 0 | M10: 210709 | N10: 0 | O10: 0 | P10: 89572 | Q10: 0 | R10: 0 | S10: 5 | T10: 4 | U10: 5 | V10: 5 | W10: 5 | X10: 210709 | Y10: 0 | Z10: 0 | AA10: 40036 | AB10: 0 | AC10: 210709 | AD10: 0 | AE10: 0 | AF10: 40036 | AG10: 0
A11: Dnipropetrovska | B11: UA12 | C11: 21-50 km | D11: 20-50km | E11: UA12_U50A | F11: 164650 | G11: 98942.748 | H11: 0 | I11: 0 | J11: 88538 | K11: 0 | L11: 0 | M11: 82212 | N11: 0 | O11: 0 | P11: 48204 | Q11: 0 | R11: 0 | S11: 4 | T11: 0 | U11: 4 | V11: 4 | W11: 4 | X11: 80620 | Y11: 0 | Z11: 0 | AA11: 36546 | AB11: 0 | AC11: 80620 | AD11: 0 | AE11: 0 | AF11: 36546 | AG11: 0
A12: Dnipropetrovska | B12: UA12 | C12: 51+ km | D12: 50+ | E12: UA12_U51P | F12: 2785796 | G12: 0 | H12: 0 | I12: 0 | J12: 325353 | K12: 0 | L12: 0 | M12: 0 | N12: 0 | O12: 0 | P12: 276793 | Q12: 0 | R12: 0 | S12: 0 | T12: 0 | U12: 3 | V12: 4 | W12: 4 | X12: 0 | Y12: 0 | Z12: 0 | AA12: 138397 | AB12: 0 | AC12: 0 | AD12: 0 | AE12: 0 | AF12: 138397 | AG12: 0
A13: Donetska | B13: UA14 | C13: 0-20 km | D13: 0-20km | E13: UA14_U20A | F13: 180210 | G13: 180210 | H13: 0 | I13: 0 | J13: 180210 | K13: 0 | L13: 0 | M13: 167637 | N13: 0 | O13: 0 | P13: 79143 | Q13: 0 | R13: 0 | S13: 5 | T13: 4 | U13: 5 | V13: 5 | W13: 5 | X13: 167637 | Y13: 0 | Z13: 0 | AA13: 32596 | AB13: 0 | AC13: 167637 | AD13: 0 | AE13: 0 | AF13: 32596 | AG13: 0
A14: Donetska | B14: UA14 | C14: 21-50 km | D14: 20-50km | E14: UA14_U50A | F14: 61456 | G14: 45700.32 | H14: 0 | I14: 0 | J14: 42803 | K14: 0 | L14: 0 | M14: 38016 | N14: 0 | O14: 0 | P14: 18019 | Q14: 0 | R14: 0 | S14: 5 | T14: 0 | U14: 4 | V14: 5 | W14: 5 | X14: 37090 | Y14: 0 | Z14: 0 | AA14: 15535 | AB14: 0 | AC14: 37090 | AD14: 0 | AE14: 0 | AF14: 15535 | AG14: 0
A15: Zhytomyrska | B15: UA18 | C15: All oblast | D15: 50+ | E15: UA18_UALL | F15: 1081427 | G15: 0 | H15: 0 | I15: 0 | J15: 53364 | K15: 0 | L15: 0 | M15: 0 | N15: 0 | O15: 0 | P15: 42407 | Q15: 0 | R15: 0 | S15: 0 | T15: 0 | U15: 3 | V15: 3 | W15: 3 | X15: 0 | Y15: 0 | Z15: 0 | AA15: 10107 | AB15: 0 | AC15: 0 | AD15: 0 | AE15: 0 | AF15: 2021 | AG15: 0
A16: Zakarpatska | B16: UA21 | C16: All oblast | D16: 50+ | E16: UA21_UALL | F16: 841388 | G16: 0 | H16: 0 | I16: 0 | J16: 59270 | K16: 0 | L16: 0 | M16: 0 | N16: 0 | O16: 0 | P16: 52751 | Q16: 0 | R16: 0 | S16: 0 | T16: 0 | U16: 3 | V16: 3 | W16: 3 | X16: 0 | Y16: 0 | Z16: 0 | AA16: 10702 | AB16: 0 | AC16: 0 | AD16: 0 | AE16: 0 | AF16: 2140 | AG16: 0
A17: Zaporizka | B17: UA23 | C17: 0-20 km | D17: 0-20km | E17: UA23_U20A | F17: 57720 | G17: 57720 | H17: 0 | I17: 0 | J17: 57720 | K17: 0 | L17: 0 | M17: 57720 | N17: 0 | O17: 0 | P17: 25078 | Q17: 0 | R17: 0 | S17: 5 | T17: 4 | U17: 5 | V17: 5 | W17: 5 | X17: 57720 | Y17: 0 | Z17: 0 | AA17: 11040 | AB17: 0 | AC17: 57720 | AD17: 0 | AE17: 0 | AF17: 11040 | AG17: 0
A18: Zaporizka | B18: UA23 | C18: 21-50 km (w/o Zaporizhzhia) | D18: 20-50km | E18: UA23_U50X | F18: 72784 | G18: 42291.226 | H18: 0 | I18: 0 | J18: 36140 | K18: 0 | L18: 0 | M18: 37016 | N18: 0 | O18: 0 | P18: 20859 | Q18: 0 | R18: 0 | S18: 4 | T18: 0 | U18: 4 | V18: 4 | W18: 4 | X18: 26257 | Y18: 0 | Z18: 0 | AA18: 14618 | AB18: 0 | AC18: 26257 | AD18: 0 | AE18: 0 | AF18: 14618 | AG18: 0
A19: Zaporizka | B19: UA23 | C19: 51+ km | D19: 50+ | E19: UA23_U51P | F19: 4512 | G19: 0 | H19: 0 | I19: 0 | J19: 1034 | K19: 0 | L19: 0 | M19: 0 | N19: 0 | O19: 0 | P19: 821 | Q19: 0 | R19: 0 | S19: 0 | T19: 0 | U19: 3 | V19: 4 | W19: 4 | X19: 0 | Y19: 0 | Z19: 0 | AA19: 290 | AB19: 0 | AC19: 0 | AD19: 0 | AE19: 0 | AF19: 290 | AG19: 0
... A58: GCA 51+ km | B58: UAGC | C58: 51+ km GCA | D58: 50+ | E58: UAGC_U51P | F58: 26727253 | G58: 0 | H58: 0 | I58: 1868838 | J58: 1910493 | K58: 6407207 | L58: 8543411 | M58: 0 | N58: 0 | O58: 1868838 | P58: 1644534 | Q58: 5048344.3 | R58: 6918589.3 | S58: 0 | T58: 0 | U58: 3 | V58: 0 | W58: 0 | X58: 0 | Y58: 0 | Z58: 491828 | AA58: 645630 | AB58: 1137458 | AC58: 0 | AD58: 0 | AE58: 98365 | AF58: 551251 | AG58: 649616
A59: Total | F59: =SUM(F8:F55) -> 31928545 | G59: =SUM(G8:G55) -> 3449506.2 | H59: =SUBTOTAL(109,overall_total[overall_aff_sp2_joint]) -> 504240 | I59: =SUBTOTAL(109,overall_total[overall_aff_sp3_joint]) -> 2735911 | J59: =SUM(J8:J55) -> 5248964 | K59: =SUBTOTAL(109,overall_total[overall_aff_sp5_joint]) -> 6902224 | L59: =SUBTOTAL(109,overall_total[overall_aff_total_joint]) -> 12811238 | M59: =SUM(M8:M55) -> 3112787 | N59: =SUBTOTAL(109,overall_total[overall_pin_sp2_joint]) -> 504240 | O59: =SUBTOTAL(109,overall_total[overall_pin_sp3_joint]) -> 2735910 | P59: =SUM(P8:P55) -> 2672383 | Q59: =SUBTOTAL(109,overall_total[overall_pin_sp5_joint]) -> 5543361.3 | R59: =SUBTOTAL(109,overall_total[overall_pin_total_joint]) -> 10849697 | X59: =SUM(X8:X55) -> 2714052 | Y59: =SUBTOTAL(109,overall_total[overall_target_sp2_joint]) -> 504240 | Z59: =SUBTOTAL(109,overall_total[overall_target_sp3_joint]) -> 928780 | AA59: =SUM(AA8:AA55) -> 1081961 | AB59: =SUBTOTAL(109,overall_total[overall_target_total_joint]) -> 4118954 | AC59: =SUM(AC8:AC55) -> 2710465 | AD59: =SUBTOTAL(109,overall_total[overall_targetPr_sp2_joint]) -> 504240 | AE59: =SUBTOTAL(109,overall_total[overall_targetPr_sp3_joint]) -> 534519 | AF59: =SUM(AF8:AF55) -> 976609 | AG59: =SUBTOTAL(109,overall_total[overall_targetPr_total_joint]) -> 3615753
F61: Cells shaded in yellow are aggregated values that are repetative of other records/zones in the table.

Sheet IDPs
A1: UKRAINE 2026 HNRP
A2: Internally-Displaced People Affected, PiN, Target and Prioritized Target by Strategic Priority
A3: =ActivityList!A3 -> Release Date: 13 January 2026
L4: ed | M4: fs | N4: he | O4: pr | P4: wa
A5: Oblast | C5: Analysis Zones | F5: Baseline | G5: # Affected IDPs | L5: # People in Need (Individuals) | Q5: Severity Phase | V5: # Target (Individuals) | AA5: # Prioritized Target (Individuals)
A6: Name (English) | B6: Pcode | C6: Geo Zone | D6: Swath | E6: Code | F6: IDPs | G6: SP1 | H6: SP2 | I6: SP3 | J6: SP4 | K6: Overall | L6: SP1 | M6: SP2 | N6: SP3 | O6: SP4 | P6: Overall | Q6: SP1 | R6: SP2 | S6: SP3 | T6: SP4 | U6: Overall | V6: SP1 | W6: SP2 | X6: SP3 | Y6: SP4 | Z6: Overall | AA6: SP1 | AB6: SP2 | AC6: SP3 | AD6: SP4 | AE6: Overall
A7: ADM1_EN | B7: ADM1_PCODE | C7: geo_zone | D7: swath | E7: UoA_code | F7: idp_all_total_joint | G7: idp_aff_sp1_joint | H7: idp_aff_sp2_joint | I7: idp_aff_sp3_joint | J7: idp_aff_sp4_joint | K7: idp_aff_total_joint | L7: idp_pin_sp1_joint | M7: idp_pin_sp2_joint | N7: idp_pin_sp3_joint | O7: idp_pin_sp4_joint | P7: idp_pin_total_joint | Q7: idp_sev_sp1_joint | R7: idp_sev_sp2_joint | S7: idp_sev_sp3_joint | T7: idp_sev_sp4_joint | U7: idp_sev_total_joint | V7: idp_target_sp1_joint | W7: idp_target_sp2_joint | X7: idp_target_sp3_joint | Y7: idp_target_sp4_joint | Z7: idp_target_total_joint | AA7: idp_targetPr_sp1_joint | AB7: idp_targetPr_sp2_joint | AC7: idp_targetPr_sp3_joint | AD7: idp_targetPr_sp4_joint | AE7: idp_targetPr_total_joint
A8: Vinnytska | B8: UA05 | C8: All oblast | D8: 50+ | E8: UA05_UALL | F8: 124404 | G8: 0 | H8: 0 | I8: 0 | J8: 88646 | K8: 0 | L8: 0 | M8: 0 | N8: 0 | O8: 71599 | Q8: 0 | R8: 0 | S8: 3 | T8: 3 | U8: 3 | V8: 0 | W8: 0 | X8: 0 | Y8: 34095 | Z8: 0 | AA8: 0 | AD8: 34095
A9: Volynska | B9: UA07 | C9: All oblast | D9: 50+ | E9: UA07_UALL | F9: 44950 | G9: 0 | H9: 0 | I9: 0 | J9: 31262 | K9: 0 | L9: 0 | M9: 0 | N9: 0 | O9: 26453 | P9: 0 | Q9: 0 | R9: 0 | S9: 3 | T9: 3 | U9: 3 | V9: 0 | W9: 0 | X9: 0 | Y9: 11761 | Z9: 0 | AA9: 0 | AD9: 11761
A10: Dnipropetrovska | B10: UA12 | C10: 0-20 km | D10: 0-20km | E10: UA12_U20A | F10: 23346 | G10: 23346 | H10: 0 | I10: 0 | J10: 23346 | K10: 0 | L10: 21550 | M10: 0 | N10: 0 | O10: 9161 | P10: 0 | Q10: 5 | R10: 4 | S10: 5 | T10: 5 | U10: 5 | V10: 21550 | W10: 0 | X10: 0 | Y10: 1745 | Z10: 0 | AA10: 21550 | AD10: 1745
A11: Dnipropetrovska | B11: UA12 | C11: 21-50 km | D11: 20-50km | E11: UA12_U50A | F11: 37607 | G11: 37607 | H11: 0 | I11: 0 | J11: 27202 | K11: 0 | L11: 32235 | M11: 0 | N11: 0 | O11: 25648 | P11: 0 | Q11: 4 | R11: 0 | S11: 4 | T11: 4 | U11: 4 | V11: 30643 | W11: 0 | X11: 0 | Y11: 13990 | Z11: 0 | AA11: 30643 | AD11: 13990
A12: Dnipropetrovska | B12: UA12 | C12: 51+ km | D12: 50+ | E12: UA12_U51P | F12: 456409 | G12: 0 | H12: 0 | I12: 0 | J12: 325353 | K12: 0 | L12: 0 | M12: 0 | N12: 0 | O12: 276793 | P12: 0 | Q12: 0 | R12: 0 | S12: 3 | T12: 4 | U12: 4 | V12: 0 | W12: 0 | X12: 0 | Y12: 138397 | Z12: 0 | AA12: 0 | AD12: 138397
A13: Donetska | B13: UA14 | C13: 0-20 km | D13: 0-20km | E13: UA14_U20A | F13: 28205 | G13: 28205 | H13: 0 | I13: 0 | J13: 28205 | K13: 0 | L13: 26237 | M13: 0 | N13: 0 | O13: 12387 | P13: 0 | Q13: 5 | R13: 4 | S13: 5 | T13: 5 | U13: 5 | V13: 26237 | W13: 0 | X13: 0 | Y13: 2252 | Z13: 0 | AA13: 26237 | AD13: 2252
A14: Donetska | B14: UA14 | C14: 21-50 km | D14: 20-50km | E14: UA14_U50A | F14: 10472 | G14: 10472 | H14: 0 | I14: 0 | J14: 7575 | K14: 0 | L14: 9425 | M14: 0 | N14: 0 | O14: 7236 | P14: 0 | Q14: 5 | R14: 0 | S14: 4 | T14: 5 | U14: 5 | V14: 8499 | W14: 0 | X14: 0 | Y14: 4752 | Z14: 0 | AA14: 8499 | AD14: 4752
A15: Zhytomyrska | B15: UA18 | C15: All oblast | D15: 50+ | E15: UA18_UALL | F15: 80718 | G15: 0 | H15: 0 | I15: 0 | J15: 53364 | K15: 0 | L15: 0 | M15: 0 | N15: 0 | O15: 42407 | P15: 0 | Q15: 0 | R15: 0 | S15: 3 | T15: 3 | U15: 3 | V15: 0 | W15: 0 | X15: 0 | Y15: 10107 | Z15: 0 | AA15: 0 | AD15: 2021
A16: Zakarpatska | B16: UA21 | C16: All oblast | D16: 50+ | E16: UA21_UALL | F16: 85221 | G16: 0 | H16: 0 | I16: 0 | J16: 59270 | K16: 0 | L16: 0 | M16: 0 | N16: 0 | O16: 52751 | P16: 0 | Q16: 0 | R16: 0 | S16: 3 | T16: 3 | U16: 3 | V16: 0 | W16: 0 | X16: 0 | Y16: 10702 | Z16: 0 | AA16: 0 | AD16: 2140
A17: Zaporizka | B17: UA23 | C17: 0-20 km | D17: 0-20km | E17: UA23_U20A | F17: 7270 | G17: 7270 | H17: 0 | I17: 0 | J17: 7270 | K17: 0 | L17: 7270 | M17: 0 | N17: 0 | O17: 3159 | P17: 0 | Q17: 5 | R17: 4 | S17: 5 | T17: 5 | U17: 5 | V17: 7270 | W17: 0 | X17: 0 | Y17: 602 | Z17: 0 | AA17: 7270 | AD17: 602
A18: Zaporizka | B18: UA23 | C18: 21-50 km (w/o Zaporizhzhia) | D18: 20-50km | E18: UA23_U50X | F18: 22234 | G18: 22234 | H18: 0 | I18: 0 | J18: 16083 | K18: 0 | L18: 18964 | M18: 0 | N18: 0 | O18: 14621 | P18: 0 | Q18: 4 | R18: 0 | S18: 4 | T18: 4 | U18: 4 | V18: 14223 | W18: 0 | X18: 0 | Y18: 8380 | Z18: 0 | AA18: 14223 | AD18: 8380
A19: Zaporizka | B19: UA23 | C19: 51+ km | D19: 50+ | E19: UA23_U51P | F19: 1450 | G19: 0 | H19: 0 | I19: 0 | J19: 1034 | K19: 0 | L19: 0 | M19: 0 | N19: 0 | O19: 821 | P19: 0 | Q19: 0 | R19: 0 | S19: 3 | T19: 4 | U19: 4 | V19: 0 | W19: 0 | X19: 0 | Y19: 290 | Z19: 0 | AA19: 0 | AD19: 290
A20: Zaporizka | B20: UA23 | C20: Zaporizhzhia city | D20: 20-50km | E20: UA23_UCAP | F20: 131221 | G20: 131221 | H20: 0 | I20: 0 | J20: 94917 | K20: 0 | L20: 107076 | M20: 0 | N20: 0 | O20: 78781 | P20: 0 | Q20: 4 | R20: 0 | S20: 4 | T20: 4 | U20: 4 | V20: 81443 | W20: 0 | X20: 0 | Y20: 46471 | Z20: 0 | AA20: 81443 | AD20: 46471
... A51: Kyiv | B51: UA80 | C51: All oblast | D51: 50+ | E51: UA80_UALL | F51: 359687 | G51: 0 | H51: 0 | I51: 0 | J51: 213148 | K51: 0 | L51: 0 | M51: 0 | N51: 0 | O51: 184996 | P51: 0 | Q51: 0 | R51: 0 | S51: 3 | T51: 3 | U51: 3 | V51: 0 | W51: 0 | X51: 0 | Y51: 42875 | Z51: 0 | AA51: 0 | AD51: 11453
A52: OT | B52: UAOT | C52: OT 0-20 km | D52: 0-20km | E52: UAOT_O20A | F52: 7414 | G52: 7414 | H52: 0 | I52: 495 | J52: 7414 | K52: 7414 | L52: 7414 | M52: 0 | N52: 495 | O52: 7414 | P52: 7414 | Q52: 5 | R52: 0 | S52: 5 | T52: 5 | U52: 5 | V52: 4236 | W52: 0 | X52: 248 | Y52: 1207 | Z52: 4236 | AA52: 4236 | AC52: 248 | AD52: 1207 | AE52: 4236
A53: OT | B53: UAOT | C53: OT 21-50 km | D53: 20-50km | E53: UAOT_O50A | F53: 10647 | G53: 10647 | H53: 0 | I53: 306 | J53: 10647 | K53: 10647 | L53: 10647 | M53: 0 | N53: 306 | O53: 10647 | P53: 10647 | Q53: 4 | R53: 0 | S53: 4 | T53: 4 | U53: 4 | V53: 5182 | W53: 0 | X53: 153 | Y53: 1734 | Z53: 5182 | AA53: 5182 | AC53: 153 | AD53: 1734 | AE53: 5182
A54: OT | B54: UAOT | C54: 51+ km (occupied after 2022) | D54: 50+ | E54: UAOT_O51N | F54: 15802 | G54: 0 | H54: 0 | I54: 314 | J54: 15802 | K54: 15802 | L54: 0 | M54: 0 | N54: 314 | O54: 15802 | P54: 15802 | Q54: 0 | R54: 0 | S54: 4 | T54: 4 | U54: 4 | V54: 0 | W54: 0 | X54: 157 | Y54: 1350 | Z54: 1507 | AA54: 0 | AC54: 157 | AD54: 1350 | AE54: 1507
A55: OT | B55: UAOT | C55: 51+ km (occupied before 2022) | D55: 50+ | E55: UAOT_O51O | F55: 9893 | G55: 0 | H55: 0 | I55: 197 | J55: 9893 | K55: 9893 | L55: 0 | M55: 0 | N55: 197 | O55: 9893 | P55: 9893 | Q55: 0 | R55: 0 | S55: 3 | T55: 3 | U55: 3 | V55: 0 | W55: 0 | X55: 49 | Y55: 1979 | Z55: 2028 | AA55: 0 | AC55: 10 | AD55: 396 | AE55: 406
A56: GCA 0-20 km | B56: UAGC | C56: 0-20 km GCA | D56: 0-20km | E56: UAGC_U20A | F56: 153755 | G56: 153755 | H56: 504240 | I56: 60464 | J56: 153755 | K56: 153755 | L56: 142420 | M56: 504240 | N56: 60464 | O56: 49022 | P56: 142420 | Q56: 0 | R56: 4 | S56: 5 | T56: 0 | U56: 0 | V56: 137706 | W56: 504240 | X56: 30232 | Y56: 9564 | Z56: 137706 | AA56: 137706 | AB56: 504240 | AC56: 30232 | AD56: 9564 | AE56: 137706
A57: GCA 21-50 km | B57: UAGC | C57: 21-50 km GCA | D57: 20-50km | E57: UAGC_U50A | F57: 494663 | G57: 494663 | H57: 0 | I57: 48072 | J57: 357932 | K57: 494663 | L57: 416154 | M57: 0 | N57: 48072 | O57: 319028 | P57: 416154 | Q57: 0 | R57: 0 | S57: 4 | T57: 0 | U57: 0 | V57: 366777 | W57: 0 | X57: 24649 | Y57: 181546 | Z57: 366777 | AA57: 366777 | AC57: 24650 | AD57: 181546 | AE57: 366777
A58: GCA 51+ km | B58: UAGC | C58: 51+ km GCA | D58: 50+ | E58: UAGC_U51P | F58: 2845667 | G58: 0 | H58: 0 | I58: 225711 | J58: 1910493 | K58: 2136204 | L58: 0 | M58: 0 | N58: 225711 | O58: 1644534 | P58: 1870245 | Q58: 0 | R58: 0 | S58: 3 | T58: 0 | U58: 0 | V58: 0 | W58: 0 | X58: 59401 | Y58: 645630 | Z58: 705031 | AA58: 0 | AC58: 11880 | AD58: 551251 | AE58: 563131
A59: Total | F59: =SUM(F8:F55) -> 3537841 | G59: =SUM(G8:G55) -> 666479 | H59: =SUBTOTAL(109,idp_total[idp_aff_sp2_joint]) -> 504240 | I59: =SUBTOTAL(109,idp_total[idp_aff_sp3_joint]) -> 335559 | J59: =SUM(J8:J55) -> 2465936 | K59: =SUBTOTAL(109,idp_total[idp_aff_total_joint]) -> 2828378 | L59: =SUM(L8:L55) -> 576635 | M59: =SUBTOTAL(109,idp_total[idp_pin_sp2_joint]) -> 504240 | N59: =SUBTOTAL(109,idp_total[idp_pin_sp3_joint]) -> 335559 | O59: =SUM(O8:O55) -> 2056340 | P59: =SUBTOTAL(109,idp_total[idp_pin_total_joint]) -> 2472575 | V59: =SUM(V8:V55) -> 513901 | W59: =SUBTOTAL(109,idp_total[idp_target_sp2_joint]) -> 504240 | X59: =SUBTOTAL(109,idp_total[idp_target_sp3_joint]) -> 114889 | Y59: =SUM(Y8:Y55) -> 843010 | Z59: =SUBTOTAL(109,idp_total[idp_target_total_joint]) -> 1222467 | AA59: =SUM(AA8:AA55) -> 513901 | AB59: =SUBTOTAL(109,idp_total[idp_targetPr_sp2_joint]) -> 504240 | AC59: =SUBTOTAL(109,idp_total[idp_targetPr_sp3_joint]) -> 67330 | AD59: =SUM(AD8:AD55) -> 747048 | AE59: =SUBTOTAL(109,idp_total[idp_targetPr_total_joint]) -> 1078945
F61: Cells shaded in yellow are aggregated values that are repetative of other records/zones in the table.

Sheet WAND
A1: UKRAINE 2026 HNRP
A2: War-Affected Non-Displaced (WAND) People Affected, PiN, Target and Prioritized Target by Strategic Priority
A3: =ActivityList!A3 -> Release Date: 13 January 2026
M4: ed | N4: fs | O4: he | P4: pr | Q4: sn | R4: wa
A5: Oblast | C5: Analysis Zones | F5: Baseline | G5: # Affected WAND | M5: # People in Need (Individuals) | S5: Severity Phase | X5: # Target (Individuals) | AC5: # Prioritized Target (Individuals)
A6: Name (English) | B6: Pcode | C6: Geo Zone | D6: Swath | E6: Code | F6: Non-displaced People | G6: SP1 | H6: SP2 | I6: SP3 | J6: SP4 | K6: WAND 50+ | L6: Overall | M6: SP1 | N6: SP2 | O6: SP3 | P6: SP4 | Q6: WAND 50+ | R6: Overall | S6: SP1 | T6: SP2 | U6: SP3 | V6: SP4 | W6: Overall | X6: SP1 | Y6: SP2 | Z6: SP3 | AA6: SP4 | AB6: Overall | AC6: SP1 | AD6: SP2 | AE6: SP3 | AF6: SP4 | AG6: Overall
A7: ADM1_EN | B7: ADM1_PCODE | C7: geo_zone | D7: swath | E7: UoA_code | F7: ndp_all_total_joint | G7: ndp_aff_sp1_joint | H7: ndp_aff_sp2_joint | I7: ndp_aff_sp3_joint | J7: ndp_aff_sp4_joint | K7: ndp_aff_sp5_joint | L7: ndp_aff_total_joint | M7: ndp_pin_sp1_joint | N7: ndp_pin_sp2_joint | O7: ndp_pin_sp3_joint | P7: ndp_pin_sp4_joint | Q7: ndp_pin_sp5_joint | R7: ndp_pin_total_joint | S7: ndp_sev_sp1_joint | T7: ndp_sev_sp2_joint | U7: ndp_sev_sp3_joint | V7: ndp_sev_sp4_joint | W7: ndp_sev_total_joint | X7: ndp_target_sp1_joint | Y7: ndp_target_sp2_joint | Z7: ndp_target_sp3_joint | AA7: ndp_target_sp4_joint | AB7: ndp_target_total_joint | AC7: ndp_targetPr_sp1_joint | AD7: ndp_targetPr_sp2_joint | AE7: ndp_targetPr_sp3_joint | AF7: ndp_targetPr_sp4_joint | AG7: ndp_targetPr_total_joint
A8: Vinnytska | B8: UA05 | C8: All oblast | D8: 50+ | E8: UA05_UALL | F8: 1222241 | G8: 0 | H8: 0 | I8: 0 | J8: 0 | K8: 0 | L8: 0 | M8: 0 | N8: 0 | O8: 0 | P8: 0 | Q8: 0 | R8: 0 | S8: 0 | T8: - | U8: 3 | V8: 0 | W8: 3 | X8: 0 | Y8: 0 | Z8: 0 | AA8: 0 | AB8: 0 | AC8: 0 | AF8: 0
A9: Volynska | B9: UA07 | C9: All oblast | D9: 50+ | E9: UA07_UALL | F9: 870618 | G9: 0 | H9: 0 | I9: 0 | J9: 0 | K9: 0 | L9: 0 | M9: 0 | N9: 0 | O9: 0 | P9: 0 | Q9: 0 | R9: 0 | S9: 0 | T9: - | U9: 3 | V9: 0 | W9: 3 | X9: 0 | Y9: 0 | Z9: 0 | AA9: 0 | AB9: 0 | AC9: 0 | AF9: 0
A10: Dnipropetrovska | B10: UA12 | C10: 0-20 km | D10: 0-20km | E10: UA12_U20A | F10: 204922 | G10: 204922 | H10: 0 | I10: 0 | J10: 204922 | K10: 0 | L10: 0 | M10: 189159 | N10: 0 | O10: 0 | P10: 80411 | Q10: 0 | R10: 0 | S10: 5 | T10: - | U10: 5 | V10: 5 | W10: 5 | X10: 189159 | Y10: 0 | Z10: 0 | AA10: 38291 | AB10: 0 | AC10: 189159 | AF10: 38291
A11: Dnipropetrovska | B11: UA12 | C11: 21-50 km | D11: 20-50km | E11: UA12_U50A | F11: 127043 | G11: 61335.748 | H11: 0 | I11: 0 | J11: 61336 | K11: 0 | L11: 0 | M11: 49977 | N11: 0 | O11: 0 | P11: 22556 | Q11: 0 | R11: 0 | S11: 4 | T11: - | U11: 4 | V11: 4 | W11: 4 | X11: 49977 | Y11: 0 | Z11: 0 | AA11: 22556 | AB11: 0 | AC11: 49977 | AF11: 22556
A12: Dnipropetrovska | B12: UA12 | C12: 51+ km | D12: 50+ | E12: UA12_U51P | F12: 2329387 | G12: 0 | H12: 0 | I12: 0 | J12: 0 | K12: 0 | L12: 0 | M12: 0 | N12: 0 | O12: 0 | P12: 0 | Q12: 0 | R12: 0 | S12: 0 | T12: - | U12: 3 | V12: 0 | W12: 3 | X12: 0 | Y12: 0 | Z12: 0 | AA12: 0 | AB12: 0 | AC12: 0 | AF12: 0
A13: Donetska | B13: UA14 | C13: 0-20 km | D13: 0-20km | E13: UA14_U20A | F13: 152005 | G13: 152005 | H13: 0 | I13: 0 | J13: 152005 | K13: 0 | L13: 0 | M13: 141400 | N13: 0 | O13: 0 | P13: 66756 | Q13: 0 | R13: 0 | S13: 5 | T13: - | U13: 5 | V13: 5 | W13: 5 | X13: 141400 | Y13: 0 | Z13: 0 | AA13: 30344 | AB13: 0 | AC13: 141400 | AF13: 30344
A14: Donetska | B14: UA14 | C14: 21-50 km | D14: 20-50km | E14: UA14_U50A | F14: 50984 | G14: 35228.32 | H14: 0 | I14: 0 | J14: 35228 | K14: 0 | L14: 0 | M14: 28591 | N14: 0 | O14: 0 | P14: 10783 | Q14: 0 | R14: 0 | S14: 5 | T14: - | U14: 4 | V14: 5 | W14: 5 | X14: 28591 | Y14: 0 | Z14: 0 | AA14: 10783 | AB14: 0 | AC14: 28591 | AF14: 10783
A15: Zhytomyrska | B15: UA18 | C15: All oblast | D15: 50+ | E15: UA18_UALL | F15: 1000709 | G15: 0 | H15: 0 | I15: 0 | J15: 0 | K15: 0 | L15: 0 | M15: 0 | N15: 0 | O15: 0 | P15: 0 | Q15: 0 | R15: 0 | S15: 0 | T15: - | U15: 3 | V15: 0 | W15: 3 | X15: 0 | Y15: 0 | Z15: 0 | AA15: 0 | AB15: 0 | AC15: 0 | AF15: 0
A16: Zakarpatska | B16: UA21 | C16: All oblast | D16: 50+ | E16: UA21_UALL | F16: 756167 | G16: 0 | H16: 0 | I16: 0 | J16: 0 | K16: 0 | L16: 0 | M16: 0 | N16: 0 | O16: 0 | P16: 0 | Q16: 0 | R16: 0 | S16: 0 | T16: - | U16: 3 | V16: 0 | W16: 3 | X16: 0 | Y16: 0 | Z16: 0 | AA16: 0 | AB16: 0 | AC16: 0 | AF16: 0
A17: Zaporizka | B17: UA23 | C17: 0-20 km | D17: 0-20km | E17: UA23_U20A | F17: 50450 | G17: 50450 | H17: 0 | I17: 0 | J17: 50450 | K17: 0 | L17: 0 | M17: 50450 | N17: 0 | O17: 0 | P17: 21919 | Q17: 0 | R17: 0 | S17: 5 | T17: - | U17: 5 | V17: 5 | W17: 5 | X17: 50450 | Y17: 0 | Z17: 0 | AA17: 10438 | AB17: 0 | AC17: 50450 | AF17: 10438
A18: Zaporizka | B18: UA23 | C18: 21-50 km (w/o Zaporizhzhia) | D18: 20-50km | E18: UA23_U50X | F18: 50550 | G18: 20057.226 | H18: 0 | I18: 0 | J18: 20057 | K18: 0 | L18: 0 | M18: 18052 | N18: 0 | O18: 0 | P18: 6238 | Q18: 0 | R18: 0 | S18: 4 | T18: - | U18: 4 | V18: 4 | W18: 4 | X18: 12034 | Y18: 0 | Z18: 0 | AA18: 6238 | AB18: 0 | AC18: 12034 | AF18: 6238
A19: Zaporizka | B19: UA23 | C19: 51+ km | D19: 50+ | E19: UA23_U51P | F19: 3062 | G19: 0 | H19: 0 | I19: 0 | J19: 0 | K19: 0 | L19: 0 | M19: 0 | N19: 0 | O19: 0 | P19: 0 | Q19: 0 | R19: 0 | S19: 0 | T19: - | U19: 3 | V19: 0 | W19: 3 | X19: 0 | Y19: 0 | Z19: 0 | AA19: 0 | AB19: 0 | AC19: 0 | AF19: 0
... A51: Kyiv | B51: UA80 | C51: All oblast | D51: 50+ | E51: UA80_UALL | F51: 3034506 | G51: 0 | H51: 0 | I51: 0 | J51: 0 | K51: 0 | L51: 0 | M51: 0 | N51: 0 | O51: 0 | P51: 0 | Q51: 0 | R51: 0 | S51: 0 | T51: - | U51: 3 | V51: 0 | W51: 3 | X51: 0 | Y51: 0 | Z51: 0 | AA51: 0 | AB51: 0 | AC51: 0 | AF51: 0
A52: OT | B52: UAOT | C52: OT 0-20 km | D52: 0-20km | E52: UAOT_O20A | F52: 224914 | G52: 224914 | H52: 0 | I52: 15029 | J52: 224914 | K52: 0 | L52: 224914 | M52: 224914 | N52: 0 | O52: 15029 | P52: 0 | Q52: 0 | R52: 224914 | S52: 5 | T52: - | U52: 5 | V52: 5 | W52: 5 | X52: 128460 | Y52: 0 | Z52: 7514 | AA52: 0 | AB52: 128460 | AC52: 128460 | AE52: 7514 | AF52: 0 | AG52: 128460
A53: OT | B53: UAOT | C53: OT 21-50 km | D53: 20-50km | E53: UAOT_O50A | F53: 225310 | G53: 225310 | H53: 0 | I53: 6485 | J53: 225310 | K53: 0 | L53: 225310 | M53: 225310 | N53: 0 | O53: 6485 | P53: 0 | Q53: 0 | R53: 225310 | S53: 4 | T53: - | U53: 4 | V53: 4 | W53: 4 | X53: 151946 | Y53: 0 | Z53: 3243 | AA53: 0 | AB53: 155189 | AC53: 151946 | AE53: 3243 | AF53: 0 | AG53: 155189
A54: OT | B54: UAOT | C54: 51+ km (occupied after 2022) | D54: 50+ | E54: UAOT_O51N | F54: 304427 | G54: 0 | H54: 0 | I54: 6055 | J54: 0 | K54: 304427 | L54: 304427 | M54: 0 | N54: 0 | O54: 6055 | P54: 0 | Q54: 304427 | R54: 304427 | S54: 0 | T54: - | U54: 4 | V54: 0 | W54: 4 | X54: 0 | Y54: 0 | Z54: 3028 | AA54: 0 | AB54: 3028 | AC54: 0 | AE54: 3028 | AF54: 0 | AG54: 3028
A55: OT | B55: UAOT | C55: 51+ km (occupied before 2022) | D55: 50+ | E55: UAOT_O51O | F55: 190590 | G55: 0 | H55: 0 | I55: 3791 | J55: 0 | K55: 190590 | L55: 190590 | M55: 0 | N55: 0 | O55: 3790 | P55: 0 | Q55: 190590 | R55: 190590 | S55: 0 | T55: - | U55: 3 | V55: 0 | W55: 3 | X55: 0 | Y55: 0 | Z55: 948 | AA55: 0 | AB55: 948 | AC55: 0 | AE55: 189 | AF55: 0 | AG55: 189
A56: GCA 0-20 km | B56: UAGC | C56: 0-20 km GCA | D56: 0-20km | E56: UAGC_U20A | F56: 1104543 | G56: 1104543 | H56: 0 | I56: 428256 | J56: 1104543 | K56: 0 | L56: 1104543 | M56: 1004983 | N56: 0 | O56: 428256 | P56: 328817 | Q56: 0 | R56: 1004983 | S56: 0 | T56: - | U56: 5 | V56: - | W56: - | X56: 982830 | Y56: 0 | Z56: 214128 | AA56: 134864 | AB56: 982830 | AC56: 982830 | AE56: 214128 | AF56: 134864 | AG56: 982830
A57: GCA 21-50 km | B57: UAGC | C57: 21-50 km GCA | D57: 20-50km | E57: UAGC_U50A | F57: 2459334 | G57: 1228260.2 | H57: 0 | I57: 297609 | J57: 1228261 | K57: 0 | L57: 1525869.2 | M57: 1080945 | N57: 0 | O57: 297609 | P57: 287226 | Q57: 0 | R57: 1378554 | S57: 0 | T57: - | U57: 4 | V57: - | W57: - | X57: 936915 | Y57: 0 | Z57: 152603 | AA57: 104087 | AB57: 1193605 | AC57: 933328 | AE57: 152602 | AF57: 94697 | AG57: 1180627
A58: GCA 51+ km | B58: UAGC | C58: 51+ km GCA | D58: 50+ | E58: UAGC_U51P | F58: 23881586 | G58: 0 | H58: 0 | I58: 1643127 | J58: 0 | K58: 6407207 | L58: 6407207 | M58: 0 | N58: 0 | O58: 1643127 | P58: 0 | Q58: 5048344.3 | R58: 5048344.3 | S58: 0 | T58: - | U58: 3 | V58: - | W58: - | X58: 0 | Y58: 0 | Z58: 432427 | AA58: 0 | AB58: 432427 | AC58: 0 | AE58: 86485 | AF58: 0 | AG58: 86485
A59: Total | F59: =SUM(F8:F55) -> 28390704 | G59: =SUM(G8:G55) -> 2783027.2 | H59: =SUBTOTAL(109,wand_total[ndp_aff_sp2_joint]) -> 0 | I59: =SUBTOTAL(109,wand_total[ndp_aff_sp3_joint]) -> 2400352 | J59: =SUM(J8:J55) -> 2783028 | K59: =SUBTOTAL(109,wand_total[ndp_aff_sp5_joint]) -> 6902224 | L59: =SUBTOTAL(109,wand_total[ndp_aff_total_joint]) -> 9982860.1 | M59: =SUM(M8:M55) -> 2536152 | N59: =SUBTOTAL(109,wand_total[ndp_pin_sp2_joint]) -> 0 | O59: =SUBTOTAL(109,wand_total[ndp_pin_sp3_joint]) -> 2400351 | P59: =SUM(P8:P55) -> 616043 | Q59: =SUBTOTAL(109,wand_total[ndp_pin_sp5_joint]) -> 5543361.3 | R59: =SUBTOTAL(109,wand_total[ndp_pin_total_joint]) -> 8377122.3 | X59: =SUM(X8:X55) -> 2200151 | Y59: =SUBTOTAL(109,wand_total[ndp_target_sp2_joint]) -> 0 | Z59: =SUBTOTAL(109,wand_total[ndp_target_sp3_joint]) -> 813891 | AA59: =SUM(AA8:AA55) -> 238951 | AB59: =SUBTOTAL(109,wand_total[ndp_target_total_joint]) -> 2896487 | AC59: =SUM(AC8:AC55) -> 2196564 | AD59: =SUBTOTAL(109,wand_total[ndp_targetPr_sp2_joint]) -> 0 | AE59: =SUBTOTAL(109,wand_total[ndp_targetPr_sp3_joint]) -> 467189 | AF59: =SUM(AF8:AF55) -> 229561 | AG59: =SUBTOTAL(109,wand_total[ndp_targetPr_total_joint]) -> 2536808
F61: Cells shaded in yellow are aggregated values that are repetative of other records/zones in the table.

Sheet SP#1 Overall
A1: UKRAINE 2026 HNRP
A2: SP1: Overall | People Affected, PiN, Target and Prioritized Target by Cluster
A3: =ActivityList!A3 -> Release Date: 13 January 2026 | I3: ="sp1_overall_pin_"&I4 -> sp1_overall_pin_ed | J3: ="sp1_overall_pin_"&J4 -> sp1_overall_pin_fs | K3: ="sp1_overall_pin_"&K4 -> sp1_overall_pin_he | L3: ="sp1_overall_pin_"&L4 -> sp1_overall_pin_pr | M3: ="sp1_overall_pin_"&M4 -> sp1_overall_pin_sn | N3: ="sp1_overall_pin_"&N4 -> sp1_overall_pin_wa | O3: ="sp1_overall_pin_"&O4 -> sp1_overall_pin_gp | P3: ="sp1_overall_pin_"&P4 -> sp1_overall_pin_cp | Q3: ="sp1_overall_pin_"&Q4 -> sp1_overall_pin_gb
I4: ed | J4: fs | K4: he | L4: pr | M4: sn | N4: wa | O4: gp | P4: cp | Q4: gb
A5: Oblast | C5: Analysis Zones | F5: # Affected People | I5: # People in Need (Individuals) | O5: Protection AoRs | R5: FSL AoRs | T5: Joint PiN | U5: Cluster Severity Phase | AA5: Protection AoRs | AD5: FSL AoRs | AF5: Intersectoral | AG5: # Target (Individuals) | AM5: Protection AoRs | AP5: FSL AoRs | AS5: Total | AT5: # Prioritized Target (Individuals) | AZ5: Protection AoRs | BC5: FSL AoRs | BF5: Total
A6: Name (English) | B6: Pcode | C6: Geographical Zone | D6: Swath | E6: Code | F6: IDP | G6: Non-Displ. | H6: Overall | I6: ED | J6: FL | K6: HE | L6: PR | M6: SN | N6: WA | O6: GP | P6: CP | Q6: GB | R6: FS | S6: LI | U6: ED | V6: FL | W6: HE | X6: PR | Y6: SN | Z6: WA | AA6: GP | AB6: CP | AC6: GB | AD6: FS | AE6: LI | AF6: Severity | AG6: ED | AH6: FL | AI6: HE | AJ6: PR | AK6: SN | AL6: WA | AM6: GP | AN6: CP | AO6: GB | AP6: FS | AQ6: LI | AR6: CW | AT6: ED | AU6: FL | AV6: HE | AW6: PR | AX6: SN | AY6: WA | AZ6: GP | BA6: CP | BB6: GB | BC6: FS | BD6: LI | BE6: CW
A7: ADM1_EN | B7: ADM1_PCODE | C7: geo_zone | D7: swath | E7: UoA_code | F7: idp_aff_sp1 | G7: ndp_aff_sp1 | H7: overall_aff_sp1 | I7: sp1_overall_pin_ed | J7: sp1_overall_pin_fl | K7: sp1_overall_pin_he | L7: sp1_overall_pin_pr | M7: sp1_overall_pin_sn | N7: sp1_overall_pin_wa | O7: sp1_overall_pin_gp | P7: sp1_overall_pin_cp | Q7: sp1_overall_pin_gb | R7: sp1_overall_pin_fs | S7: sp1_overall_pin_li | T7: sp1_overall_pin_adopted | U7: sp1_overall_sev_ed | V7: sp1_overall_sev_fl | W7: sp1_overall_sev_he | X7: sp1_overall_sev_pr | Y7: sp1_overall_sev_sn | Z7: sp1_overall_sev_wa | AA7: sp1_overall_sev_gp | AB7: sp1_overall_sev_cp | AC7: sp1_overall_sev_gb | AD7: sp1_overall_sev_fs | AE7: sp1_overall_sev_li | AF7: sp1_overall_sev_adopted | AG7: sp1_overall_target_ed | AH7: sp1_overall_target_fl | AI7: sp1_overall_target_he | AJ7: sp1_overall_target_pr | AK7: sp1_overall_target_sn | AL7: sp1_overall_target_wa | AM7: sp1_overall_target_gp | AN7: sp1_overall_target_cp | AO7: sp1_overall_target_gb | AP7: sp1_overall_target_fs | AQ7: sp1_overall_target_li | AR7: sp1_overall_target_cw | AS7: sp1_overall_target_joint | AT7: sp1_overall_targetPr_ed | AU7: sp1_overall_targetPr_fl | AV7: sp1_overall_targetPr_he | AW7: sp1_overall_targetPr_pr | AX7: sp1_overall_targetPr_sn | AY7: sp1_overall_targetPr_wa | AZ7: sp1_overall_targetPr_gp | BA7: sp1_overall_targetPr_cp | BB7: sp1_overall_targetPr_gb | BC7: sp1_overall_targetPr_fs | BD7: sp1_overall_targetPr_li | BE7: sp1_overall_targetPr_cw | BF7: sp1_overall_targetPr_joint
A8: Vinnytska | B8: UA05 | C8: All oblast | D8: 50+ | E8: UA05_UALL | F8: 0 | G8: 0 | I8: =idp_SP1[[#This Row],[sp1_idp_pin_ed]]+ndp_SP1[[#This Row],[sp1_ndp_pin_ed]] -> 0 | J8: =idp_SP1[[#This Row],[sp1_idp_pin_fl]]+ndp_SP1[[#This Row],[sp1_ndp_pin_fl]] -> 0 | K8: =idp_SP1[[#This Row],[sp1_idp_pin_he]]+ndp_SP1[[#This Row],[sp1_ndp_pin_he]] -> 0 | L8: =idp_SP1[[#This Row],[sp1_idp_pin_pr]]+ndp_SP1[[#This Row],[sp1_ndp_pin_pr]] -> 0 | M8: =idp_SP1[[#This Row],[sp1_idp_pin_sn]]+ndp_SP1[[#This Row],[sp1_ndp_pin_sn]] -> 0 | N8: =idp_SP1[[#This Row],[sp1_idp_pin_wa]]+ndp_SP1[[#This Row],[sp1_ndp_pin_wa]] -> 0 | O8: =idp_SP1[[#This Row],[sp1_idp_pin_gp]]+ndp_SP1[[#This Row],[sp1_ndp_pin_gp]] -> 0 | P8: =idp_SP1[[#This Row],[sp1_idp_pin_cp]]+ndp_SP1[[#This Row],[sp1_ndp_pin_cp]] -> 0 | Q8: =idp_SP1[[#This Row],[sp1_idp_pin_gb]]+ndp_SP1[[#This Row],[sp1_ndp_pin_gb]] -> 0 | R8: =idp_SP1[[#This Row],[sp1_idp_pin_fs]]+ndp_SP1[[#This Row],[sp1_ndp_pin_fs]] -> 0 | S8: =idp_SP1[[#This Row],[sp1_idp_pin_li]]+ndp_SP1[[#This Row],[sp1_ndp_pin_li]] -> 0 | T8: =idp_SP1[[#This Row],[sp1_idp_pin_adopted]]+ndp_SP1[[#This Row],[sp1_ndp_pin_adopted]] -> 0 | X8: =MAX(idp_SP1[[#This Row],[sp1_idp_sev_pr]],ndp_SP1[[#This Row],[sp1_ndp_sev_pr]]) -> 0 | Y8: 0 | AG8: =idp_SP1[[#This Row],[sp1_idp_target_ed]]+ndp_SP1[[#This Row],[sp1_ndp_target_ed]] -> 0 | AH8: =idp_SP1[[#This Row],[sp1_idp_target_fl]]+ndp_SP1[[#This Row],[sp1_ndp_target_fl]] -> 0 | AI8: =idp_SP1[[#This Row],[sp1_idp_target_he]]+ndp_SP1[[#This Row],[sp1_ndp_target_he]] -> 0 | AJ8: =idp_SP1[[#This Row],[sp1_idp_target_pr]]+ndp_SP1[[#This Row],[sp1_ndp_target_pr]] -> 0 | AK8: =idp_SP1[[#This Row],[sp1_idp_target_sn]]+ndp_SP1[[#This Row],[sp1_ndp_target_sn]] -> 0 | AL8: =idp_SP1[[#This Row],[sp1_idp_target_wa]]+ndp_SP1[[#This Row],[sp1_ndp_target_wa]] -> 0 | AM8: =idp_SP1[[#This Row],[sp1_idp_target_gp]]+ndp_SP1[[#This Row],[sp1_ndp_target_gp]] -> 0 | AN8: =idp_SP1[[#This Row],[sp1_idp_target_cp]]+ndp_SP1[[#This Row],[sp1_ndp_target_cp]] -> 0 | AO8: =idp_SP1[[#This Row],[sp1_idp_target_gb]]+ndp_SP1[[#This Row],[sp1_ndp_target_gb]] -> 0 | AP8: =idp_SP1[[#This Row],[sp1_idp_target_fs]]+ndp_SP1[[#This Row],[sp1_ndp_target_fs]] -> 0 | AQ8: =idp_SP1[[#This Row],[sp1_idp_target_li]]+ndp_SP1[[#This Row],[sp1_ndp_target_li]] -> 0 | AR8: =idp_SP1[[#This Row],[sp1_idp_target_cw]]+ndp_SP1[[#This Row],[sp1_ndp_target_cw]] -> 0 | AS8: =idp_SP1[[#This Row],[sp1_idp_target_joint]]+ndp_SP1[[#This Row],[sp1_ndp_target_joint]] -> 0 | AT8: 0 | AU8: 0 | AV8: 0 | AW8: 0 | AX8: 0 | AY8: 0 | AZ8: 0 | BA8: 0 | BB8: 0 | BC8: 0 | BD8: 0 | BE8: 0 | BF8: 0
A9: Volynska | B9: UA07 | C9: All oblast | D9: 50+ | E9: UA07_UALL | F9: 0 | G9: 0 | I9: =idp_SP1[[#This Row],[sp1_idp_pin_ed]]+ndp_SP1[[#This Row],[sp1_ndp_pin_ed]] -> 0 | J9: =idp_SP1[[#This Row],[sp1_idp_pin_fl]]+ndp_SP1[[#This Row],[sp1_ndp_pin_fl]] -> 0 | K9: =idp_SP1[[#This Row],[sp1_idp_pin_he]]+ndp_SP1[[#This Row],[sp1_ndp_pin_he]] -> 0 | L9: =idp_SP1[[#This Row],[sp1_idp_pin_pr]]+ndp_SP1[[#This Row],[sp1_ndp_pin_pr]] -> 0 | M9: =idp_SP1[[#This Row],[sp1_idp_pin_sn]]+ndp_SP1[[#This Row],[sp1_ndp_pin_sn]] -> 0 | N9: =idp_SP1[[#This Row],[sp1_idp_pin_wa]]+ndp_SP1[[#This Row],[sp1_ndp_pin_wa]] -> 0 | O9: =idp_SP1[[#This Row],[sp1_idp_pin_gp]]+ndp_SP1[[#This Row],[sp1_ndp_pin_gp]] -> 0 | P9: =idp_SP1[[#This Row],[sp1_idp_pin_cp]]+ndp_SP1[[#This Row],[sp1_ndp_pin_cp]] -> 0 | Q9: =idp_SP1[[#This Row],[sp1_idp_pin_gb]]+ndp_SP1[[#This Row],[sp1_ndp_pin_gb]] -> 0 | R9: =idp_SP1[[#This Row],[sp1_idp_pin_fs]]+ndp_SP1[[#This Row],[sp1_ndp_pin_fs]] -> 0 | S9: =idp_SP1[[#This Row],[sp1_idp_pin_li]]+ndp_SP1[[#This Row],[sp1_ndp_pin_li]] -> 0 | T9: =idp_SP1[[#This Row],[sp1_idp_pin_adopted]]+ndp_SP1[[#This Row],[sp1_ndp_pin_adopted]] -> 0 | X9: =MAX(idp_SP1[[#This Row],[sp1_idp_sev_pr]],ndp_SP1[[#This Row],[sp1_ndp_sev_pr]]) -> 0 | Y9: 0 | AG9: =idp_SP1[[#This Row],[sp1_idp_target_ed]]+ndp_SP1[[#This Row],[sp1_ndp_target_ed]] -> 0 | AH9: =idp_SP1[[#This Row],[sp1_idp_target_fl]]+ndp_SP1[[#This Row],[sp1_ndp_target_fl]] -> 0 | AI9: =idp_SP1[[#This Row],[sp1_idp_target_he]]+ndp_SP1[[#This Row],[sp1_ndp_target_he]] -> 0 | AJ9: =idp_SP1[[#This Row],[sp1_idp_target_pr]]+ndp_SP1[[#This Row],[sp1_ndp_target_pr]] -> 0 | AK9: =idp_SP1[[#This Row],[sp1_idp_target_sn]]+ndp_SP1[[#This Row],[sp1_ndp_target_sn]] -> 0 | AL9: =idp_SP1[[#This Row],[sp1_idp_target_wa]]+ndp_SP1[[#This Row],[sp1_ndp_target_wa]] -> 0 | AM9: =idp_SP1[[#This Row],[sp1_idp_target_gp]]+ndp_SP1[[#This Row],[sp1_ndp_target_gp]] -> 0 | AN9: =idp_SP1[[#This Row],[sp1_idp_target_cp]]+ndp_SP1[[#This Row],[sp1_ndp_target_cp]] -> 0 | AO9: =idp_SP1[[#This Row],[sp1_idp_target_gb]]+ndp_SP1[[#This Row],[sp1_ndp_target_gb]] -> 0 | AP9: =idp_SP1[[#This Row],[sp1_idp_target_fs]]+ndp_SP1[[#This Row],[sp1_ndp_target_fs]] -> 0 | AQ9: =idp_SP1[[#This Row],[sp1_idp_target_li]]+ndp_SP1[[#This Row],[sp1_ndp_target_li]] -> 0 | AR9: =idp_SP1[[#This Row],[sp1_idp_target_cw]]+ndp_SP1[[#This Row],[sp1_ndp_target_cw]] -> 0 | AS9: =idp_SP1[[#This Row],[sp1_idp_target_joint]]+ndp_SP1[[#This Row],[sp1_ndp_target_joint]] -> 0 | AT9: 0 | AU9: 0 | AV9: 0 | AW9: 0 | AX9: 0 | AY9: 0 | AZ9: 0 | BA9: 0 | BB9: 0 | BC9: 0 | BD9: 0 | BE9: 0 | BF9: 0
A10: Dnipropetrovska | B10: UA12 | C10: 0-20 km | D10: 0-20km | E10: UA12_U20A | F10: 23346 | G10: 204922 | H10: 228268 | I10: =idp_SP1[[#This Row],[sp1_idp_pin_ed]]+ndp_SP1[[#This Row],[sp1_ndp_pin_ed]] -> 14307 | J10: =idp_SP1[[#This Row],[sp1_idp_pin_fl]]+ndp_SP1[[#This Row],[sp1_ndp_pin_fl]] -> 89572 | K10: =idp_SP1[[#This Row],[sp1_idp_pin_he]]+ndp_SP1[[#This Row],[sp1_ndp_pin_he]] -> 177085 | L10: =idp_SP1[[#This Row],[sp1_idp_pin_pr]]+ndp_SP1[[#This Row],[sp1_ndp_pin_pr]] -> 161529 | M10: =idp_SP1[[#This Row],[sp1_idp_pin_sn]]+ndp_SP1[[#This Row],[sp1_ndp_pin_sn]] -> 190223 | N10: =idp_SP1[[#This Row],[sp1_idp_pin_wa]]+ndp_SP1[[#This Row],[sp1_ndp_pin_wa]] -> 210709 | O10: =idp_SP1[[#This Row],[sp1_idp_pin_gp]]+ndp_SP1[[#This Row],[sp1_ndp_pin_gp]] -> 161529 | P10: =idp_SP1[[#This Row],[sp1_idp_pin_cp]]+ndp_SP1[[#This Row],[sp1_ndp_pin_cp]] -> 61777 | Q10: =idp_SP1[[#This Row],[sp1_idp_pin_gb]]+ndp_SP1[[#This Row],[sp1_ndp_pin_gb]] -> 115047 | R10: =idp_SP1[[#This Row],[sp1_idp_pin_fs]]+ndp_SP1[[#This Row],[sp1_ndp_pin_fs]] -> 89572 | S10: =idp_SP1[[#This Row],[sp1_idp_pin_li]]+ndp_SP1[[#This Row],[sp1_ndp_pin_li]] -> 0 | T10: =idp_SP1[[#This Row],[sp1_idp_pin_adopted]]+ndp_SP1[[#This Row],[sp1_ndp_pin_adopted]] -> 210709 | U10: 5 | V10: 4 | W10: 4 | X10: =MAX(idp_SP1[[#This Row],[sp1_idp_sev_pr]],ndp_SP1[[#This Row],[sp1_ndp_sev_pr]]) -> 5 | Y10: 5 | Z10: 5 | AA10: 5 | AB10: 5 | AC10: 5 | AD10: 4 | AE10: 4 | AF10: 5 | AG10: =idp_SP1[[#This Row],[sp1_idp_target_ed]]+ndp_SP1[[#This Row],[sp1_ndp_target_ed]] -> 12877 | AH10: =idp_SP1[[#This Row],[sp1_idp_target_fl]]+ndp_SP1[[#This Row],[sp1_ndp_target_fl]] -> 89572 | AI10: =idp_SP1[[#This Row],[sp1_idp_target_he]]+ndp_SP1[[#This Row],[sp1_ndp_target_he]] -> 100563 | AJ10: =idp_SP1[[#This Row],[sp1_idp_target_pr]]+ndp_SP1[[#This Row],[sp1_ndp_target_pr]] -> 64939 | AK10: =idp_SP1[[#This Row],[sp1_idp_target_sn]]+ndp_SP1[[#This Row],[sp1_ndp_target_sn]] -> 128305 | AL10: =idp_SP1[[#This Row],[sp1_idp_target_wa]]+ndp_SP1[[#This Row],[sp1_ndp_target_wa]] -> 210709 | AM10: =idp_SP1[[#This Row],[sp1_idp_target_gp]]+ndp_SP1[[#This Row],[sp1_ndp_target_gp]] -> 64939 | AN10: =idp_SP1[[#This Row],[sp1_idp_target_cp]]+ndp_SP1[[#This Row],[sp1_ndp_target_cp]] -> 51951 | AO10: =idp_SP1[[#This Row],[sp1_idp_target_gb]]+ndp_SP1[[#This Row],[sp1_ndp_target_gb]] -> 5752 | AP10: =idp_SP1[[#This Row],[sp1_idp_target_fs]]+ndp_SP1[[#This Row],[sp1_ndp_target_fs]] -> 89572 | AQ10: =idp_SP1[[#This Row],[sp1_idp_target_li]]+ndp_SP1[[#This Row],[sp1_ndp_target_li]] -> 0 | AR10: =idp_SP1[[#This Row],[sp1_idp_target_cw]]+ndp_SP1[[#This Row],[sp1_ndp_target_cw]] -> 143399 | AS10: =idp_SP1[[#This Row],[sp1_idp_target_joint]]+ndp_SP1[[#This Row],[sp1_ndp_target_joint]] -> 210709 | AT10: 12877 | AU10: 89572 | AV10: 100563 | AW10: 64939 | AX10: 128305 | AY10: 210709 | AZ10: 64939 | BA10: 51951 | BB10: 5752 | BC10: 89572 | BD10: 0 | BE10: 143399 | BF10: 210709
A11: Dnipropetrovska | B11: UA12 | C11: 21-50 km | D11: 20-50km | E11: UA12_U50A | F11: 37607 | G11: 61335.748 | H11: 98942.748 | I11: =idp_SP1[[#This Row],[sp1_idp_pin_ed]]+ndp_SP1[[#This Row],[sp1_ndp_pin_ed]] -> 11127 | J11: =idp_SP1[[#This Row],[sp1_idp_pin_fl]]+ndp_SP1[[#This Row],[sp1_ndp_pin_fl]] -> 36386 | K11: =idp_SP1[[#This Row],[sp1_idp_pin_he]]+ndp_SP1[[#This Row],[sp1_ndp_pin_he]] -> 76758 | L11: =idp_SP1[[#This Row],[sp1_idp_pin_pr]]+ndp_SP1[[#This Row],[sp1_ndp_pin_pr]] -> 70901 | M11: =idp_SP1[[#This Row],[sp1_idp_pin_sn]]+ndp_SP1[[#This Row],[sp1_ndp_pin_sn]] -> 69599 | N11: =idp_SP1[[#This Row],[sp1_idp_pin_wa]]+ndp_SP1[[#This Row],[sp1_ndp_pin_wa]] -> 80620 | O11: =idp_SP1[[#This Row],[sp1_idp_pin_gp]]+ndp_SP1[[#This Row],[sp1_ndp_pin_gp]] -> 70901 | P11: =idp_SP1[[#This Row],[sp1_idp_pin_cp]]+ndp_SP1[[#This Row],[sp1_ndp_pin_cp]] -> 27712 | Q11: =idp_SP1[[#This Row],[sp1_idp_pin_gb]]+ndp_SP1[[#This Row],[sp1_ndp_pin_gb]] -> 38786 | R11: =idp_SP1[[#This Row],[sp1_idp_pin_fs]]+ndp_SP1[[#This Row],[sp1_ndp_pin_fs]] -> 36386 | S11: =idp_SP1[[#This Row],[sp1_idp_pin_li]]+ndp_SP1[[#This Row],[sp1_ndp_pin_li]] -> 0 | T11: =idp_SP1[[#This Row],[sp1_idp_pin_adopted]]+ndp_SP1[[#This Row],[sp1_ndp_pin_adopted]] -> 82212 | U11: 4 | V11: 4 | W11: 4 | X11: =MAX(idp_SP1[[#This Row],[sp1_idp_sev_pr]],ndp_SP1[[#This Row],[sp1_ndp_sev_pr]]) -> 4 | Y11: 4 | Z11: 4 | AA11: 4 | AB11: 4 | AC11: 4 | AD11: 4 | AE11: 4 | AF11: 4 | AG11: =idp_SP1[[#This Row],[sp1_idp_target_ed]]+ndp_SP1[[#This Row],[sp1_ndp_target_ed]] -> 10015 | AH11: =idp_SP1[[#This Row],[sp1_idp_target_fl]]+ndp_SP1[[#This Row],[sp1_ndp_target_fl]] -> 36386 | AI11: =idp_SP1[[#This Row],[sp1_idp_target_he]]+ndp_SP1[[#This Row],[sp1_ndp_target_he]] -> 53397 | AJ11: =idp_SP1[[#This Row],[sp1_idp_target_pr]]+ndp_SP1[[#This Row],[sp1_ndp_target_pr]] -> 37709 | AK11: =idp_SP1[[#This Row],[sp1_idp_target_sn]]+ndp_SP1[[#This Row],[sp1_ndp_target_sn]] -> 40472 | AL11: =idp_SP1[[#This Row],[sp1_idp_target_wa]]+ndp_SP1[[#This Row],[sp1_ndp_target_wa]] -> 80620 | AM11: =idp_SP1[[#This Row],[sp1_idp_target_gp]]+ndp_SP1[[#This Row],[sp1_ndp_target_gp]] -> 37709 | AN11: =idp_SP1[[#This Row],[sp1_idp_target_cp]]+ndp_SP1[[#This Row],[sp1_ndp_target_cp]] -> 20048 | AO11: =idp_SP1[[#This Row],[sp1_idp_target_gb]]+ndp_SP1[[#This Row],[sp1_ndp_target_gb]] -> 14584 | AP11: =idp_SP1[[#This Row],[sp1_idp_target_fs]]+ndp_SP1[[#This Row],[sp1_ndp_target_fs]] -> 36386 | AQ11: =idp_SP1[[#This Row],[sp1_idp_target_li]]+ndp_SP1[[#This Row],[sp1_ndp_target_li]] -> 0 | AR11: =idp_SP1[[#This Row],[sp1_idp_target_cw]]+ndp_SP1[[#This Row],[sp1_ndp_target_cw]] -> 26375 | AS11: =idp_SP1[[#This Row],[sp1_idp_target_joint]]+ndp_SP1[[#This Row],[sp1_ndp_target_joint]] -> 80620 | AT11: 10015 | AU11: 36386 | AV11: 53397 | AW11: 37709 | AX11: 40472 | AY11: 80620 | AZ11: 37709 | BA11: 20048 | BB11: 14584 | BC11: 36386 | BD11: 0 | BE11: 26375 | BF11: 80620
A12: Dnipropetrovska | B12: UA12 | C12: 51+ km | D12: 50+ | E12: UA12_U51P | F12: 0 | G12: 0 | I12: =idp_SP1[[#This Row],[sp1_idp_pin_ed]]+ndp_SP1[[#This Row],[sp1_ndp_pin_ed]] -> 0 | J12: =idp_SP1[[#This Row],[sp1_idp_pin_fl]]+ndp_SP1[[#This Row],[sp1_ndp_pin_fl]] -> 0 | K12: =idp_SP1[[#This Row],[sp1_idp_pin_he]]+ndp_SP1[[#This Row],[sp1_ndp_pin_he]] -> 0 | L12: =idp_SP1[[#This Row],[sp1_idp_pin_pr]]+ndp_SP1[[#This Row],[sp1_ndp_pin_pr]] -> 0 | M12: =idp_SP1[[#This Row],[sp1_idp_pin_sn]]+ndp_SP1[[#This Row],[sp1_ndp_pin_sn]] -> 0 | N12: =idp_SP1[[#This Row],[sp1_idp_pin_wa]]+ndp_SP1[[#This Row],[sp1_ndp_pin_wa]] -> 0 | O12: =idp_SP1[[#This Row],[sp1_idp_pin_gp]]+ndp_SP1[[#This Row],[sp1_ndp_pin_gp]] -> 0 | P12: =idp_SP1[[#This Row],[sp1_idp_pin_cp]]+ndp_SP1[[#This Row],[sp1_ndp_pin_cp]] -> 0 | Q12: =idp_SP1[[#This Row],[sp1_idp_pin_gb]]+ndp_SP1[[#This Row],[sp1_ndp_pin_gb]] -> 0 | R12: =idp_SP1[[#This Row],[sp1_idp_pin_fs]]+ndp_SP1[[#This Row],[sp1_ndp_pin_fs]] -> 0 | S12: =idp_SP1[[#This Row],[sp1_idp_pin_li]]+ndp_SP1[[#This Row],[sp1_ndp_pin_li]] -> 0 | T12: =idp_SP1[[#This Row],[sp1_idp_pin_adopted]]+ndp_SP1[[#This Row],[sp1_ndp_pin_adopted]] -> 0 | X12: =MAX(idp_SP1[[#This Row],[sp1_idp_sev_pr]],ndp_SP1[[#This Row],[sp1_ndp_sev_pr]]) -> 0 | Y12: 0 | AG12: =idp_SP1[[#This Row],[sp1_idp_target_ed]]+ndp_SP1[[#This Row],[sp1_ndp_target_ed]] -> 0 | AH12: =idp_SP1[[#This Row],[sp1_idp_target_fl]]+ndp_SP1[[#This Row],[sp1_ndp_target_fl]] -> 0 | AI12: =idp_SP1[[#This Row],[sp1_idp_target_he]]+ndp_SP1[[#This Row],[sp1_ndp_target_he]] -> 0 | AJ12: =idp_SP1[[#This Row],[sp1_idp_target_pr]]+ndp_SP1[[#This Row],[sp1_ndp_target_pr]] -> 0 | AK12: =idp_SP1[[#This Row],[sp1_idp_target_sn]]+ndp_SP1[[#This Row],[sp1_ndp_target_sn]] -> 0 | AL12: =idp_SP1[[#This Row],[sp1_idp_target_wa]]+ndp_SP1[[#This Row],[sp1_ndp_target_wa]] -> 0 | AM12: =idp_SP1[[#This Row],[sp1_idp_target_gp]]+ndp_SP1[[#This Row],[sp1_ndp_target_gp]] -> 0 | AN12: =idp_SP1[[#This Row],[sp1_idp_target_cp]]+ndp_SP1[[#This Row],[sp1_ndp_target_cp]] -> 0 | AO12: =idp_SP1[[#This Row],[sp1_idp_target_gb]]+ndp_SP1[[#This Row],[sp1_ndp_target_gb]] -> 0 | AP12: =idp_SP1[[#This Row],[sp1_idp_target_fs]]+ndp_SP1[[#This Row],[sp1_ndp_target_fs]] -> 0 | AQ12: =idp_SP1[[#This Row],[sp1_idp_target_li]]+ndp_SP1[[#This Row],[sp1_ndp_target_li]] -> 0 | AR12: =idp_SP1[[#This Row],[sp1_idp_target_cw]]+ndp_SP1[[#This Row],[sp1_ndp_target_cw]] -> 0 | AS12: =idp_SP1[[#This Row],[sp1_idp_target_joint]]+ndp_SP1[[#This Row],[sp1_ndp_target_joint]] -> 0 | AT12: 0 | AU12: 0 | AV12: 0 | AW12: 0 | AX12: 0 | AY12: 0 | AZ12: 0 | BA12: 0 | BB12: 0 | BC12: 0 | BD12: 0 | BE12: 0 | BF12: 0
A13: Donetska | B13: UA14 | C13: 0-20 km | D13: 0-20km | E13: UA14_U20A | F13: 28205 | G13: 152005 | H13: 180210 | I13: =idp_SP1[[#This Row],[sp1_idp_pin_ed]]+ndp_SP1[[#This Row],[sp1_ndp_pin_ed]] -> 13100 | J13: =idp_SP1[[#This Row],[sp1_idp_pin_fl]]+ndp_SP1[[#This Row],[sp1_ndp_pin_fl]] -> 79143 | K13: =idp_SP1[[#This Row],[sp1_idp_pin_he]]+ndp_SP1[[#This Row],[sp1_ndp_pin_he]] -> 139803 | L13: =idp_SP1[[#This Row],[sp1_idp_pin_pr]]+ndp_SP1[[#This Row],[sp1_ndp_pin_pr]] -> 149183 | M13: =idp_SP1[[#This Row],[sp1_idp_pin_sn]]+ndp_SP1[[#This Row],[sp1_ndp_pin_sn]] -> 159255 | N13: =idp_SP1[[#This Row],[sp1_idp_pin_wa]]+ndp_SP1[[#This Row],[sp1_ndp_pin_wa]] -> 167637 | O13: =idp_SP1[[#This Row],[sp1_idp_pin_gp]]+ndp_SP1[[#This Row],[sp1_ndp_pin_gp]] -> 149183 | P13: =idp_SP1[[#This Row],[sp1_idp_pin_cp]]+ndp_SP1[[#This Row],[sp1_ndp_pin_cp]] -> 50601 | Q13: =idp_SP1[[#This Row],[sp1_idp_pin_gb]]+ndp_SP1[[#This Row],[sp1_ndp_pin_gb]] -> 90826 | R13: =idp_SP1[[#This Row],[sp1_idp_pin_fs]]+ndp_SP1[[#This Row],[sp1_ndp_pin_fs]] -> 79143 | S13: =idp_SP1[[#This Row],[sp1_idp_pin_li]]+ndp_SP1[[#This Row],[sp1_ndp_pin_li]] -> 0 | T13: =idp_SP1[[#This Row],[sp1_idp_pin_adopted]]+ndp_SP1[[#This Row],[sp1_ndp_pin_adopted]] -> 167637 | U13: 5 | V13: 4 | W13: 4 | X13: =MAX(idp_SP1[[#This Row],[sp1_idp_sev_pr]],ndp_SP1[[#This Row],[sp1_ndp_sev_pr]]) -> 5 | Y13: 5 | Z13: 5 | AA13: 5 | AB13: 5 | AC13: 5 | AD13: 4 | AE13: 4 | AF13: 5 | AG13: =idp_SP1[[#This Row],[sp1_idp_target_ed]]+ndp_SP1[[#This Row],[sp1_ndp_target_ed]] -> 11789 | AH13: =idp_SP1[[#This Row],[sp1_idp_target_fl]]+ndp_SP1[[#This Row],[sp1_ndp_target_fl]] -> 79143 | AI13: =idp_SP1[[#This Row],[sp1_idp_target_he]]+ndp_SP1[[#This Row],[sp1_ndp_target_he]] -> 80867 | AJ13: =idp_SP1[[#This Row],[sp1_idp_target_pr]]+ndp_SP1[[#This Row],[sp1_ndp_target_pr]] -> 62368 | AK13: =idp_SP1[[#This Row],[sp1_idp_target_sn]]+ndp_SP1[[#This Row],[sp1_ndp_target_sn]] -> 77884 | AL13: =idp_SP1[[#This Row],[sp1_idp_target_wa]]+ndp_SP1[[#This Row],[sp1_ndp_target_wa]] -> 167637 | AM13: =idp_SP1[[#This Row],[sp1_idp_target_gp]]+ndp_SP1[[#This Row],[sp1_ndp_target_gp]] -> 62368 | AN13: =idp_SP1[[#This Row],[sp1_idp_target_cp]]+ndp_SP1[[#This Row],[sp1_ndp_target_cp]] -> 42069 | AO13: =idp_SP1[[#This Row],[sp1_idp_target_gb]]+ndp_SP1[[#This Row],[sp1_ndp_target_gb]] -> 4542 | AP13: =idp_SP1[[#This Row],[sp1_idp_target_fs]]+ndp_SP1[[#This Row],[sp1_ndp_target_fs]] -> 79143 | AQ13: =idp_SP1[[#This Row],[sp1_idp_target_li]]+ndp_SP1[[#This Row],[sp1_ndp_target_li]] -> 0 | AR13: =idp_SP1[[#This Row],[sp1_idp_target_cw]]+ndp_SP1[[#This Row],[sp1_ndp_target_cw]] -> 129919 | AS13: =idp_SP1[[#This Row],[sp1_idp_target_joint]]+ndp_SP1[[#This Row],[sp1_ndp_target_joint]] -> 167637 | AT13: 11789 | AU13: 79143 | AV13: 80867 | AW13: 62368 | AX13: 77884 | AY13: 167637 | AZ13: 62368 | BA13: 42069 | BB13: 4542 | BC13: 79143 | BD13: 0 | BE13: 129919 | BF13: 167637
A14: Donetska | B14: UA14 | C14: 21-50 km | D14: 20-50km | E14: UA14_U50A | F14: 10472 | G14: 35228.32 | H14: 45700.32 | I14: =idp_SP1[[#This Row],[sp1_idp_pin_ed]]+ndp_SP1[[#This Row],[sp1_ndp_pin_ed]] -> 2961 | J14: =idp_SP1[[#This Row],[sp1_idp_pin_fl]]+ndp_SP1[[#This Row],[sp1_ndp_pin_fl]] -> 13988 | K14: =idp_SP1[[#This Row],[sp1_idp_pin_he]]+ndp_SP1[[#This Row],[sp1_ndp_pin_he]] -> 35453 | L14: =idp_SP1[[#This Row],[sp1_idp_pin_pr]]+ndp_SP1[[#This Row],[sp1_ndp_pin_pr]] -> 32544 | M14: =idp_SP1[[#This Row],[sp1_idp_pin_sn]]+ndp_SP1[[#This Row],[sp1_ndp_pin_sn]] -> 36540 | N14: =idp_SP1[[#This Row],[sp1_idp_pin_wa]]+ndp_SP1[[#This Row],[sp1_ndp_pin_wa]] -> 37090 | O14: =idp_SP1[[#This Row],[sp1_idp_pin_gp]]+ndp_SP1[[#This Row],[sp1_ndp_pin_gp]] -> 32544 | P14: =idp_SP1[[#This Row],[sp1_idp_pin_cp]]+ndp_SP1[[#This Row],[sp1_ndp_pin_cp]] -> 13151 | Q14: =idp_SP1[[#This Row],[sp1_idp_pin_gb]]+ndp_SP1[[#This Row],[sp1_ndp_pin_gb]] -> 23033 | R14: =idp_SP1[[#This Row],[sp1_idp_pin_fs]]+ndp_SP1[[#This Row],[sp1_ndp_pin_fs]] -> 13988 | S14: =idp_SP1[[#This Row],[sp1_idp_pin_li]]+ndp_SP1[[#This Row],[sp1_ndp_pin_li]] -> 0 | T14: =idp_SP1[[#This Row],[sp1_idp_pin_adopted]]+ndp_SP1[[#This Row],[sp1_ndp_pin_adopted]] -> 38016 | U14: 5 | V14: 4 | W14: 4 | X14: =MAX(idp_SP1[[#This Row],[sp1_idp_sev_pr]],ndp_SP1[[#This Row],[sp1_ndp_sev_pr]]) -> 5 | Y14: 5 | Z14: 4 | AA14: 5 | AB14: 5 | AC14: 5 | AD14: 4 | AE14: 4 | AF14: 5 | AG14: =idp_SP1[[#This Row],[sp1_idp_target_ed]]+ndp_SP1[[#This Row],[sp1_ndp_target_ed]] -> 2665 | AH14: =idp_SP1[[#This Row],[sp1_idp_target_fl]]+ndp_SP1[[#This Row],[sp1_ndp_target_fl]] -> 13988 | AI14: =idp_SP1[[#This Row],[sp1_idp_target_he]]+ndp_SP1[[#This Row],[sp1_ndp_target_he]] -> 24502 | AJ14: =idp_SP1[[#This Row],[sp1_idp_target_pr]]+ndp_SP1[[#This Row],[sp1_ndp_target_pr]] -> 17722 | AK14: =idp_SP1[[#This Row],[sp1_idp_target_sn]]+ndp_SP1[[#This Row],[sp1_ndp_target_sn]] -> 17666 | AL14: =idp_SP1[[#This Row],[sp1_idp_target_wa]]+ndp_SP1[[#This Row],[sp1_ndp_target_wa]] -> 37090 | AM14: =idp_SP1[[#This Row],[sp1_idp_target_gp]]+ndp_SP1[[#This Row],[sp1_ndp_target_gp]] -> 15161 | AN14: =idp_SP1[[#This Row],[sp1_idp_target_cp]]+ndp_SP1[[#This Row],[sp1_ndp_target_cp]] -> 10578 | AO14: =idp_SP1[[#This Row],[sp1_idp_target_gb]]+ndp_SP1[[#This Row],[sp1_ndp_target_gb]] -> 13820 | AP14: =idp_SP1[[#This Row],[sp1_idp_target_fs]]+ndp_SP1[[#This Row],[sp1_ndp_target_fs]] -> 13988 | AQ14: =idp_SP1[[#This Row],[sp1_idp_target_li]]+ndp_SP1[[#This Row],[sp1_ndp_target_li]] -> 0 | AR14: =idp_SP1[[#This Row],[sp1_idp_target_cw]]+ndp_SP1[[#This Row],[sp1_ndp_target_cw]] -> 11273 | AS14: =idp_SP1[[#This Row],[sp1_idp_target_joint]]+ndp_SP1[[#This Row],[sp1_ndp_target_joint]] -> 37090 | AT14: 2665 | AU14: 13988 | AV14: 24502 | AW14: 17722 | AX14: 17666 | AY14: 37090 | AZ14: 15161 | BA14: 10578 | BB14: 13820 | BC14: 13988 | BD14: 0 | BE14: 11273 | BF14: 37090
A15: Zhytomyrska | B15: UA18 | C15: All oblast | D15: 50+ | E15: UA18_UALL | F15: 0 | G15: 0 | I15: =idp_SP1[[#This Row],[sp1_idp_pin_ed]]+ndp_SP1[[#This Row],[sp1_ndp_pin_ed]] -> 0 | J15: =idp_SP1[[#This Row],[sp1_idp_pin_fl]]+ndp_SP1[[#This Row],[sp1_ndp_pin_fl]] -> 0 | K15: =idp_SP1[[#This Row],[sp1_idp_pin_he]]+ndp_SP1[[#This Row],[sp1_ndp_pin_he]] -> 0 | L15: =idp_SP1[[#This Row],[sp1_idp_pin_pr]]+ndp_SP1[[#This Row],[sp1_ndp_pin_pr]] -> 0 | M15: =idp_SP1[[#This Row],[sp1_idp_pin_sn]]+ndp_SP1[[#This Row],[sp1_ndp_pin_sn]] -> 0 | N15: =idp_SP1[[#This Row],[sp1_idp_pin_wa]]+ndp_SP1[[#This Row],[sp1_ndp_pin_wa]] -> 0 | O15: =idp_SP1[[#This Row],[sp1_idp_pin_gp]]+ndp_SP1[[#This Row],[sp1_ndp_pin_gp]] -> 0 | P15: =idp_SP1[[#This Row],[sp1_idp_pin_cp]]+ndp_SP1[[#This Row],[sp1_ndp_pin_cp]] -> 0 | Q15: =idp_SP1[[#This Row],[sp1_idp_pin_gb]]+ndp_SP1[[#This Row],[sp1_ndp_pin_gb]] -> 0 | R15: =idp_SP1[[#This Row],[sp1_idp_pin_fs]]+ndp_SP1[[#This Row],[sp1_ndp_pin_fs]] -> 0 | S15: =idp_SP1[[#This Row],[sp1_idp_pin_li]]+ndp_SP1[[#This Row],[sp1_ndp_pin_li]] -> 0 | T15: =idp_SP1[[#This Row],[sp1_idp_pin_adopted]]+ndp_SP1[[#This Row],[sp1_ndp_pin_adopted]] -> 0 | X15: =MAX(idp_SP1[[#This Row],[sp1_idp_sev_pr]],ndp_SP1[[#This Row],[sp1_ndp_sev_pr]]) -> 0 | Y15: 0 | AG15: =idp_SP1[[#This Row],[sp1_idp_target_ed]]+ndp_SP1[[#This Row],[sp1_ndp_target_ed]] -> 0 | AH15: =idp_SP1[[#This Row],[sp1_idp_target_fl]]+ndp_SP1[[#This Row],[sp1_ndp_target_fl]] -> 0 | AI15: =idp_SP1[[#This Row],[sp1_idp_target_he]]+ndp_SP1[[#This Row],[sp1_ndp_target_he]] -> 0 | AJ15: =idp_SP1[[#This Row],[sp1_idp_target_pr]]+ndp_SP1[[#This Row],[sp1_ndp_target_pr]] -> 0 | AK15: =idp_SP1[[#This Row],[sp1_idp_target_sn]]+ndp_SP1[[#This Row],[sp1_ndp_target_sn]] -> 0 | AL15: =idp_SP1[[#This Row],[sp1_idp_target_wa]]+ndp_SP1[[#This Row],[sp1_ndp_target_wa]] -> 0 | AM15: =idp_SP1[[#This Row],[sp1_idp_target_gp]]+ndp_SP1[[#This Row],[sp1_ndp_target_gp]] -> 0 | AN15: =idp_SP1[[#This Row],[sp1_idp_target_cp]]+ndp_SP1[[#This Row],[sp1_ndp_target_cp]] -> 0 | AO15: =idp_SP1[[#This Row],[sp1_idp_target_gb]]+ndp_SP1[[#This Row],[sp1_ndp_target_gb]] -> 0 | AP15: =idp_SP1[[#This Row],[sp1_idp_target_fs]]+ndp_SP1[[#This Row],[sp1_ndp_target_fs]] -> 0 | AQ15: =idp_SP1[[#This Row],[sp1_idp_target_li]]+ndp_SP1[[#This Row],[sp1_ndp_target_li]] -> 0 | AR15: =idp_SP1[[#This Row],[sp1_idp_target_cw]]+ndp_SP1[[#This Row],[sp1_ndp_target_cw]] -> 0 | AS15: =idp_SP1[[#This Row],[sp1_idp_target_joint]]+ndp_SP1[[#This Row],[sp1_ndp_target_joint]] -> 0 | AT15: 0 | AU15: 0 | AV15: 0 | AW15: 0 | AX15: 0 | AY15: 0 | AZ15: 0 | BA15: 0 | BB15: 0 | BC15: 0 | BD15: 0 | BE15: 0 | BF15: 0
A16: Zakarpatska | B16: UA21 | C16: All oblast | D16: 50+ | E16: UA21_UALL | F16: 0 | G16: 0 | I16: =idp_SP1[[#This Row],[sp1_idp_pin_ed]]+ndp_SP1[[#This Row],[sp1_ndp_pin_ed]] -> 0 | J16: =idp_SP1[[#This Row],[sp1_idp_pin_fl]]+ndp_SP1[[#This Row],[sp1_ndp_pin_fl]] -> 0 | K16: =idp_SP1[[#This Row],[sp1_idp_pin_he]]+ndp_SP1[[#This Row],[sp1_ndp_pin_he]] -> 0 | L16: =idp_SP1[[#This Row],[sp1_idp_pin_pr]]+ndp_SP1[[#This Row],[sp1_ndp_pin_pr]] -> 0 | M16: =idp_SP1[[#This Row],[sp1_idp_pin_sn]]+ndp_SP1[[#This Row],[sp1_ndp_pin_sn]] -> 0 | N16: =idp_SP1[[#This Row],[sp1_idp_pin_wa]]+ndp_SP1[[#This Row],[sp1_ndp_pin_wa]] -> 0 | O16: =idp_SP1[[#This Row],[sp1_idp_pin_gp]]+ndp_SP1[[#This Row],[sp1_ndp_pin_gp]] -> 0 | P16: =idp_SP1[[#This Row],[sp1_idp_pin_cp]]+ndp_SP1[[#This Row],[sp1_ndp_pin_cp]] -> 0 | Q16: =idp_SP1[[#This Row],[sp1_idp_pin_gb]]+ndp_SP1[[#This Row],[sp1_ndp_pin_gb]] -> 0 | R16: =idp_SP1[[#This Row],[sp1_idp_pin_fs]]+ndp_SP1[[#This Row],[sp1_ndp_pin_fs]] -> 0 | S16: =idp_SP1[[#This Row],[sp1_idp_pin_li]]+ndp_SP1[[#This Row],[sp1_ndp_pin_li]] -> 0 | T16: =idp_SP1[[#This Row],[sp1_idp_pin_adopted]]+ndp_SP1[[#This Row],[sp1_ndp_pin_adopted]] -> 0 | X16: =MAX(idp_SP1[[#This Row],[sp1_idp_sev_pr]],ndp_SP1[[#This Row],[sp1_ndp_sev_pr]]) -> 0 | Y16: 0 | AG16: =idp_SP1[[#This Row],[sp1_idp_target_ed]]+ndp_SP1[[#This Row],[sp1_ndp_target_ed]] -> 0 | AH16: =idp_SP1[[#This Row],[sp1_idp_target_fl]]+ndp_SP1[[#This Row],[sp1_ndp_target_fl]] -> 0 | AI16: =idp_SP1[[#This Row],[sp1_idp_target_he]]+ndp_SP1[[#This Row],[sp1_ndp_target_he]] -> 0 | AJ16: =idp_SP1[[#This Row],[sp1_idp_target_pr]]+ndp_SP1[[#This Row],[sp1_ndp_target_pr]] -> 0 | AK16: =idp_SP1[[#This Row],[sp1_idp_target_sn]]+ndp_SP1[[#This Row],[sp1_ndp_target_sn]] -> 0 | AL16: =idp_SP1[[#This Row],[sp1_idp_target_wa]]+ndp_SP1[[#This Row],[sp1_ndp_target_wa]] -> 0 | AM16: =idp_SP1[[#This Row],[sp1_idp_target_gp]]+ndp_SP1[[#This Row],[sp1_ndp_target_gp]] -> 0 | AN16: =idp_SP1[[#This Row],[sp1_idp_target_cp]]+ndp_SP1[[#This Row],[sp1_ndp_target_cp]] -> 0 | AO16: =idp_SP1[[#This Row],[sp1_idp_target_gb]]+ndp_SP1[[#This Row],[sp1_ndp_target_gb]] -> 0 | AP16: =idp_SP1[[#This Row],[sp1_idp_target_fs]]+ndp_SP1[[#This Row],[sp1_ndp_target_fs]] -> 0 | AQ16: =idp_SP1[[#This Row],[sp1_idp_target_li]]+ndp_SP1[[#This Row],[sp1_ndp_target_li]] -> 0 | AR16: =idp_SP1[[#This Row],[sp1_idp_target_cw]]+ndp_SP1[[#This Row],[sp1_ndp_target_cw]] -> 0 | AS16: =idp_SP1[[#This Row],[sp1_idp_target_joint]]+ndp_SP1[[#This Row],[sp1_ndp_target_joint]] -> 0 | AT16: 0 | AU16: 0 | AV16: 0 | AW16: 0 | AX16: 0 | AY16: 0 | AZ16: 0 | BA16: 0 | BB16: 0 | BC16: 0 | BD16: 0 | BE16: 0 | BF16: 0
A17: Zaporizka | B17: UA23 | C17: 0-20 km | D17: 0-20km | E17: UA23_U20A | F17: 7270 | G17: 50450 | H17: 57720 | I17: =idp_SP1[[#This Row],[sp1_idp_pin_ed]]+ndp_SP1[[#This Row],[sp1_ndp_pin_ed]] -> 2736 | J17: =idp_SP1[[#This Row],[sp1_idp_pin_fl]]+ndp_SP1[[#This Row],[sp1_ndp_pin_fl]] -> 25078 | K17: =idp_SP1[[#This Row],[sp1_idp_pin_he]]+ndp_SP1[[#This Row],[sp1_ndp_pin_he]] -> 44778 | L17: =idp_SP1[[#This Row],[sp1_idp_pin_pr]]+ndp_SP1[[#This Row],[sp1_ndp_pin_pr]] -> 49559 | M17: =idp_SP1[[#This Row],[sp1_idp_pin_sn]]+ndp_SP1[[#This Row],[sp1_ndp_pin_sn]] -> 45250 | N17: =idp_SP1[[#This Row],[sp1_idp_pin_wa]]+ndp_SP1[[#This Row],[sp1_ndp_pin_wa]] -> 57720 | O17: =idp_SP1[[#This Row],[sp1_idp_pin_gp]]+ndp_SP1[[#This Row],[sp1_ndp_pin_gp]] -> 49559 | P17: =idp_SP1[[#This Row],[sp1_idp_pin_cp]]+ndp_SP1[[#This Row],[sp1_ndp_pin_cp]] -> 17762 | Q17: =idp_SP1[[#This Row],[sp1_idp_pin_gb]]+ndp_SP1[[#This Row],[sp1_ndp_pin_gb]] -> 29091 | R17: =idp_SP1[[#This Row],[sp1_idp_pin_fs]]+ndp_SP1[[#This Row],[sp1_ndp_pin_fs]] -> 25078 | S17: =idp_SP1[[#This Row],[sp1_idp_pin_li]]+ndp_SP1[[#This Row],[sp1_ndp_pin_li]] -> 0 | T17: =idp_SP1[[#This Row],[sp1_idp_pin_adopted]]+ndp_SP1[[#This Row],[sp1_ndp_pin_adopted]] -> 57720 | U17: 5 | V17: 4 | W17: 4 | X17: =MAX(idp_SP1[[#This Row],[sp1_idp_sev_pr]],ndp_SP1[[#This Row],[sp1_ndp_sev_pr]]) -> 5 | Y17: 5 | Z17: 5 | AA17: 4 | AB17: 5 | AC17: 5 | AD17: 4 | AE17: 4 | AF17: 5 | AG17: =idp_SP1[[#This Row],[sp1_idp_target_ed]]+ndp_SP1[[#This Row],[sp1_ndp_target_ed]] -> 2463 | AH17: =idp_SP1[[#This Row],[sp1_idp_target_fl]]+ndp_SP1[[#This Row],[sp1_ndp_target_fl]] -> 25078 | AI17: =idp_SP1[[#This Row],[sp1_idp_target_he]]+ndp_SP1[[#This Row],[sp1_ndp_target_he]] -> 25612 | AJ17: =idp_SP1[[#This Row],[sp1_idp_target_pr]]+ndp_SP1[[#This Row],[sp1_ndp_target_pr]] -> 19008 | AK17: =idp_SP1[[#This Row],[sp1_idp_target_sn]]+ndp_SP1[[#This Row],[sp1_ndp_target_sn]] -> 27809 | AL17: =idp_SP1[[#This Row],[sp1_idp_target_wa]]+ndp_SP1[[#This Row],[sp1_ndp_target_wa]] -> 57720 | AM17: =idp_SP1[[#This Row],[sp1_idp_target_gp]]+ndp_SP1[[#This Row],[sp1_ndp_target_gp]] -> 19008 | AN17: =idp_SP1[[#This Row],[sp1_idp_target_cp]]+ndp_SP1[[#This Row],[sp1_ndp_target_cp]] -> 14868 | AO17: =idp_SP1[[#This Row],[sp1_idp_target_gb]]+ndp_SP1[[#This Row],[sp1_ndp_target_gb]] -> 1454 | AP17: =idp_SP1[[#This Row],[sp1_idp_target_fs]]+ndp_SP1[[#This Row],[sp1_ndp_target_fs]] -> 25078 | AQ17: =idp_SP1[[#This Row],[sp1_idp_target_li]]+ndp_SP1[[#This Row],[sp1_ndp_target_li]] -> 0 | AR17: =idp_SP1[[#This Row],[sp1_idp_target_cw]]+ndp_SP1[[#This Row],[sp1_ndp_target_cw]] -> 13079 | AS17: =idp_SP1[[#This Row],[sp1_idp_target_joint]]+ndp_SP1[[#This Row],[sp1_ndp_target_joint]] -> 57720 | AT17: 2463 | AU17: 25078 | AV17: 25612 | AW17: 19008 | AX17: 27809 | AY17: 57720 | AZ17: 19008 | BA17: 14868 | BB17: 1454 | BC17: 25078 | BD17: 0 | BE17: 13079 | BF17: 57720
A18: Zaporizka | B18: UA23 | C18: 21-50 km (w/o Zaporizhzhia) | D18: 20-50km | E18: UA23_U50X | F18: 22234 | G18: 20057.226 | H18: 42291.226 | I18: =idp_SP1[[#This Row],[sp1_idp_pin_ed]]+ndp_SP1[[#This Row],[sp1_ndp_pin_ed]] -> 1640 | J18: =idp_SP1[[#This Row],[sp1_idp_pin_fl]]+ndp_SP1[[#This Row],[sp1_ndp_pin_fl]] -> 13153 | K18: =idp_SP1[[#This Row],[sp1_idp_pin_he]]+ndp_SP1[[#This Row],[sp1_ndp_pin_he]] -> 32809 | L18: =idp_SP1[[#This Row],[sp1_idp_pin_pr]]+ndp_SP1[[#This Row],[sp1_ndp_pin_pr]] -> 37016 | M18: =idp_SP1[[#This Row],[sp1_idp_pin_sn]]+ndp_SP1[[#This Row],[sp1_ndp_pin_sn]] -> 26223 | N18: =idp_SP1[[#This Row],[sp1_idp_pin_wa]]+ndp_SP1[[#This Row],[sp1_ndp_pin_wa]] -> 25374 | O18: =idp_SP1[[#This Row],[sp1_idp_pin_gp]]+ndp_SP1[[#This Row],[sp1_ndp_pin_gp]] -> 37016 | P18: =idp_SP1[[#This Row],[sp1_idp_pin_cp]]+ndp_SP1[[#This Row],[sp1_ndp_pin_cp]] -> 15382 | Q18: =idp_SP1[[#This Row],[sp1_idp_pin_gb]]+ndp_SP1[[#This Row],[sp1_ndp_pin_gb]] -> 16578 | R18: =idp_SP1[[#This Row],[sp1_idp_pin_fs]]+ndp_SP1[[#This Row],[sp1_ndp_pin_fs]] -> 13153 | S18: =idp_SP1[[#This Row],[sp1_idp_pin_li]]+ndp_SP1[[#This Row],[sp1_ndp_pin_li]] -> 0 | T18: =idp_SP1[[#This Row],[sp1_idp_pin_adopted]]+ndp_SP1[[#This Row],[sp1_ndp_pin_adopted]] -> 37016 | U18: 4 | V18: 4 | W18: 4 | X18: =MAX(idp_SP1[[#This Row],[sp1_idp_sev_pr]],ndp_SP1[[#This Row],[sp1_ndp_sev_pr]]) -> 4 | Y18: 4 | Z18: 4 | AA18: 4 | AB18: 4 | AC18: 4 | AD18: 4 | AE18: 4 | AF18: 4 | AG18: =idp_SP1[[#This Row],[sp1_idp_target_ed]]+ndp_SP1[[#This Row],[sp1_ndp_target_ed]] -> 1477 | AH18: =idp_SP1[[#This Row],[sp1_idp_target_fl]]+ndp_SP1[[#This Row],[sp1_ndp_target_fl]] -> 13153 | AI18: =idp_SP1[[#This Row],[sp1_idp_target_he]]+ndp_SP1[[#This Row],[sp1_ndp_target_he]] -> 22968 | AJ18: =idp_SP1[[#This Row],[sp1_idp_target_pr]]+ndp_SP1[[#This Row],[sp1_ndp_target_pr]] -> 20541 | AK18: =idp_SP1[[#This Row],[sp1_idp_target_sn]]+ndp_SP1[[#This Row],[sp1_ndp_target_sn]] -> 18004 | AL18: =idp_SP1[[#This Row],[sp1_idp_target_wa]]+ndp_SP1[[#This Row],[sp1_ndp_target_wa]] -> 25374 | AM18: =idp_SP1[[#This Row],[sp1_idp_target_gp]]+ndp_SP1[[#This Row],[sp1_ndp_target_gp]] -> 20541 | AN18: =idp_SP1[[#This Row],[sp1_idp_target_cp]]+ndp_SP1[[#This Row],[sp1_ndp_target_cp]] -> 10390 | AO18: =idp_SP1[[#This Row],[sp1_idp_target_gb]]+ndp_SP1[[#This Row],[sp1_ndp_target_gb]] -> 8289 | AP18: =idp_SP1[[#This Row],[sp1_idp_target_fs]]+ndp_SP1[[#This Row],[sp1_ndp_target_fs]] -> 13153 | AQ18: =idp_SP1[[#This Row],[sp1_idp_target_li]]+ndp_SP1[[#This Row],[sp1_ndp_target_li]] -> 0 | AR18: =idp_SP1[[#This Row],[sp1_idp_target_cw]]+ndp_SP1[[#This Row],[sp1_ndp_target_cw]] -> 2027 | AS18: =idp_SP1[[#This Row],[sp1_idp_target_joint]]+ndp_SP1[[#This Row],[sp1_ndp_target_joint]] -> 26257 | AT18: 1477 | AU18: 13153 | AV18: 22968 | AW18: 20541 | AX18: 18004 | AY18: 25374 | AZ18: 20541 | BA18: 10390 | BB18: 8289 | BC18: 13153 | BD18: 0 | BE18: 2027 | BF18: 26257
A19: Zaporizka | B19: UA23 | C19: 51+ km | D19: 50+ | E19: UA23_U51P | F19: 0 | G19: 0 | I19: =idp_SP1[[#This Row],[sp1_idp_pin_ed]]+ndp_SP1[[#This Row],[sp1_ndp_pin_ed]] -> 0 | J19: =idp_SP1[[#This Row],[sp1_idp_pin_fl]]+ndp_SP1[[#This Row],[sp1_ndp_pin_fl]] -> 0 | K19: =idp_SP1[[#This Row],[sp1_idp_pin_he]]+ndp_SP1[[#This Row],[sp1_ndp_pin_he]] -> 0 | L19: =idp_SP1[[#This Row],[sp1_idp_pin_pr]]+ndp_SP1[[#This Row],[sp1_ndp_pin_pr]] -> 0 | M19: =idp_SP1[[#This Row],[sp1_idp_pin_sn]]+ndp_SP1[[#This Row],[sp1_ndp_pin_sn]] -> 0 | N19: =idp_SP1[[#This Row],[sp1_idp_pin_wa]]+ndp_SP1[[#This Row],[sp1_ndp_pin_wa]] -> 0 | O19: =idp_SP1[[#This Row],[sp1_idp_pin_gp]]+ndp_SP1[[#This Row],[sp1_ndp_pin_gp]] -> 0 | P19: =idp_SP1[[#This Row],[sp1_idp_pin_cp]]+ndp_SP1[[#This Row],[sp1_ndp_pin_cp]] -> 0 | Q19: =idp_SP1[[#This Row],[sp1_idp_pin_gb]]+ndp_SP1[[#This Row],[sp1_ndp_pin_gb]] -> 0 | R19: =idp_SP1[[#This Row],[sp1_idp_pin_fs]]+ndp_SP1[[#This Row],[sp1_ndp_pin_fs]] -> 0 | S19: =idp_SP1[[#This Row],[sp1_idp_pin_li]]+ndp_SP1[[#This Row],[sp1_ndp_pin_li]] -> 0 | T19: =idp_SP1[[#This Row],[sp1_idp_pin_adopted]]+ndp_SP1[[#This Row],[sp1_ndp_pin_adopted]] -> 0 | X19: =MAX(idp_SP1[[#This Row],[sp1_idp_sev_pr]],ndp_SP1[[#This Row],[sp1_ndp_sev_pr]]) -> 0 | Y19: 0 | Z19: 0 | AA19: 0 | AG19: =idp_SP1[[#This Row],[sp1_idp_target_ed]]+ndp_SP1[[#This Row],[sp1_ndp_target_ed]] -> 0 | AH19: =idp_SP1[[#This Row],[sp1_idp_target_fl]]+ndp_SP1[[#This Row],[sp1_ndp_target_fl]] -> 0 | AI19: =idp_SP1[[#This Row],[sp1_idp_target_he]]+ndp_SP1[[#This Row],[sp1_ndp_target_he]] -> 0 | AJ19: =idp_SP1[[#This Row],[sp1_idp_target_pr]]+ndp_SP1[[#This Row],[sp1_ndp_target_pr]] -> 0 | AK19: =idp_SP1[[#This Row],[sp1_idp_target_sn]]+ndp_SP1[[#This Row],[sp1_ndp_target_sn]] -> 0 | AL19: =idp_SP1[[#This Row],[sp1_idp_target_wa]]+ndp_SP1[[#This Row],[sp1_ndp_target_wa]] -> 0 | AM19: =idp_SP1[[#This Row],[sp1_idp_target_gp]]+ndp_SP1[[#This Row],[sp1_ndp_target_gp]] -> 0 | AN19: =idp_SP1[[#This Row],[sp1_idp_target_cp]]+ndp_SP1[[#This Row],[sp1_ndp_target_cp]] -> 0 | AO19: =idp_SP1[[#This Row],[sp1_idp_target_gb]]+ndp_SP1[[#This Row],[sp1_ndp_target_gb]] -> 0 | AP19: =idp_SP1[[#This Row],[sp1_idp_target_fs]]+ndp_SP1[[#This Row],[sp1_ndp_target_fs]] -> 0 | AQ19: =idp_SP1[[#This Row],[sp1_idp_target_li]]+ndp_SP1[[#This Row],[sp1_ndp_target_li]] -> 0 | AR19: =idp_SP1[[#This Row],[sp1_idp_target_cw]]+ndp_SP1[[#This Row],[sp1_ndp_target_cw]] -> 0 | AS19: =idp_SP1[[#This Row],[sp1_idp_target_joint]]+ndp_SP1[[#This Row],[sp1_ndp_target_joint]] -> 0 | AT19: 0 | AU19: 0 | AV19: 0 | AW19: 0 | AX19: 0 | AY19: 0 | AZ19: 0 | BA19: 0 | BB19: 0 | BC19: 0 | BD19: 0 | BE19: 0 | BF19: 0
A20: Zaporizka | B20: UA23 | C20: Zaporizhzhia city | D20: 20-50km | E20: UA23_UCAP | F20: 131221 | G20: 246952.56 | H20: 378173.56 | I20: =idp_SP1[[#This Row],[sp1_idp_pin_ed]]+ndp_SP1[[#This Row],[sp1_ndp_pin_ed]] -> 25643 | J20: =idp_SP1[[#This Row],[sp1_idp_pin_fl]]+ndp_SP1[[#This Row],[sp1_ndp_pin_fl]] -> 118553 | K20: =idp_SP1[[#This Row],[sp1_idp_pin_he]]+ndp_SP1[[#This Row],[sp1_ndp_pin_he]] -> 293378 | L20: =idp_SP1[[#This Row],[sp1_idp_pin_pr]]+ndp_SP1[[#This Row],[sp1_ndp_pin_pr]] -> 342542 | M20: =idp_SP1[[#This Row],[sp1_idp_pin_sn]]+ndp_SP1[[#This Row],[sp1_ndp_pin_sn]] -> 225732 | N20: =idp_SP1[[#This Row],[sp1_idp_pin_wa]]+ndp_SP1[[#This Row],[sp1_ndp_pin_wa]] -> 223122 | O20: =idp_SP1[[#This Row],[sp1_idp_pin_gp]]+ndp_SP1[[#This Row],[sp1_ndp_pin_gp]] -> 342542 | P20: =idp_SP1[[#This Row],[sp1_idp_pin_cp]]+ndp_SP1[[#This Row],[sp1_ndp_pin_cp]] -> 118951 | Q20: =idp_SP1[[#This Row],[sp1_idp_pin_gb]]+ndp_SP1[[#This Row],[sp1_ndp_pin_gb]] -> 148244 | R20: =idp_SP1[[#This Row],[sp1_idp_pin_fs]]+ndp_SP1[[#This Row],[sp1_ndp_pin_fs]] -> 118553 | S20: =idp_SP1[[#This Row],[sp1_idp_pin_li]]+ndp_SP1[[#This Row],[sp1_ndp_pin_li]] -> 0 | T20: =idp_SP1[[#This Row],[sp1_idp_pin_adopted]]+ndp_SP1[[#This Row],[sp1_ndp_pin_adopted]] -> 342542 | U20: 4 | V20: 4 | W20: 4 | X20: =MAX(idp_SP1[[#This Row],[sp1_idp_sev_pr]],ndp_SP1[[#This Row],[sp1_ndp_sev_pr]]) -> 4 | Y20: 4 | Z20: 4 | AA20: 4 | AB20: 4 | AC20: 4 | AD20: 4 | AE20: 4 | AF20: 4 | AG20: =idp_SP1[[#This Row],[sp1_idp_target_ed]]+ndp_SP1[[#This Row],[sp1_ndp_target_ed]] -> 23078 | AH20: =idp_SP1[[#This Row],[sp1_idp_target_fl]]+ndp_SP1[[#This Row],[sp1_ndp_target_fl]] -> 118553 | AI20: =idp_SP1[[#This Row],[sp1_idp_target_he]]+ndp_SP1[[#This Row],[sp1_ndp_target_he]] -> 151280 | AJ20: =idp_SP1[[#This Row],[sp1_idp_target_pr]]+ndp_SP1[[#This Row],[sp1_ndp_target_pr]] -> 162720 | AK20: =idp_SP1[[#This Row],[sp1_idp_target_sn]]+ndp_SP1[[#This Row],[sp1_ndp_target_sn]] -> 110476 | AL20: =idp_SP1[[#This Row],[sp1_idp_target_wa]]+ndp_SP1[[#This Row],[sp1_ndp_target_wa]] -> 223122 | AM20: =idp_SP1[[#This Row],[sp1_idp_target_gp]]+ndp_SP1[[#This Row],[sp1_ndp_target_gp]] -> 162720 | AN20: =idp_SP1[[#This Row],[sp1_idp_target_cp]]+ndp_SP1[[#This Row],[sp1_ndp_target_cp]] -> 87484 | AO20: =idp_SP1[[#This Row],[sp1_idp_target_gb]]+ndp_SP1[[#This Row],[sp1_ndp_target_gb]] -> 74122 | AP20: =idp_SP1[[#This Row],[sp1_idp_target_fs]]+ndp_SP1[[#This Row],[sp1_ndp_target_fs]] -> 118553 | AQ20: =idp_SP1[[#This Row],[sp1_idp_target_li]]+ndp_SP1[[#This Row],[sp1_ndp_target_li]] -> 0 | AR20: =idp_SP1[[#This Row],[sp1_idp_target_cw]]+ndp_SP1[[#This Row],[sp1_ndp_target_cw]] -> 10266 | AS20: =idp_SP1[[#This Row],[sp1_idp_target_joint]]+ndp_SP1[[#This Row],[sp1_ndp_target_joint]] -> 227145 | AT20: 23078 | AU20: 118553 | AV20: 95410 | AW20: 162720 | AX20: 110476 | AY20: 223122 | AZ20: 162720 | BA20: 87484 | BB20: 74122 | BC20: 118553 | BD20: 0 | BE20: 10266 | BF20: 227145
A21: Ivano-Frankivska | B21: UA26 | C21: All oblast | D21: 50+ | E21: UA26_UALL | F21: 0 | G21: 0 | I21: =idp_SP1[[#This Row],[sp1_idp_pin_ed]]+ndp_SP1[[#This Row],[sp1_ndp_pin_ed]] -> 0 | J21: =idp_SP1[[#This Row],[sp1_idp_pin_fl]]+ndp_SP1[[#This Row],[sp1_ndp_pin_fl]] -> 0 | K21: =idp_SP1[[#This Row],[sp1_idp_pin_he]]+ndp_SP1[[#This Row],[sp1_ndp_pin_he]] -> 0 | L21: =idp_SP1[[#This Row],[sp1_idp_pin_pr]]+ndp_SP1[[#This Row],[sp1_ndp_pin_pr]] -> 0 | M21: =idp_SP1[[#This Row],[sp1_idp_pin_sn]]+ndp_SP1[[#This Row],[sp1_ndp_pin_sn]] -> 0 | N21: =idp_SP1[[#This Row],[sp1_idp_pin_wa]]+ndp_SP1[[#This Row],[sp1_ndp_pin_wa]] -> 0 | O21: =idp_SP1[[#This Row],[sp1_idp_pin_gp]]+ndp_SP1[[#This Row],[sp1_ndp_pin_gp]] -> 0 | P21: =idp_SP1[[#This Row],[sp1_idp_pin_cp]]+ndp_SP1[[#This Row],[sp1_ndp_pin_cp]] -> 0 | Q21: =idp_SP1[[#This Row],[sp1_idp_pin_gb]]+ndp_SP1[[#This Row],[sp1_ndp_pin_gb]] -> 0 | R21: =idp_SP1[[#This Row],[sp1_idp_pin_fs]]+ndp_SP1[[#This Row],[sp1_ndp_pin_fs]] -> 0 | S21: =idp_SP1[[#This Row],[sp1_idp_pin_li]]+ndp_SP1[[#This Row],[sp1_ndp_pin_li]] -> 0 | T21: =idp_SP1[[#This Row],[sp1_idp_pin_adopted]]+ndp_SP1[[#This Row],[sp1_ndp_pin_adopted]] -> 0 | X21: =MAX(idp_SP1[[#This Row],[sp1_idp_sev_pr]],ndp_SP1[[#This Row],[sp1_ndp_sev_pr]]) -> 0 | Y21: 0 | AG21: =idp_SP1[[#This Row],[sp1_idp_target_ed]]+ndp_SP1[[#This Row],[sp1_ndp_target_ed]] -> 0 | AH21: =idp_SP1[[#This Row],[sp1_idp_target_fl]]+ndp_SP1[[#This Row],[sp1_ndp_target_fl]] -> 0 | AI21: =idp_SP1[[#This Row],[sp1_idp_target_he]]+ndp_SP1[[#This Row],[sp1_ndp_target_he]] -> 0 | AJ21: =idp_SP1[[#This Row],[sp1_idp_target_pr]]+ndp_SP1[[#This Row],[sp1_ndp_target_pr]] -> 0 | AK21: =idp_SP1[[#This Row],[sp1_idp_target_sn]]+ndp_SP1[[#This Row],[sp1_ndp_target_sn]] -> 0 | AL21: =idp_SP1[[#This Row],[sp1_idp_target_wa]]+ndp_SP1[[#This Row],[sp1_ndp_target_wa]] -> 0 | AM21: =idp_SP1[[#This Row],[sp1_idp_target_gp]]+ndp_SP1[[#This Row],[sp1_ndp_target_gp]] -> 0 | AN21: =idp_SP1[[#This Row],[sp1_idp_target_cp]]+ndp_SP1[[#This Row],[sp1_ndp_target_cp]] -> 0 | AO21: =idp_SP1[[#This Row],[sp1_idp_target_gb]]+ndp_SP1[[#This Row],[sp1_ndp_target_gb]] -> 0 | AP21: =idp_SP1[[#This Row],[sp1_idp_target_fs]]+ndp_SP1[[#This Row],[sp1_ndp_target_fs]] -> 0 | AQ21: =idp_SP1[[#This Row],[sp1_idp_target_li]]+ndp_SP1[[#This Row],[sp1_ndp_target_li]] -> 0 | AR21: =idp_SP1[[#This Row],[sp1_idp_target_cw]]+ndp_SP1[[#This Row],[sp1_ndp_target_cw]] -> 0 | AS21: =idp_SP1[[#This Row],[sp1_idp_target_joint]]+ndp_SP1[[#This Row],[sp1_ndp_target_joint]] -> 0 | AT21: 0 | AU21: 0 | AV21: 0 | AW21: 0 | AX21: 0 | AY21: 0 | AZ21: 0 | BA21: 0 | BB21: 0 | BC21: 0 | BD21: 0 | BE21: 0 | BF21: 0
A22: Kyivska | B22: UA32 | C22: All oblast | D22: 50+ | E22: UA32_UALL | F22: 0 | G22: 0 | I22: =idp_SP1[[#This Row],[sp1_idp_pin_ed]]+ndp_SP1[[#This Row],[sp1_ndp_pin_ed]] -> 0 | J22: =idp_SP1[[#This Row],[sp1_idp_pin_fl]]+ndp_SP1[[#This Row],[sp1_ndp_pin_fl]] -> 0 | K22: =idp_SP1[[#This Row],[sp1_idp_pin_he]]+ndp_SP1[[#This Row],[sp1_ndp_pin_he]] -> 0 | L22: =idp_SP1[[#This Row],[sp1_idp_pin_pr]]+ndp_SP1[[#This Row],[sp1_ndp_pin_pr]] -> 0 | M22: =idp_SP1[[#This Row],[sp1_idp_pin_sn]]+ndp_SP1[[#This Row],[sp1_ndp_pin_sn]] -> 0 | N22: =idp_SP1[[#This Row],[sp1_idp_pin_wa]]+ndp_SP1[[#This Row],[sp1_ndp_pin_wa]] -> 0 | O22: =idp_SP1[[#This Row],[sp1_idp_pin_gp]]+ndp_SP1[[#This Row],[sp1_ndp_pin_gp]] -> 0 | P22: =idp_SP1[[#This Row],[sp1_idp_pin_cp]]+ndp_SP1[[#This Row],[sp1_ndp_pin_cp]] -> 0 | Q22: =idp_SP1[[#This Row],[sp1_idp_pin_gb]]+ndp_SP1[[#This Row],[sp1_ndp_pin_gb]] -> 0 | R22: =idp_SP1[[#This Row],[sp1_idp_pin_fs]]+ndp_SP1[[#This Row],[sp1_ndp_pin_fs]] -> 0 | S22: =idp_SP1[[#This Row],[sp1_idp_pin_li]]+ndp_SP1[[#This Row],[sp1_ndp_pin_li]] -> 0 | T22: =idp_SP1[[#This Row],[sp1_idp_pin_adopted]]+ndp_SP1[[#This Row],[sp1_ndp_pin_adopted]] -> 0 | X22: =MAX(idp_SP1[[#This Row],[sp1_idp_sev_pr]],ndp_SP1[[#This Row],[sp1_ndp_sev_pr]]) -> 0 | Y22: 0 | AG22: =idp_SP1[[#This Row],[sp1_idp_target_ed]]+ndp_SP1[[#This Row],[sp1_ndp_target_ed]] -> 0 | AH22: =idp_SP1[[#This Row],[sp1_idp_target_fl]]+ndp_SP1[[#This Row],[sp1_ndp_target_fl]] -> 0 | AI22: =idp_SP1[[#This Row],[sp1_idp_target_he]]+ndp_SP1[[#This Row],[sp1_ndp_target_he]] -> 0 | AJ22: =idp_SP1[[#This Row],[sp1_idp_target_pr]]+ndp_SP1[[#This Row],[sp1_ndp_target_pr]] -> 0 | AK22: =idp_SP1[[#This Row],[sp1_idp_target_sn]]+ndp_SP1[[#This Row],[sp1_ndp_target_sn]] -> 0 | AL22: =idp_SP1[[#This Row],[sp1_idp_target_wa]]+ndp_SP1[[#This Row],[sp1_ndp_target_wa]] -> 0 | AM22: =idp_SP1[[#This Row],[sp1_idp_target_gp]]+ndp_SP1[[#This Row],[sp1_ndp_target_gp]] -> 0 | AN22: =idp_SP1[[#This Row],[sp1_idp_target_cp]]+ndp_SP1[[#This Row],[sp1_ndp_target_cp]] -> 0 | AO22: =idp_SP1[[#This Row],[sp1_idp_target_gb]]+ndp_SP1[[#This Row],[sp1_ndp_target_gb]] -> 0 | AP22: =idp_SP1[[#This Row],[sp1_idp_target_fs]]+ndp_SP1[[#This Row],[sp1_ndp_target_fs]] -> 0 | AQ22: =idp_SP1[[#This Row],[sp1_idp_target_li]]+ndp_SP1[[#This Row],[sp1_ndp_target_li]] -> 0 | AR22: =idp_SP1[[#This Row],[sp1_idp_target_cw]]+ndp_SP1[[#This Row],[sp1_ndp_target_cw]] -> 0 | AS22: =idp_SP1[[#This Row],[sp1_idp_target_joint]]+ndp_SP1[[#This Row],[sp1_ndp_target_joint]] -> 0 | AT22: 0 | AU22: 0 | AV22: 0 | AW22: 0 | AX22: 0 | AY22: 0 | AZ22: 0 | BA22: 0 | BB22: 0 | BC22: 0 | BD22: 0 | BE22: 0 | BF22: 0
A23: Kirovohradska | B23: UA35 | C23: All oblast | D23: 50+ | E23: UA35_UALL | F23: 0 | G23: 0 | I23: =idp_SP1[[#This Row],[sp1_idp_pin_ed]]+ndp_SP1[[#This Row],[sp1_ndp_pin_ed]] -> 0 | J23: =idp_SP1[[#This Row],[sp1_idp_pin_fl]]+ndp_SP1[[#This Row],[sp1_ndp_pin_fl]] -> 0 | K23: =idp_SP1[[#This Row],[sp1_idp_pin_he]]+ndp_SP1[[#This Row],[sp1_ndp_pin_he]] -> 0 | L23: =idp_SP1[[#This Row],[sp1_idp_pin_pr]]+ndp_SP1[[#This Row],[sp1_ndp_pin_pr]] -> 0 | M23: =idp_SP1[[#This Row],[sp1_idp_pin_sn]]+ndp_SP1[[#This Row],[sp1_ndp_pin_sn]] -> 0 | N23: =idp_SP1[[#This Row],[sp1_idp_pin_wa]]+ndp_SP1[[#This Row],[sp1_ndp_pin_wa]] -> 0 | O23: =idp_SP1[[#This Row],[sp1_idp_pin_gp]]+ndp_SP1[[#This Row],[sp1_ndp_pin_gp]] -> 0 | P23: =idp_SP1[[#This Row],[sp1_idp_pin_cp]]+ndp_SP1[[#This Row],[sp1_ndp_pin_cp]] -> 0 | Q23: =idp_SP1[[#This Row],[sp1_idp_pin_gb]]+ndp_SP1[[#This Row],[sp1_ndp_pin_gb]] -> 0 | R23: =idp_SP1[[#This Row],[sp1_idp_pin_fs]]+ndp_SP1[[#This Row],[sp1_ndp_pin_fs]] -> 0 | S23: =idp_SP1[[#This Row],[sp1_idp_pin_li]]+ndp_SP1[[#This Row],[sp1_ndp_pin_li]] -> 0 | T23: =idp_SP1[[#This Row],[sp1_idp_pin_adopted]]+ndp_SP1[[#This Row],[sp1_ndp_pin_adopted]] -> 0 | X23: =MAX(idp_SP1[[#This Row],[sp1_idp_sev_pr]],ndp_SP1[[#This Row],[sp1_ndp_sev_pr]]) -> 0 | Y23: 0 | AG23: =idp_SP1[[#This Row],[sp1_idp_target_ed]]+ndp_SP1[[#This Row],[sp1_ndp_target_ed]] -> 0 | AH23: =idp_SP1[[#This Row],[sp1_idp_target_fl]]+ndp_SP1[[#This Row],[sp1_ndp_target_fl]] -> 0 | AI23: =idp_SP1[[#This Row],[sp1_idp_target_he]]+ndp_SP1[[#This Row],[sp1_ndp_target_he]] -> 0 | AJ23: =idp_SP1[[#This Row],[sp1_idp_target_pr]]+ndp_SP1[[#This Row],[sp1_ndp_target_pr]] -> 0 | AK23: =idp_SP1[[#This Row],[sp1_idp_target_sn]]+ndp_SP1[[#This Row],[sp1_ndp_target_sn]] -> 0 | AL23: =idp_SP1[[#This Row],[sp1_idp_target_wa]]+ndp_SP1[[#This Row],[sp1_ndp_target_wa]] -> 0 | AM23: =idp_SP1[[#This Row],[sp1_idp_target_gp]]+ndp_SP1[[#This Row],[sp1_ndp_target_gp]] -> 0 | AN23: =idp_SP1[[#This Row],[sp1_idp_target_cp]]+ndp_SP1[[#This Row],[sp1_ndp_target_cp]] -> 0 | AO23: =idp_SP1[[#This Row],[sp1_idp_target_gb]]+ndp_SP1[[#This Row],[sp1_ndp_target_gb]] -> 0 | AP23: =idp_SP1[[#This Row],[sp1_idp_target_fs]]+ndp_SP1[[#This Row],[sp1_ndp_target_fs]] -> 0 | AQ23: =idp_SP1[[#This Row],[sp1_idp_target_li]]+ndp_SP1[[#This Row],[sp1_ndp_target_li]] -> 0 | AR23: =idp_SP1[[#This Row],[sp1_idp_target_cw]]+ndp_SP1[[#This Row],[sp1_ndp_target_cw]] -> 0 | AS23: =idp_SP1[[#This Row],[sp1_idp_target_joint]]+ndp_SP1[[#This Row],[sp1_ndp_target_joint]] -> 0 | AT23: 0 | AU23: 0 | AV23: 0 | AW23: 0 | AX23: 0 | AY23: 0 | AZ23: 0 | BA23: 0 | BB23: 0 | BC23: 0 | BD23: 0 | BE23: 0 | BF23: 0
A24: Lvivska | B24: UA46 | C24: All oblast | D24: 50+ | E24: UA46_UALL | F24: 0 | G24: 0 | I24: =idp_SP1[[#This Row],[sp1_idp_pin_ed]]+ndp_SP1[[#This Row],[sp1_ndp_pin_ed]] -> 0 | J24: =idp_SP1[[#This Row],[sp1_idp_pin_fl]]+ndp_SP1[[#This Row],[sp1_ndp_pin_fl]] -> 0 | K24: =idp_SP1[[#This Row],[sp1_idp_pin_he]]+ndp_SP1[[#This Row],[sp1_ndp_pin_he]] -> 0 | L24: =idp_SP1[[#This Row],[sp1_idp_pin_pr]]+ndp_SP1[[#This Row],[sp1_ndp_pin_pr]] -> 0 | M24: =idp_SP1[[#This Row],[sp1_idp_pin_sn]]+ndp_SP1[[#This Row],[sp1_ndp_pin_sn]] -> 0 | N24: =idp_SP1[[#This Row],[sp1_idp_pin_wa]]+ndp_SP1[[#This Row],[sp1_ndp_pin_wa]] -> 0 | O24: =idp_SP1[[#This Row],[sp1_idp_pin_gp]]+ndp_SP1[[#This Row],[sp1_ndp_pin_gp]] -> 0 | P24: =idp_SP1[[#This Row],[sp1_idp_pin_cp]]+ndp_SP1[[#This Row],[sp1_ndp_pin_cp]] -> 0 | Q24: =idp_SP1[[#This Row],[sp1_idp_pin_gb]]+ndp_SP1[[#This Row],[sp1_ndp_pin_gb]] -> 0 | R24: =idp_SP1[[#This Row],[sp1_idp_pin_fs]]+ndp_SP1[[#This Row],[sp1_ndp_pin_fs]] -> 0 | S24: =idp_SP1[[#This Row],[sp1_idp_pin_li]]+ndp_SP1[[#This Row],[sp1_ndp_pin_li]] -> 0 | T24: =idp_SP1[[#This Row],[sp1_idp_pin_adopted]]+ndp_SP1[[#This Row],[sp1_ndp_pin_adopted]] -> 0 | X24: =MAX(idp_SP1[[#This Row],[sp1_idp_sev_pr]],ndp_SP1[[#This Row],[sp1_ndp_sev_pr]]) -> 0 | Y24: 0 | AG24: =idp_SP1[[#This Row],[sp1_idp_target_ed]]+ndp_SP1[[#This Row],[sp1_ndp_target_ed]] -> 0 | AH24: =idp_SP1[[#This Row],[sp1_idp_target_fl]]+ndp_SP1[[#This Row],[sp1_ndp_target_fl]] -> 0 | AI24: =idp_SP1[[#This Row],[sp1_idp_target_he]]+ndp_SP1[[#This Row],[sp1_ndp_target_he]] -> 0 | AJ24: =idp_SP1[[#This Row],[sp1_idp_target_pr]]+ndp_SP1[[#This Row],[sp1_ndp_target_pr]] -> 0 | AK24: =idp_SP1[[#This Row],[sp1_idp_target_sn]]+ndp_SP1[[#This Row],[sp1_ndp_target_sn]] -> 0 | AL24: =idp_SP1[[#This Row],[sp1_idp_target_wa]]+ndp_SP1[[#This Row],[sp1_ndp_target_wa]] -> 0 | AM24: =idp_SP1[[#This Row],[sp1_idp_target_gp]]+ndp_SP1[[#This Row],[sp1_ndp_target_gp]] -> 0 | AN24: =idp_SP1[[#This Row],[sp1_idp_target_cp]]+ndp_SP1[[#This Row],[sp1_ndp_target_cp]] -> 0 | AO24: =idp_SP1[[#This Row],[sp1_idp_target_gb]]+ndp_SP1[[#This Row],[sp1_ndp_target_gb]] -> 0 | AP24: =idp_SP1[[#This Row],[sp1_idp_target_fs]]+ndp_SP1[[#This Row],[sp1_ndp_target_fs]] -> 0 | AQ24: =idp_SP1[[#This Row],[sp1_idp_target_li]]+ndp_SP1[[#This Row],[sp1_ndp_target_li]] -> 0 | AR24: =idp_SP1[[#This Row],[sp1_idp_target_cw]]+ndp_SP1[[#This Row],[sp1_ndp_target_cw]] -> 0 | AS24: =idp_SP1[[#This Row],[sp1_idp_target_joint]]+ndp_SP1[[#This Row],[sp1_ndp_target_joint]] -> 0 | AT24: 0 | AU24: 0 | AV24: 0 | AW24: 0 | AX24: 0 | AY24: 0 | AZ24: 0 | BA24: 0 | BB24: 0 | BC24: 0 | BD24: 0 | BE24: 0 | BF24: 0
A25: Mykolaivska | B25: UA48 | C25: 0-20 km | D25: 0-20km | E25: UA48_U20A | F25: 5384 | G25: 20407 | H25: 25791 | I25: =idp_SP1[[#This Row],[sp1_idp_pin_ed]]+ndp_SP1[[#This Row],[sp1_ndp_pin_ed]] -> 2140 | J25: =idp_SP1[[#This Row],[sp1_idp_pin_fl]]+ndp_SP1[[#This Row],[sp1_ndp_pin_fl]] -> 8926 | K25: =idp_SP1[[#This Row],[sp1_idp_pin_he]]+ndp_SP1[[#This Row],[sp1_ndp_pin_he]] -> 20008 | L25: =idp_SP1[[#This Row],[sp1_idp_pin_pr]]+ndp_SP1[[#This Row],[sp1_ndp_pin_pr]] -> 20824 | M25: =idp_SP1[[#This Row],[sp1_idp_pin_sn]]+ndp_SP1[[#This Row],[sp1_ndp_pin_sn]] -> 18756 | N25: =idp_SP1[[#This Row],[sp1_idp_pin_wa]]+ndp_SP1[[#This Row],[sp1_ndp_pin_wa]] -> 15474 | O25: =idp_SP1[[#This Row],[sp1_idp_pin_gp]]+ndp_SP1[[#This Row],[sp1_ndp_pin_gp]] -> 20824 | P25: =idp_SP1[[#This Row],[sp1_idp_pin_cp]]+ndp_SP1[[#This Row],[sp1_ndp_pin_cp]] -> 7190 | Q25: =idp_SP1[[#This Row],[sp1_idp_pin_gb]]+ndp_SP1[[#This Row],[sp1_ndp_pin_gb]] -> 10111 | R25: =idp_SP1[[#This Row],[sp1_idp_pin_fs]]+ndp_SP1[[#This Row],[sp1_ndp_pin_fs]] -> 8926 | S25: =idp_SP1[[#This Row],[sp1_idp_pin_li]]+ndp_SP1[[#This Row],[sp1_ndp_pin_li]] -> 0 | T25: =idp_SP1[[#This Row],[sp1_idp_pin_adopted]]+ndp_SP1[[#This Row],[sp1_ndp_pin_adopted]] -> 20824 | U25: 4 | V25: 4 | W25: 4 | X25: =MAX(idp_SP1[[#This Row],[sp1_idp_sev_pr]],ndp_SP1[[#This Row],[sp1_ndp_sev_pr]]) -> 4 | Y25: 5 | Z25: 4 | AA25: 4 | AB25: 4 | AC25: 4 | AD25: 4 | AE25: 4 | AF25: 4 | AG25: =idp_SP1[[#This Row],[sp1_idp_target_ed]]+ndp_SP1[[#This Row],[sp1_ndp_target_ed]] -> 1927 | AH25: =idp_SP1[[#This Row],[sp1_idp_target_fl]]+ndp_SP1[[#This Row],[sp1_ndp_target_fl]] -> 8926 | AI25: =idp_SP1[[#This Row],[sp1_idp_target_he]]+ndp_SP1[[#This Row],[sp1_ndp_target_he]] -> 11768 | AJ25: =idp_SP1[[#This Row],[sp1_idp_target_pr]]+ndp_SP1[[#This Row],[sp1_ndp_target_pr]] -> 9158 | AK25: =idp_SP1[[#This Row],[sp1_idp_target_sn]]+ndp_SP1[[#This Row],[sp1_ndp_target_sn]] -> 14042 | AL25: =idp_SP1[[#This Row],[sp1_idp_target_wa]]+ndp_SP1[[#This Row],[sp1_ndp_target_wa]] -> 15474 | AM25: =idp_SP1[[#This Row],[sp1_idp_target_gp]]+ndp_SP1[[#This Row],[sp1_ndp_target_gp]] -> 9158 | AN25: =idp_SP1[[#This Row],[sp1_idp_target_cp]]+ndp_SP1[[#This Row],[sp1_ndp_target_cp]] -> 5760 | AO25: =idp_SP1[[#This Row],[sp1_idp_target_gb]]+ndp_SP1[[#This Row],[sp1_ndp_target_gb]] -> 506 | AP25: =idp_SP1[[#This Row],[sp1_idp_target_fs]]+ndp_SP1[[#This Row],[sp1_ndp_target_fs]] -> 8926 | AQ25: =idp_SP1[[#This Row],[sp1_idp_target_li]]+ndp_SP1[[#This Row],[sp1_ndp_target_li]] -> 0 | AR25: =idp_SP1[[#This Row],[sp1_idp_target_cw]]+ndp_SP1[[#This Row],[sp1_ndp_target_cw]] -> 11451 | AS25: =idp_SP1[[#This Row],[sp1_idp_target_joint]]+ndp_SP1[[#This Row],[sp1_ndp_target_joint]] -> 15749 | AT25: 1927 | AU25: 8926 | AV25: 11768 | AW25: 9158 | AX25: 14042 | AY25: 15474 | AZ25: 9158 | BA25: 5760 | BB25: 506 | BC25: 8926 | BD25: 0 | BE25: 11451 | BF25: 15749
A26: Mykolaivska | B26: UA48 | C26: 21-50 km (w/o Mykolaiv) | D26: 20-50km | E26: UA48_U50X | F26: 8270 | G26: 24448.662 | H26: 32718.662 | I26: =idp_SP1[[#This Row],[sp1_idp_pin_ed]]+ndp_SP1[[#This Row],[sp1_ndp_pin_ed]] -> 2951 | J26: =idp_SP1[[#This Row],[sp1_idp_pin_fl]]+ndp_SP1[[#This Row],[sp1_ndp_pin_fl]] -> 5756 | K26: =idp_SP1[[#This Row],[sp1_idp_pin_he]]+ndp_SP1[[#This Row],[sp1_ndp_pin_he]] -> 25383 | L26: =idp_SP1[[#This Row],[sp1_idp_pin_pr]]+ndp_SP1[[#This Row],[sp1_ndp_pin_pr]] -> 19399 | M26: =idp_SP1[[#This Row],[sp1_idp_pin_sn]]+ndp_SP1[[#This Row],[sp1_ndp_pin_sn]] -> 17404 | N26: =idp_SP1[[#This Row],[sp1_idp_pin_wa]]+ndp_SP1[[#This Row],[sp1_ndp_pin_wa]] -> 22428 | O26: =idp_SP1[[#This Row],[sp1_idp_pin_gp]]+ndp_SP1[[#This Row],[sp1_ndp_pin_gp]] -> 19399 | P26: =idp_SP1[[#This Row],[sp1_idp_pin_cp]]+ndp_SP1[[#This Row],[sp1_ndp_pin_cp]] -> 8282 | Q26: =idp_SP1[[#This Row],[sp1_idp_pin_gb]]+ndp_SP1[[#This Row],[sp1_ndp_pin_gb]] -> 12826 | R26: =idp_SP1[[#This Row],[sp1_idp_pin_fs]]+ndp_SP1[[#This Row],[sp1_ndp_pin_fs]] -> 5756 | S26: =idp_SP1[[#This Row],[sp1_idp_pin_li]]+ndp_SP1[[#This Row],[sp1_ndp_pin_li]] -> 0 | T26: =idp_SP1[[#This Row],[sp1_idp_pin_adopted]]+ndp_SP1[[#This Row],[sp1_ndp_pin_adopted]] -> 25383 | U26: 4 | V26: 4 | W26: 4 | X26: =MAX(idp_SP1[[#This Row],[sp1_idp_sev_pr]],ndp_SP1[[#This Row],[sp1_ndp_sev_pr]]) -> 4 | Y26: 3 | Z26: 3 | AA26: 4 | AB26: 4 | AC26: 4 | AD26: 4 | AE26: 4 | AF26: 4 | AG26: =idp_SP1[[#This Row],[sp1_idp_target_ed]]+ndp_SP1[[#This Row],[sp1_ndp_target_ed]] -> 2656 | AH26: =idp_SP1[[#This Row],[sp1_idp_target_fl]]+ndp_SP1[[#This Row],[sp1_ndp_target_fl]] -> 5756 | AI26: =idp_SP1[[#This Row],[sp1_idp_target_he]]+ndp_SP1[[#This Row],[sp1_ndp_target_he]] -> 12047 | AJ26: =idp_SP1[[#This Row],[sp1_idp_target_pr]]+ndp_SP1[[#This Row],[sp1_ndp_target_pr]] -> 9341 | AK26: =idp_SP1[[#This Row],[sp1_idp_target_sn]]+ndp_SP1[[#This Row],[sp1_ndp_target_sn]] -> 5086 | AL26: =idp_SP1[[#This Row],[sp1_idp_target_wa]]+ndp_SP1[[#This Row],[sp1_ndp_target_wa]] -> 11213 | AM26: =idp_SP1[[#This Row],[sp1_idp_target_gp]]+ndp_SP1[[#This Row],[sp1_ndp_target_gp]] -> 9216 | AN26: =idp_SP1[[#This Row],[sp1_idp_target_cp]]+ndp_SP1[[#This Row],[sp1_ndp_target_cp]] -> 6237 | AO26: =idp_SP1[[#This Row],[sp1_idp_target_gb]]+ndp_SP1[[#This Row],[sp1_ndp_target_gb]] -> 6413 | AP26: =idp_SP1[[#This Row],[sp1_idp_target_fs]]+ndp_SP1[[#This Row],[sp1_ndp_target_fs]] -> 5756 | AQ26: =idp_SP1[[#This Row],[sp1_idp_target_li]]+ndp_SP1[[#This Row],[sp1_ndp_target_li]] -> 0 | AR26: =idp_SP1[[#This Row],[sp1_idp_target_cw]]+ndp_SP1[[#This Row],[sp1_ndp_target_cw]] -> 1990 | AS26: =idp_SP1[[#This Row],[sp1_idp_target_joint]]+ndp_SP1[[#This Row],[sp1_ndp_target_joint]] -> 13512 | AT26: 2656 | AU26: 2315 | AV26: 6516 | AW26: 9341 | AX26: 1017 | AY26: 2243 | AZ26: 9216 | BA26: 6237 | BB26: 6413 | BC26: 2315 | BD26: 0 | BE26: 823 | BF26: 9925
A27: Mykolaivska | B27: UA48 | C27: 51+ km | D27: 50+ | E27: UA48_U51P | F27: 0 | G27: 0 | I27: =idp_SP1[[#This Row],[sp1_idp_pin_ed]]+ndp_SP1[[#This Row],[sp1_ndp_pin_ed]] -> 0 | J27: =idp_SP1[[#This Row],[sp1_idp_pin_fl]]+ndp_SP1[[#This Row],[sp1_ndp_pin_fl]] -> 0 | K27: =idp_SP1[[#This Row],[sp1_idp_pin_he]]+ndp_SP1[[#This Row],[sp1_ndp_pin_he]] -> 0 | L27: =idp_SP1[[#This Row],[sp1_idp_pin_pr]]+ndp_SP1[[#This Row],[sp1_ndp_pin_pr]] -> 0 | M27: =idp_SP1[[#This Row],[sp1_idp_pin_sn]]+ndp_SP1[[#This Row],[sp1_ndp_pin_sn]] -> 0 | N27: =idp_SP1[[#This Row],[sp1_idp_pin_wa]]+ndp_SP1[[#This Row],[sp1_ndp_pin_wa]] -> 0 | O27: =idp_SP1[[#This Row],[sp1_idp_pin_gp]]+ndp_SP1[[#This Row],[sp1_ndp_pin_gp]] -> 0 | P27: =idp_SP1[[#This Row],[sp1_idp_pin_cp]]+ndp_SP1[[#This Row],[sp1_ndp_pin_cp]] -> 0 | Q27: =idp_SP1[[#This Row],[sp1_idp_pin_gb]]+ndp_SP1[[#This Row],[sp1_ndp_pin_gb]] -> 0 | R27: =idp_SP1[[#This Row],[sp1_idp_pin_fs]]+ndp_SP1[[#This Row],[sp1_ndp_pin_fs]] -> 0 | S27: =idp_SP1[[#This Row],[sp1_idp_pin_li]]+ndp_SP1[[#This Row],[sp1_ndp_pin_li]] -> 0 | T27: =idp_SP1[[#This Row],[sp1_idp_pin_adopted]]+ndp_SP1[[#This Row],[sp1_ndp_pin_adopted]] -> 0 | X27: =MAX(idp_SP1[[#This Row],[sp1_idp_sev_pr]],ndp_SP1[[#This Row],[sp1_ndp_sev_pr]]) -> 0 | Y27: 0 | AG27: =idp_SP1[[#This Row],[sp1_idp_target_ed]]+ndp_SP1[[#This Row],[sp1_ndp_target_ed]] -> 0 | AH27: =idp_SP1[[#This Row],[sp1_idp_target_fl]]+ndp_SP1[[#This Row],[sp1_ndp_target_fl]] -> 0 | AI27: =idp_SP1[[#This Row],[sp1_idp_target_he]]+ndp_SP1[[#This Row],[sp1_ndp_target_he]] -> 0 | AJ27: =idp_SP1[[#This Row],[sp1_idp_target_pr]]+ndp_SP1[[#This Row],[sp1_ndp_target_pr]] -> 0 | AK27: =idp_SP1[[#This Row],[sp1_idp_target_sn]]+ndp_SP1[[#This Row],[sp1_ndp_target_sn]] -> 0 | AL27: =idp_SP1[[#This Row],[sp1_idp_target_wa]]+ndp_SP1[[#This Row],[sp1_ndp_target_wa]] -> 0 | AM27: =idp_SP1[[#This Row],[sp1_idp_target_gp]]+ndp_SP1[[#This Row],[sp1_ndp_target_gp]] -> 0 | AN27: =idp_SP1[[#This Row],[sp1_idp_target_cp]]+ndp_SP1[[#This Row],[sp1_ndp_target_cp]] -> 0 | AO27: =idp_SP1[[#This Row],[sp1_idp_target_gb]]+ndp_SP1[[#This Row],[sp1_ndp_target_gb]] -> 0 | AP27: =idp_SP1[[#This Row],[sp1_idp_target_fs]]+ndp_SP1[[#This Row],[sp1_ndp_target_fs]] -> 0 | AQ27: =idp_SP1[[#This Row],[sp1_idp_target_li]]+ndp_SP1[[#This Row],[sp1_ndp_target_li]] -> 0 | AR27: =idp_SP1[[#This Row],[sp1_idp_target_cw]]+ndp_SP1[[#This Row],[sp1_ndp_target_cw]] -> 0 | AS27: =idp_SP1[[#This Row],[sp1_idp_target_joint]]+ndp_SP1[[#This Row],[sp1_ndp_target_joint]] -> 0 | AT27: 0 | AU27: 0 | AV27: 0 | AW27: 0 | AX27: 0 | AY27: 0 | AZ27: 0 | BA27: 0 | BB27: 0 | BC27: 0 | BD27: 0 | BE27: 0 | BF27: 0
A28: Mykolaivska | B28: UA48 | C28: Mykolaiv city | D28: 20-50km | E28: UA48_UCAP | F28: 39435 | G28: 139009.71 | H28: 178444.71 | I28: =idp_SP1[[#This Row],[sp1_idp_pin_ed]]+ndp_SP1[[#This Row],[sp1_ndp_pin_ed]] -> 10883 | J28: =idp_SP1[[#This Row],[sp1_idp_pin_fl]]+ndp_SP1[[#This Row],[sp1_ndp_pin_fl]] -> 28313 | K28: =idp_SP1[[#This Row],[sp1_idp_pin_he]]+ndp_SP1[[#This Row],[sp1_ndp_pin_he]] -> 138433 | L28: =idp_SP1[[#This Row],[sp1_idp_pin_pr]]+ndp_SP1[[#This Row],[sp1_ndp_pin_pr]] -> 119262 | M28: =idp_SP1[[#This Row],[sp1_idp_pin_sn]]+ndp_SP1[[#This Row],[sp1_ndp_pin_sn]] -> 88373 | N28: =idp_SP1[[#This Row],[sp1_idp_pin_wa]]+ndp_SP1[[#This Row],[sp1_ndp_pin_wa]] -> 163150 | O28: =idp_SP1[[#This Row],[sp1_idp_pin_gp]]+ndp_SP1[[#This Row],[sp1_ndp_pin_gp]] -> 119262 | P28: =idp_SP1[[#This Row],[sp1_idp_pin_cp]]+ndp_SP1[[#This Row],[sp1_ndp_pin_cp]] -> 50949 | Q28: =idp_SP1[[#This Row],[sp1_idp_pin_gb]]+ndp_SP1[[#This Row],[sp1_ndp_pin_gb]] -> 69951 | R28: =idp_SP1[[#This Row],[sp1_idp_pin_fs]]+ndp_SP1[[#This Row],[sp1_ndp_pin_fs]] -> 28313 | S28: =idp_SP1[[#This Row],[sp1_idp_pin_li]]+ndp_SP1[[#This Row],[sp1_ndp_pin_li]] -> 0 | T28: =idp_SP1[[#This Row],[sp1_idp_pin_adopted]]+ndp_SP1[[#This Row],[sp1_ndp_pin_adopted]] -> 163150 | U28: 4 | V28: 4 | W28: 4 | X28: =MAX(idp_SP1[[#This Row],[sp1_idp_sev_pr]],ndp_SP1[[#This Row],[sp1_ndp_sev_pr]]) -> 4 | Y28: 4 | Z28: 4 | AA28: 4 | AB28: 4 | AC28: 4 | AD28: 4 | AE28: 4 | AF28: 4 | AG28: =idp_SP1[[#This Row],[sp1_idp_target_ed]]+ndp_SP1[[#This Row],[sp1_ndp_target_ed]] -> 9795 | AH28: =idp_SP1[[#This Row],[sp1_idp_target_fl]]+ndp_SP1[[#This Row],[sp1_ndp_target_fl]] -> 28313 | AI28: =idp_SP1[[#This Row],[sp1_idp_target_he]]+ndp_SP1[[#This Row],[sp1_ndp_target_he]] -> 94991 | AJ28: =idp_SP1[[#This Row],[sp1_idp_target_pr]]+ndp_SP1[[#This Row],[sp1_ndp_target_pr]] -> 55579 | AK28: =idp_SP1[[#This Row],[sp1_idp_target_sn]]+ndp_SP1[[#This Row],[sp1_ndp_target_sn]] -> 28903 | AL28: =idp_SP1[[#This Row],[sp1_idp_target_wa]]+ndp_SP1[[#This Row],[sp1_ndp_target_wa]] -> 163150 | AM28: =idp_SP1[[#This Row],[sp1_idp_target_gp]]+ndp_SP1[[#This Row],[sp1_ndp_target_gp]] -> 55579 | AN28: =idp_SP1[[#This Row],[sp1_idp_target_cp]]+ndp_SP1[[#This Row],[sp1_ndp_target_cp]] -> 25034 | AO28: =idp_SP1[[#This Row],[sp1_idp_target_gb]]+ndp_SP1[[#This Row],[sp1_ndp_target_gb]] -> 34975 | AP28: =idp_SP1[[#This Row],[sp1_idp_target_fs]]+ndp_SP1[[#This Row],[sp1_ndp_target_fs]] -> 28313 | AQ28: =idp_SP1[[#This Row],[sp1_idp_target_li]]+ndp_SP1[[#This Row],[sp1_ndp_target_li]] -> 0 | AR28: =idp_SP1[[#This Row],[sp1_idp_target_cw]]+ndp_SP1[[#This Row],[sp1_ndp_target_cw]] -> 10394 | AS28: =idp_SP1[[#This Row],[sp1_idp_target_joint]]+ndp_SP1[[#This Row],[sp1_ndp_target_joint]] -> 163150 | AT28: 9795 | AU28: 28313 | AV28: 94991 | AW28: 55579 | AX28: 28903 | AY28: 163150 | AZ28: 55579 | BA28: 13052 | BB28: 34975 | BC28: 28313 | BD28: 0 | BE28: 10394 | BF28: 163150
A29: Odeska | B29: UA51 | C29: All oblast | D29: 50+ | E29: UA51_UALL | F29: 0 | G29: 0 | I29: =idp_SP1[[#This Row],[sp1_idp_pin_ed]]+ndp_SP1[[#This Row],[sp1_ndp_pin_ed]] -> 0 | J29: =idp_SP1[[#This Row],[sp1_idp_pin_fl]]+ndp_SP1[[#This Row],[sp1_ndp_pin_fl]] -> 0 | K29: =idp_SP1[[#This Row],[sp1_idp_pin_he]]+ndp_SP1[[#This Row],[sp1_ndp_pin_he]] -> 0 | L29: =idp_SP1[[#This Row],[sp1_idp_pin_pr]]+ndp_SP1[[#This Row],[sp1_ndp_pin_pr]] -> 0 | M29: =idp_SP1[[#This Row],[sp1_idp_pin_sn]]+ndp_SP1[[#This Row],[sp1_ndp_pin_sn]] -> 0 | N29: =idp_SP1[[#This Row],[sp1_idp_pin_wa]]+ndp_SP1[[#This Row],[sp1_ndp_pin_wa]] -> 0 | O29: =idp_SP1[[#This Row],[sp1_idp_pin_gp]]+ndp_SP1[[#This Row],[sp1_ndp_pin_gp]] -> 0 | P29: =idp_SP1[[#This Row],[sp1_idp_pin_cp]]+ndp_SP1[[#This Row],[sp1_ndp_pin_cp]] -> 0 | Q29: =idp_SP1[[#This Row],[sp1_idp_pin_gb]]+ndp_SP1[[#This Row],[sp1_ndp_pin_gb]] -> 0 | R29: =idp_SP1[[#This Row],[sp1_idp_pin_fs]]+ndp_SP1[[#This Row],[sp1_ndp_pin_fs]] -> 0 | S29: =idp_SP1[[#This Row],[sp1_idp_pin_li]]+ndp_SP1[[#This Row],[sp1_ndp_pin_li]] -> 0 | T29: =idp_SP1[[#This Row],[sp1_idp_pin_adopted]]+ndp_SP1[[#This Row],[sp1_ndp_pin_adopted]] -> 0 | X29: =MAX(idp_SP1[[#This Row],[sp1_idp_sev_pr]],ndp_SP1[[#This Row],[sp1_ndp_sev_pr]]) -> 0 | Y29: 0 | AG29: =idp_SP1[[#This Row],[sp1_idp_target_ed]]+ndp_SP1[[#This Row],[sp1_ndp_target_ed]] -> 0 | AH29: =idp_SP1[[#This Row],[sp1_idp_target_fl]]+ndp_SP1[[#This Row],[sp1_ndp_target_fl]] -> 0 | AI29: =idp_SP1[[#This Row],[sp1_idp_target_he]]+ndp_SP1[[#This Row],[sp1_ndp_target_he]] -> 0 | AJ29: =idp_SP1[[#This Row],[sp1_idp_target_pr]]+ndp_SP1[[#This Row],[sp1_ndp_target_pr]] -> 0 | AK29: =idp_SP1[[#This Row],[sp1_idp_target_sn]]+ndp_SP1[[#This Row],[sp1_ndp_target_sn]] -> 0 | AL29: =idp_SP1[[#This Row],[sp1_idp_target_wa]]+ndp_SP1[[#This Row],[sp1_ndp_target_wa]] -> 0 | AM29: =idp_SP1[[#This Row],[sp1_idp_target_gp]]+ndp_SP1[[#This Row],[sp1_ndp_target_gp]] -> 0 | AN29: =idp_SP1[[#This Row],[sp1_idp_target_cp]]+ndp_SP1[[#This Row],[sp1_ndp_target_cp]] -> 0 | AO29: =idp_SP1[[#This Row],[sp1_idp_target_gb]]+ndp_SP1[[#This Row],[sp1_ndp_target_gb]] -> 0 | AP29: =idp_SP1[[#This Row],[sp1_idp_target_fs]]+ndp_SP1[[#This Row],[sp1_ndp_target_fs]] -> 0 | AQ29: =idp_SP1[[#This Row],[sp1_idp_target_li]]+ndp_SP1[[#This Row],[sp1_ndp_target_li]] -> 0 | AR29: =idp_SP1[[#This Row],[sp1_idp_target_cw]]+ndp_SP1[[#This Row],[sp1_ndp_target_cw]] -> 0 | AS29: =idp_SP1[[#This Row],[sp1_idp_target_joint]]+ndp_SP1[[#This Row],[sp1_ndp_target_joint]] -> 0 | AT29: 0 | AU29: 0 | AV29: 0 | AW29: 0 | AX29: 0 | AY29: 0 | AZ29: 0 | BA29: 0 | BB29: 0 | BC29: 0 | BD29: 0 | BE29: 0 | BF29: 0
A30: Poltavska | B30: UA53 | C30: All oblast | D30: 50+ | E30: UA53_UALL | F30: 0 | G30: 0 | I30: =idp_SP1[[#This Row],[sp1_idp_pin_ed]]+ndp_SP1[[#This Row],[sp1_ndp_pin_ed]] -> 0 | J30: =idp_SP1[[#This Row],[sp1_idp_pin_fl]]+ndp_SP1[[#This Row],[sp1_ndp_pin_fl]] -> 0 | K30: =idp_SP1[[#This Row],[sp1_idp_pin_he]]+ndp_SP1[[#This Row],[sp1_ndp_pin_he]] -> 0 | L30: =idp_SP1[[#This Row],[sp1_idp_pin_pr]]+ndp_SP1[[#This Row],[sp1_ndp_pin_pr]] -> 0 | M30: =idp_SP1[[#This Row],[sp1_idp_pin_sn]]+ndp_SP1[[#This Row],[sp1_ndp_pin_sn]] -> 0 | N30: =idp_SP1[[#This Row],[sp1_idp_pin_wa]]+ndp_SP1[[#This Row],[sp1_ndp_pin_wa]] -> 0 | O30: =idp_SP1[[#This Row],[sp1_idp_pin_gp]]+ndp_SP1[[#This Row],[sp1_ndp_pin_gp]] -> 0 | P30: =idp_SP1[[#This Row],[sp1_idp_pin_cp]]+ndp_SP1[[#This Row],[sp1_ndp_pin_cp]] -> 0 | Q30: =idp_SP1[[#This Row],[sp1_idp_pin_gb]]+ndp_SP1[[#This Row],[sp1_ndp_pin_gb]] -> 0 | R30: =idp_SP1[[#This Row],[sp1_idp_pin_fs]]+ndp_SP1[[#This Row],[sp1_ndp_pin_fs]] -> 0 | S30: =idp_SP1[[#This Row],[sp1_idp_pin_li]]+ndp_SP1[[#This Row],[sp1_ndp_pin_li]] -> 0 | T30: =idp_SP1[[#This Row],[sp1_idp_pin_adopted]]+ndp_SP1[[#This Row],[sp1_ndp_pin_adopted]] -> 0 | X30: =MAX(idp_SP1[[#This Row],[sp1_idp_sev_pr]],ndp_SP1[[#This Row],[sp1_ndp_sev_pr]]) -> 0 | Y30: 0 | AG30: =idp_SP1[[#This Row],[sp1_idp_target_ed]]+ndp_SP1[[#This Row],[sp1_ndp_target_ed]] -> 0 | AH30: =idp_SP1[[#This Row],[sp1_idp_target_fl]]+ndp_SP1[[#This Row],[sp1_ndp_target_fl]] -> 0 | AI30: =idp_SP1[[#This Row],[sp1_idp_target_he]]+ndp_SP1[[#This Row],[sp1_ndp_target_he]] -> 0 | AJ30: =idp_SP1[[#This Row],[sp1_idp_target_pr]]+ndp_SP1[[#This Row],[sp1_ndp_target_pr]] -> 0 | AK30: =idp_SP1[[#This Row],[sp1_idp_target_sn]]+ndp_SP1[[#This Row],[sp1_ndp_target_sn]] -> 0 | AL30: =idp_SP1[[#This Row],[sp1_idp_target_wa]]+ndp_SP1[[#This Row],[sp1_ndp_target_wa]] -> 0 | AM30: =idp_SP1[[#This Row],[sp1_idp_target_gp]]+ndp_SP1[[#This Row],[sp1_ndp_target_gp]] -> 0 | AN30: =idp_SP1[[#This Row],[sp1_idp_target_cp]]+ndp_SP1[[#This Row],[sp1_ndp_target_cp]] -> 0 | AO30: =idp_SP1[[#This Row],[sp1_idp_target_gb]]+ndp_SP1[[#This Row],[sp1_ndp_target_gb]] -> 0 | AP30: =idp_SP1[[#This Row],[sp1_idp_target_fs]]+ndp_SP1[[#This Row],[sp1_ndp_target_fs]] -> 0 | AQ30: =idp_SP1[[#This Row],[sp1_idp_target_li]]+ndp_SP1[[#This Row],[sp1_ndp_target_li]] -> 0 | AR30: =idp_SP1[[#This Row],[sp1_idp_target_cw]]+ndp_SP1[[#This Row],[sp1_ndp_target_cw]] -> 0 | AS30: =idp_SP1[[#This Row],[sp1_idp_target_joint]]+ndp_SP1[[#This Row],[sp1_ndp_target_joint]] -> 0 | AT30: 0 | AU30: 0 | AV30: 0 | AW30: 0 | AX30: 0 | AY30: 0 | AZ30: 0 | BA30: 0 | BB30: 0 | BC30: 0 | BD30: 0 | BE30: 0 | BF30: 0
A31: Rivnenska | B31: UA56 | C31: All oblast | D31: 50+ | E31: UA56_UALL | F31: 0 | G31: 0 | I31: =idp_SP1[[#This Row],[sp1_idp_pin_ed]]+ndp_SP1[[#This Row],[sp1_ndp_pin_ed]] -> 0 | J31: =idp_SP1[[#This Row],[sp1_idp_pin_fl]]+ndp_SP1[[#This Row],[sp1_ndp_pin_fl]] -> 0 | K31: =idp_SP1[[#This Row],[sp1_idp_pin_he]]+ndp_SP1[[#This Row],[sp1_ndp_pin_he]] -> 0 | L31: =idp_SP1[[#This Row],[sp1_idp_pin_pr]]+ndp_SP1[[#This Row],[sp1_ndp_pin_pr]] -> 0 | M31: =idp_SP1[[#This Row],[sp1_idp_pin_sn]]+ndp_SP1[[#This Row],[sp1_ndp_pin_sn]] -> 0 | N31: =idp_SP1[[#This Row],[sp1_idp_pin_wa]]+ndp_SP1[[#This Row],[sp1_ndp_pin_wa]] -> 0 | O31: =idp_SP1[[#This Row],[sp1_idp_pin_gp]]+ndp_SP1[[#This Row],[sp1_ndp_pin_gp]] -> 0 | P31: =idp_SP1[[#This Row],[sp1_idp_pin_cp]]+ndp_SP1[[#This Row],[sp1_ndp_pin_cp]] -> 0 | Q31: =idp_SP1[[#This Row],[sp1_idp_pin_gb]]+ndp_SP1[[#This Row],[sp1_ndp_pin_gb]] -> 0 | R31: =idp_SP1[[#This Row],[sp1_idp_pin_fs]]+ndp_SP1[[#This Row],[sp1_ndp_pin_fs]] -> 0 | S31: =idp_SP1[[#This Row],[sp1_idp_pin_li]]+ndp_SP1[[#This Row],[sp1_ndp_pin_li]] -> 0 | T31: =idp_SP1[[#This Row],[sp1_idp_pin_adopted]]+ndp_SP1[[#This Row],[sp1_ndp_pin_adopted]] -> 0 | X31: =MAX(idp_SP1[[#This Row],[sp1_idp_sev_pr]],ndp_SP1[[#This Row],[sp1_ndp_sev_pr]]) -> 0 | Y31: 0 | AG31: =idp_SP1[[#This Row],[sp1_idp_target_ed]]+ndp_SP1[[#This Row],[sp1_ndp_target_ed]] -> 0 | AH31: =idp_SP1[[#This Row],[sp1_idp_target_fl]]+ndp_SP1[[#This Row],[sp1_ndp_target_fl]] -> 0 | AI31: =idp_SP1[[#This Row],[sp1_idp_target_he]]+ndp_SP1[[#This Row],[sp1_ndp_target_he]] -> 0 | AJ31: =idp_SP1[[#This Row],[sp1_idp_target_pr]]+ndp_SP1[[#This Row],[sp1_ndp_target_pr]] -> 0 | AK31: =idp_SP1[[#This Row],[sp1_idp_target_sn]]+ndp_SP1[[#This Row],[sp1_ndp_target_sn]] -> 0 | AL31: =idp_SP1[[#This Row],[sp1_idp_target_wa]]+ndp_SP1[[#This Row],[sp1_ndp_target_wa]] -> 0 | AM31: =idp_SP1[[#This Row],[sp1_idp_target_gp]]+ndp_SP1[[#This Row],[sp1_ndp_target_gp]] -> 0 | AN31: =idp_SP1[[#This Row],[sp1_idp_target_cp]]+ndp_SP1[[#This Row],[sp1_ndp_target_cp]] -> 0 | AO31: =idp_SP1[[#This Row],[sp1_idp_target_gb]]+ndp_SP1[[#This Row],[sp1_ndp_target_gb]] -> 0 | AP31: =idp_SP1[[#This Row],[sp1_idp_target_fs]]+ndp_SP1[[#This Row],[sp1_ndp_target_fs]] -> 0 | AQ31: =idp_SP1[[#This Row],[sp1_idp_target_li]]+ndp_SP1[[#This Row],[sp1_ndp_target_li]] -> 0 | AR31: =idp_SP1[[#This Row],[sp1_idp_target_cw]]+ndp_SP1[[#This Row],[sp1_ndp_target_cw]] -> 0 | AS31: =idp_SP1[[#This Row],[sp1_idp_target_joint]]+ndp_SP1[[#This Row],[sp1_ndp_target_joint]] -> 0 | AT31: 0 | AU31: 0 | AV31: 0 | AW31: 0 | AX31: 0 | AY31: 0 | AZ31: 0 | BA31: 0 | BB31: 0 | BC31: 0 | BD31: 0 | BE31: 0 | BF31: 0
A32: Sumska | B32: UA59 | C32: 0-20 km (w/o Sumy) | D32: 0-20km | E32: UA59_U20X | F32: 14447 | G32: 107044 | H32: 121491 | I32: =idp_SP1[[#This Row],[sp1_idp_pin_ed]]+ndp_SP1[[#This Row],[sp1_ndp_pin_ed]] -> 8677 | J32: =idp_SP1[[#This Row],[sp1_idp_pin_fl]]+ndp_SP1[[#This Row],[sp1_ndp_pin_fl]] -> 21375 | K32: =idp_SP1[[#This Row],[sp1_idp_pin_he]]+ndp_SP1[[#This Row],[sp1_ndp_pin_he]] -> 94250 | L32: =idp_SP1[[#This Row],[sp1_idp_pin_pr]]+ndp_SP1[[#This Row],[sp1_ndp_pin_pr]] -> 100140 | M32: =idp_SP1[[#This Row],[sp1_idp_pin_sn]]+ndp_SP1[[#This Row],[sp1_ndp_pin_sn]] -> 90000 | N32: =idp_SP1[[#This Row],[sp1_idp_pin_wa]]+ndp_SP1[[#This Row],[sp1_ndp_pin_wa]] -> 69792 | O32: =idp_SP1[[#This Row],[sp1_idp_pin_gp]]+ndp_SP1[[#This Row],[sp1_ndp_pin_gp]] -> 100140 | P32: =idp_SP1[[#This Row],[sp1_idp_pin_cp]]+ndp_SP1[[#This Row],[sp1_ndp_pin_cp]] -> 33995 | Q32: =idp_SP1[[#This Row],[sp1_idp_pin_gb]]+ndp_SP1[[#This Row],[sp1_ndp_pin_gb]] -> 47624 | R32: =idp_SP1[[#This Row],[sp1_idp_pin_fs]]+ndp_SP1[[#This Row],[sp1_ndp_pin_fs]] -> 21375 | S32: =idp_SP1[[#This Row],[sp1_idp_pin_li]]+ndp_SP1[[#This Row],[sp1_ndp_pin_li]] -> 0 | T32: =idp_SP1[[#This Row],[sp1_idp_pin_adopted]]+ndp_SP1[[#This Row],[sp1_ndp_pin_adopted]] -> 101717 | U32: 5 | V32: 4 | W32: 4 | X32: =MAX(idp_SP1[[#This Row],[sp1_idp_sev_pr]],ndp_SP1[[#This Row],[sp1_ndp_sev_pr]]) -> 4 | Y32: 5 | Z32: 4 | AA32: 4 | AB32: 5 | AC32: 4 | AD32: 4 | AE32: 4 | AF32: 5 | AG32: =idp_SP1[[#This Row],[sp1_idp_target_ed]]+ndp_SP1[[#This Row],[sp1_ndp_target_ed]] -> 7809 | AH32: =idp_SP1[[#This Row],[sp1_idp_target_fl]]+ndp_SP1[[#This Row],[sp1_ndp_target_fl]] -> 21375 | AI32: =idp_SP1[[#This Row],[sp1_idp_target_he]]+ndp_SP1[[#This Row],[sp1_ndp_target_he]] -> 53780 | AJ32: =idp_SP1[[#This Row],[sp1_idp_target_pr]]+ndp_SP1[[#This Row],[sp1_ndp_target_pr]] -> 38901 | AK32: =idp_SP1[[#This Row],[sp1_idp_target_sn]]+ndp_SP1[[#This Row],[sp1_ndp_target_sn]] -> 54785 | AL32: =idp_SP1[[#This Row],[sp1_idp_target_wa]]+ndp_SP1[[#This Row],[sp1_ndp_target_wa]] -> 69792 | AM32: =idp_SP1[[#This Row],[sp1_idp_target_gp]]+ndp_SP1[[#This Row],[sp1_ndp_target_gp]] -> 38901 | AN32: =idp_SP1[[#This Row],[sp1_idp_target_cp]]+ndp_SP1[[#This Row],[sp1_ndp_target_cp]] -> 28365 | AO32: =idp_SP1[[#This Row],[sp1_idp_target_gb]]+ndp_SP1[[#This Row],[sp1_ndp_target_gb]] -> 2381 | AP32: =idp_SP1[[#This Row],[sp1_idp_target_fs]]+ndp_SP1[[#This Row],[sp1_ndp_target_fs]] -> 21375 | AQ32: =idp_SP1[[#This Row],[sp1_idp_target_li]]+ndp_SP1[[#This Row],[sp1_ndp_target_li]] -> 0 | AR32: =idp_SP1[[#This Row],[sp1_idp_target_cw]]+ndp_SP1[[#This Row],[sp1_ndp_target_cw]] -> 83471 | AS32: =idp_SP1[[#This Row],[sp1_idp_target_joint]]+ndp_SP1[[#This Row],[sp1_ndp_target_joint]] -> 83471 | AT32: 7809 | AU32: 21375 | AV32: 53780 | AW32: 38901 | AX32: 54785 | AY32: 69792 | AZ32: 38901 | BA32: 28365 | BB32: 2381 | BC32: 21375 | BD32: 0 | BE32: 83471 | BF32: 83471
A33: Sumska | B33: UA59 | C33: 21-50 km | D33: 20-50km | E33: UA59_U50A | F33: 25722 | G33: 93192.104 | H33: 118914.1 | I33: =idp_SP1[[#This Row],[sp1_idp_pin_ed]]+ndp_SP1[[#This Row],[sp1_ndp_pin_ed]] -> 6672 | J33: =idp_SP1[[#This Row],[sp1_idp_pin_fl]]+ndp_SP1[[#This Row],[sp1_ndp_pin_fl]] -> 18410 | K33: =idp_SP1[[#This Row],[sp1_idp_pin_he]]+ndp_SP1[[#This Row],[sp1_ndp_pin_he]] -> 92251 | L33: =idp_SP1[[#This Row],[sp1_idp_pin_pr]]+ndp_SP1[[#This Row],[sp1_ndp_pin_pr]] -> 74948 | M33: =idp_SP1[[#This Row],[sp1_idp_pin_sn]]+ndp_SP1[[#This Row],[sp1_ndp_pin_sn]] -> 69267 | N33: =idp_SP1[[#This Row],[sp1_idp_pin_wa]]+ndp_SP1[[#This Row],[sp1_ndp_pin_wa]] -> 55699 | O33: =idp_SP1[[#This Row],[sp1_idp_pin_gp]]+ndp_SP1[[#This Row],[sp1_ndp_pin_gp]] -> 74948 | P33: =idp_SP1[[#This Row],[sp1_idp_pin_cp]]+ndp_SP1[[#This Row],[sp1_ndp_pin_cp]] -> 32146 | Q33: =idp_SP1[[#This Row],[sp1_idp_pin_gb]]+ndp_SP1[[#This Row],[sp1_ndp_pin_gb]] -> 36177 | R33: =idp_SP1[[#This Row],[sp1_idp_pin_fs]]+ndp_SP1[[#This Row],[sp1_ndp_pin_fs]] -> 18410 | S33: =idp_SP1[[#This Row],[sp1_idp_pin_li]]+ndp_SP1[[#This Row],[sp1_ndp_pin_li]] -> 0 | T33: =idp_SP1[[#This Row],[sp1_idp_pin_adopted]]+ndp_SP1[[#This Row],[sp1_ndp_pin_adopted]] -> 92251 | U33: 4 | V33: 4 | W33: 4 | X33: =MAX(idp_SP1[[#This Row],[sp1_idp_sev_pr]],ndp_SP1[[#This Row],[sp1_ndp_sev_pr]]) -> 4 | Y33: 4 | Z33: 3 | AA33: 4 | AB33: 4 | AC33: 4 | AD33: 4 | AE33: 4 | AF33: 4 | AG33: =idp_SP1[[#This Row],[sp1_idp_target_ed]]+ndp_SP1[[#This Row],[sp1_ndp_target_ed]] -> 6005 | AH33: =idp_SP1[[#This Row],[sp1_idp_target_fl]]+ndp_SP1[[#This Row],[sp1_ndp_target_fl]] -> 18410 | AI33: =idp_SP1[[#This Row],[sp1_idp_target_he]]+ndp_SP1[[#This Row],[sp1_ndp_target_he]] -> 63720 | AJ33: =idp_SP1[[#This Row],[sp1_idp_target_pr]]+ndp_SP1[[#This Row],[sp1_ndp_target_pr]] -> 31680 | AK33: =idp_SP1[[#This Row],[sp1_idp_target_sn]]+ndp_SP1[[#This Row],[sp1_ndp_target_sn]] -> 33276 | AL33: =idp_SP1[[#This Row],[sp1_idp_target_wa]]+ndp_SP1[[#This Row],[sp1_ndp_target_wa]] -> 27849 | AM33: =idp_SP1[[#This Row],[sp1_idp_target_gp]]+ndp_SP1[[#This Row],[sp1_ndp_target_gp]] -> 31680 | AN33: =idp_SP1[[#This Row],[sp1_idp_target_cp]]+ndp_SP1[[#This Row],[sp1_ndp_target_cp]] -> 15789 | AO33: =idp_SP1[[#This Row],[sp1_idp_target_gb]]+ndp_SP1[[#This Row],[sp1_ndp_target_gb]] -> 12870 | AP33: =idp_SP1[[#This Row],[sp1_idp_target_fs]]+ndp_SP1[[#This Row],[sp1_ndp_target_fs]] -> 18410 | AQ33: =idp_SP1[[#This Row],[sp1_idp_target_li]]+ndp_SP1[[#This Row],[sp1_ndp_target_li]] -> 0 | AR33: =idp_SP1[[#This Row],[sp1_idp_target_cw]]+ndp_SP1[[#This Row],[sp1_ndp_target_cw]] -> 7203 | AS33: =idp_SP1[[#This Row],[sp1_idp_target_joint]]+ndp_SP1[[#This Row],[sp1_ndp_target_joint]] -> 63720 | AT33: 6005 | AU33: 6868 | AV33: 63720 | AW33: 31680 | AX33: 33276 | AY33: 5570 | AZ33: 31680 | BA33: 8379 | BB33: 6608 | BC33: 6868 | BD33: 0 | BE33: 3733 | BF33: 63720
A34: Sumska | B34: UA59 | C34: 51+ km | D34: 50+ | E34: UA59_U51P | F34: 0 | G34: 0 | I34: =idp_SP1[[#This Row],[sp1_idp_pin_ed]]+ndp_SP1[[#This Row],[sp1_ndp_pin_ed]] -> 0 | J34: =idp_SP1[[#This Row],[sp1_idp_pin_fl]]+ndp_SP1[[#This Row],[sp1_ndp_pin_fl]] -> 0 | K34: =idp_SP1[[#This Row],[sp1_idp_pin_he]]+ndp_SP1[[#This Row],[sp1_ndp_pin_he]] -> 0 | L34: =idp_SP1[[#This Row],[sp1_idp_pin_pr]]+ndp_SP1[[#This Row],[sp1_ndp_pin_pr]] -> 0 | M34: =idp_SP1[[#This Row],[sp1_idp_pin_sn]]+ndp_SP1[[#This Row],[sp1_ndp_pin_sn]] -> 0 | N34: =idp_SP1[[#This Row],[sp1_idp_pin_wa]]+ndp_SP1[[#This Row],[sp1_ndp_pin_wa]] -> 0 | O34: =idp_SP1[[#This Row],[sp1_idp_pin_gp]]+ndp_SP1[[#This Row],[sp1_ndp_pin_gp]] -> 0 | P34: =idp_SP1[[#This Row],[sp1_idp_pin_cp]]+ndp_SP1[[#This Row],[sp1_ndp_pin_cp]] -> 0 | Q34: =idp_SP1[[#This Row],[sp1_idp_pin_gb]]+ndp_SP1[[#This Row],[sp1_ndp_pin_gb]] -> 0 | R34: =idp_SP1[[#This Row],[sp1_idp_pin_fs]]+ndp_SP1[[#This Row],[sp1_ndp_pin_fs]] -> 0 | S34: =idp_SP1[[#This Row],[sp1_idp_pin_li]]+ndp_SP1[[#This Row],[sp1_ndp_pin_li]] -> 0 | T34: =idp_SP1[[#This Row],[sp1_idp_pin_adopted]]+ndp_SP1[[#This Row],[sp1_ndp_pin_adopted]] -> 0 | X34: =MAX(idp_SP1[[#This Row],[sp1_idp_sev_pr]],ndp_SP1[[#This Row],[sp1_ndp_sev_pr]]) -> 0 | Y34: 0 | AG34: =idp_SP1[[#This Row],[sp1_idp_target_ed]]+ndp_SP1[[#This Row],[sp1_ndp_target_ed]] -> 0 | AH34: =idp_SP1[[#This Row],[sp1_idp_target_fl]]+ndp_SP1[[#This Row],[sp1_ndp_target_fl]] -> 0 | AI34: =idp_SP1[[#This Row],[sp1_idp_target_he]]+ndp_SP1[[#This Row],[sp1_ndp_target_he]] -> 0 | AJ34: =idp_SP1[[#This Row],[sp1_idp_target_pr]]+ndp_SP1[[#This Row],[sp1_ndp_target_pr]] -> 0 | AK34: =idp_SP1[[#This Row],[sp1_idp_target_sn]]+ndp_SP1[[#This Row],[sp1_ndp_target_sn]] -> 0 | AL34: =idp_SP1[[#This Row],[sp1_idp_target_wa]]+ndp_SP1[[#This Row],[sp1_ndp_target_wa]] -> 0 | AM34: =idp_SP1[[#This Row],[sp1_idp_target_gp]]+ndp_SP1[[#This Row],[sp1_ndp_target_gp]] -> 0 | AN34: =idp_SP1[[#This Row],[sp1_idp_target_cp]]+ndp_SP1[[#This Row],[sp1_ndp_target_cp]] -> 0 | AO34: =idp_SP1[[#This Row],[sp1_idp_target_gb]]+ndp_SP1[[#This Row],[sp1_ndp_target_gb]] -> 0 | AP34: =idp_SP1[[#This Row],[sp1_idp_target_fs]]+ndp_SP1[[#This Row],[sp1_ndp_target_fs]] -> 0 | AQ34: =idp_SP1[[#This Row],[sp1_idp_target_li]]+ndp_SP1[[#This Row],[sp1_ndp_target_li]] -> 0 | AR34: =idp_SP1[[#This Row],[sp1_idp_target_cw]]+ndp_SP1[[#This Row],[sp1_ndp_target_cw]] -> 0 | AS34: =idp_SP1[[#This Row],[sp1_idp_target_joint]]+ndp_SP1[[#This Row],[sp1_ndp_target_joint]] -> 0 | AT34: 0 | AU34: 0 | AV34: 0 | AW34: 0 | AX34: 0 | AY34: 0 | AZ34: 0 | BA34: 0 | BB34: 0 | BC34: 0 | BD34: 0 | BE34: 0 | BF34: 0
A35: Sumska | B35: UA59 | C35: Sumy city | D35: 0-20km | E35: UA59_UCAP | F35: 25799 | G35: 231388 | H35: 257187 | I35: =idp_SP1[[#This Row],[sp1_idp_pin_ed]]+ndp_SP1[[#This Row],[sp1_ndp_pin_ed]] -> 19936 | J35: =idp_SP1[[#This Row],[sp1_idp_pin_fl]]+ndp_SP1[[#This Row],[sp1_ndp_pin_fl]] -> 33264 | K35: =idp_SP1[[#This Row],[sp1_idp_pin_he]]+ndp_SP1[[#This Row],[sp1_ndp_pin_he]] -> 199519 | L35: =idp_SP1[[#This Row],[sp1_idp_pin_pr]]+ndp_SP1[[#This Row],[sp1_ndp_pin_pr]] -> 187896 | M35: =idp_SP1[[#This Row],[sp1_idp_pin_sn]]+ndp_SP1[[#This Row],[sp1_ndp_pin_sn]] -> 140284 | N35: =idp_SP1[[#This Row],[sp1_idp_pin_wa]]+ndp_SP1[[#This Row],[sp1_ndp_pin_wa]] -> 257187 | O35: =idp_SP1[[#This Row],[sp1_idp_pin_gp]]+ndp_SP1[[#This Row],[sp1_ndp_pin_gp]] -> 187080 | P35: =idp_SP1[[#This Row],[sp1_idp_pin_cp]]+ndp_SP1[[#This Row],[sp1_ndp_pin_cp]] -> 75058 | Q35: =idp_SP1[[#This Row],[sp1_idp_pin_gb]]+ndp_SP1[[#This Row],[sp1_ndp_pin_gb]] -> 100817 | R35: =idp_SP1[[#This Row],[sp1_idp_pin_fs]]+ndp_SP1[[#This Row],[sp1_ndp_pin_fs]] -> 33264 | S35: =idp_SP1[[#This Row],[sp1_idp_pin_li]]+ndp_SP1[[#This Row],[sp1_ndp_pin_li]] -> 0 | T35: =idp_SP1[[#This Row],[sp1_idp_pin_adopted]]+ndp_SP1[[#This Row],[sp1_ndp_pin_adopted]] -> 257187 | U35: 4 | V35: 4 | W35: 4 | X35: =MAX(idp_SP1[[#This Row],[sp1_idp_sev_pr]],ndp_SP1[[#This Row],[sp1_ndp_sev_pr]]) -> 4 | Y35: 5 | Z35: 4 | AA35: 4 | AB35: 4 | AC35: 4 | AD35: 4 | AE35: 4 | AF35: 4 | AG35: =idp_SP1[[#This Row],[sp1_idp_target_ed]]+ndp_SP1[[#This Row],[sp1_ndp_target_ed]] -> 17943 | AH35: =idp_SP1[[#This Row],[sp1_idp_target_fl]]+ndp_SP1[[#This Row],[sp1_ndp_target_fl]] -> 33264 | AI35: =idp_SP1[[#This Row],[sp1_idp_target_he]]+ndp_SP1[[#This Row],[sp1_ndp_target_he]] -> 80298 | AJ35: =idp_SP1[[#This Row],[sp1_idp_target_pr]]+ndp_SP1[[#This Row],[sp1_ndp_target_pr]] -> 70294 | AK35: =idp_SP1[[#This Row],[sp1_idp_target_sn]]+ndp_SP1[[#This Row],[sp1_ndp_target_sn]] -> 55730 | AL35: =idp_SP1[[#This Row],[sp1_idp_target_wa]]+ndp_SP1[[#This Row],[sp1_ndp_target_wa]] -> 257187 | AM35: =idp_SP1[[#This Row],[sp1_idp_target_gp]]+ndp_SP1[[#This Row],[sp1_ndp_target_gp]] -> 70294 | AN35: =idp_SP1[[#This Row],[sp1_idp_target_cp]]+ndp_SP1[[#This Row],[sp1_ndp_target_cp]] -> 63253 | AO35: =idp_SP1[[#This Row],[sp1_idp_target_gb]]+ndp_SP1[[#This Row],[sp1_ndp_target_gb]] -> 5041 | AP35: =idp_SP1[[#This Row],[sp1_idp_target_fs]]+ndp_SP1[[#This Row],[sp1_ndp_target_fs]] -> 33264 | AQ35: =idp_SP1[[#This Row],[sp1_idp_target_li]]+ndp_SP1[[#This Row],[sp1_ndp_target_li]] -> 0 | AR35: =idp_SP1[[#This Row],[sp1_idp_target_cw]]+ndp_SP1[[#This Row],[sp1_ndp_target_cw]] -> 86842 | AS35: =idp_SP1[[#This Row],[sp1_idp_target_joint]]+ndp_SP1[[#This Row],[sp1_ndp_target_joint]] -> 257187 | AT35: 17943 | AU35: 33264 | AV35: 27950 | AW35: 70294 | AX35: 55730 | AY35: 257187 | AZ35: 70294 | BA35: 63253 | BB35: 5041 | BC35: 33264 | BD35: 0 | BE35: 86842 | BF35: 257187
A36: Ternopilska | B36: UA61 | C36: All oblast | D36: 50+ | E36: UA61_UALL | F36: 0 | G36: 0 | I36: =idp_SP1[[#This Row],[sp1_idp_pin_ed]]+ndp_SP1[[#This Row],[sp1_ndp_pin_ed]] -> 0 | J36: =idp_SP1[[#This Row],[sp1_idp_pin_fl]]+ndp_SP1[[#This Row],[sp1_ndp_pin_fl]] -> 0 | K36: =idp_SP1[[#This Row],[sp1_idp_pin_he]]+ndp_SP1[[#This Row],[sp1_ndp_pin_he]] -> 0 | L36: =idp_SP1[[#This Row],[sp1_idp_pin_pr]]+ndp_SP1[[#This Row],[sp1_ndp_pin_pr]] -> 0 | M36: =idp_SP1[[#This Row],[sp1_idp_pin_sn]]+ndp_SP1[[#This Row],[sp1_ndp_pin_sn]] -> 0 | N36: =idp_SP1[[#This Row],[sp1_idp_pin_wa]]+ndp_SP1[[#This Row],[sp1_ndp_pin_wa]] -> 0 | O36: =idp_SP1[[#This Row],[sp1_idp_pin_gp]]+ndp_SP1[[#This Row],[sp1_ndp_pin_gp]] -> 0 | P36: =idp_SP1[[#This Row],[sp1_idp_pin_cp]]+ndp_SP1[[#This Row],[sp1_ndp_pin_cp]] -> 0 | Q36: =idp_SP1[[#This Row],[sp1_idp_pin_gb]]+ndp_SP1[[#This Row],[sp1_ndp_pin_gb]] -> 0 | R36: =idp_SP1[[#This Row],[sp1_idp_pin_fs]]+ndp_SP1[[#This Row],[sp1_ndp_pin_fs]] -> 0 | S36: =idp_SP1[[#This Row],[sp1_idp_pin_li]]+ndp_SP1[[#This Row],[sp1_ndp_pin_li]] -> 0 | T36: =idp_SP1[[#This Row],[sp1_idp_pin_adopted]]+ndp_SP1[[#This Row],[sp1_ndp_pin_adopted]] -> 0 | X36: =MAX(idp_SP1[[#This Row],[sp1_idp_sev_pr]],ndp_SP1[[#This Row],[sp1_ndp_sev_pr]]) -> 0 | Y36: 0 | AG36: =idp_SP1[[#This Row],[sp1_idp_target_ed]]+ndp_SP1[[#This Row],[sp1_ndp_target_ed]] -> 0 | AH36: =idp_SP1[[#This Row],[sp1_idp_target_fl]]+ndp_SP1[[#This Row],[sp1_ndp_target_fl]] -> 0 | AI36: =idp_SP1[[#This Row],[sp1_idp_target_he]]+ndp_SP1[[#This Row],[sp1_ndp_target_he]] -> 0 | AJ36: =idp_SP1[[#This Row],[sp1_idp_target_pr]]+ndp_SP1[[#This Row],[sp1_ndp_target_pr]] -> 0 | AK36: =idp_SP1[[#This Row],[sp1_idp_target_sn]]+ndp_SP1[[#This Row],[sp1_ndp_target_sn]] -> 0 | AL36: =idp_SP1[[#This Row],[sp1_idp_target_wa]]+ndp_SP1[[#This Row],[sp1_ndp_target_wa]] -> 0 | AM36: =idp_SP1[[#This Row],[sp1_idp_target_gp]]+ndp_SP1[[#This Row],[sp1_ndp_target_gp]] -> 0 | AN36: =idp_SP1[[#This Row],[sp1_idp_target_cp]]+ndp_SP1[[#This Row],[sp1_ndp_target_cp]] -> 0 | AO36: =idp_SP1[[#This Row],[sp1_idp_target_gb]]+ndp_SP1[[#This Row],[sp1_ndp_target_gb]] -> 0 | AP36: =idp_SP1[[#This Row],[sp1_idp_target_fs]]+ndp_SP1[[#This Row],[sp1_ndp_target_fs]] -> 0 | AQ36: =idp_SP1[[#This Row],[sp1_idp_target_li]]+ndp_SP1[[#This Row],[sp1_ndp_target_li]] -> 0 | AR36: =idp_SP1[[#This Row],[sp1_idp_target_cw]]+ndp_SP1[[#This Row],[sp1_ndp_target_cw]] -> 0 | AS36: =idp_SP1[[#This Row],[sp1_idp_target_joint]]+ndp_SP1[[#This Row],[sp1_ndp_target_joint]] -> 0 | AT36: 0 | AU36: 0 | AV36: 0 | AW36: 0 | AX36: 0 | AY36: 0 | AZ36: 0 | BA36: 0 | BB36: 0 | BC36: 0 | BD36: 0 | BE36: 0 | BF36: 0
A37: Kharkivska | B37: UA63 | C37: 0-20 km | D37: 0-20km | E37: UA63_U20A | F37: 29217 | G37: 173398 | H37: 202615 | I37: =idp_SP1[[#This Row],[sp1_idp_pin_ed]]+ndp_SP1[[#This Row],[sp1_ndp_pin_ed]] -> 9572 | J37: =idp_SP1[[#This Row],[sp1_idp_pin_fl]]+ndp_SP1[[#This Row],[sp1_ndp_pin_fl]] -> 74880 | K37: =idp_SP1[[#This Row],[sp1_idp_pin_he]]+ndp_SP1[[#This Row],[sp1_ndp_pin_he]] -> 157184 | L37: =idp_SP1[[#This Row],[sp1_idp_pin_pr]]+ndp_SP1[[#This Row],[sp1_ndp_pin_pr]] -> 154818 | M37: =idp_SP1[[#This Row],[sp1_idp_pin_sn]]+ndp_SP1[[#This Row],[sp1_ndp_pin_sn]] -> 142428 | N37: =idp_SP1[[#This Row],[sp1_idp_pin_wa]]+ndp_SP1[[#This Row],[sp1_ndp_pin_wa]] -> 157589 | O37: =idp_SP1[[#This Row],[sp1_idp_pin_gp]]+ndp_SP1[[#This Row],[sp1_ndp_pin_gp]] -> 154818 | P37: =idp_SP1[[#This Row],[sp1_idp_pin_cp]]+ndp_SP1[[#This Row],[sp1_ndp_pin_cp]] -> 55090 | Q37: =idp_SP1[[#This Row],[sp1_idp_pin_gb]]+ndp_SP1[[#This Row],[sp1_ndp_pin_gb]] -> 77324 | R37: =idp_SP1[[#This Row],[sp1_idp_pin_fs]]+ndp_SP1[[#This Row],[sp1_ndp_pin_fs]] -> 74880 | S37: =idp_SP1[[#This Row],[sp1_idp_pin_li]]+ndp_SP1[[#This Row],[sp1_ndp_pin_li]] -> 0 | T37: =idp_SP1[[#This Row],[sp1_idp_pin_adopted]]+ndp_SP1[[#This Row],[sp1_ndp_pin_adopted]] -> 161160 | U37: 5 | V37: 4 | W37: 4 | X37: =MAX(idp_SP1[[#This Row],[sp1_idp_sev_pr]],ndp_SP1[[#This Row],[sp1_ndp_sev_pr]]) -> 5 | Y37: 5 | Z37: 5 | AA37: 5 | AB37: 5 | AC37: 5 | AD37: 4 | AE37: 4 | AF37: 5 | AG37: =idp_SP1[[#This Row],[sp1_idp_target_ed]]+ndp_SP1[[#This Row],[sp1_ndp_target_ed]] -> 8615 | AH37: =idp_SP1[[#This Row],[sp1_idp_target_fl]]+ndp_SP1[[#This Row],[sp1_ndp_target_fl]] -> 74880 | AI37: =idp_SP1[[#This Row],[sp1_idp_target_he]]+ndp_SP1[[#This Row],[sp1_ndp_target_he]] -> 90544 | AJ37: =idp_SP1[[#This Row],[sp1_idp_target_pr]]+ndp_SP1[[#This Row],[sp1_ndp_target_pr]] -> 64704 | AK37: =idp_SP1[[#This Row],[sp1_idp_target_sn]]+ndp_SP1[[#This Row],[sp1_ndp_target_sn]] -> 68607 | AL37: =idp_SP1[[#This Row],[sp1_idp_target_wa]]+ndp_SP1[[#This Row],[sp1_ndp_target_wa]] -> 157589 | AM37: =idp_SP1[[#This Row],[sp1_idp_target_gp]]+ndp_SP1[[#This Row],[sp1_ndp_target_gp]] -> 64704 | AN37: =idp_SP1[[#This Row],[sp1_idp_target_cp]]+ndp_SP1[[#This Row],[sp1_ndp_target_cp]] -> 44888 | AO37: =idp_SP1[[#This Row],[sp1_idp_target_gb]]+ndp_SP1[[#This Row],[sp1_ndp_target_gb]] -> 3866 | AP37: =idp_SP1[[#This Row],[sp1_idp_target_fs]]+ndp_SP1[[#This Row],[sp1_ndp_target_fs]] -> 74880 | AQ37: =idp_SP1[[#This Row],[sp1_idp_target_li]]+ndp_SP1[[#This Row],[sp1_ndp_target_li]] -> 0 | AR37: =idp_SP1[[#This Row],[sp1_idp_target_cw]]+ndp_SP1[[#This Row],[sp1_ndp_target_cw]] -> 75159 | AS37: =idp_SP1[[#This Row],[sp1_idp_target_joint]]+ndp_SP1[[#This Row],[sp1_ndp_target_joint]] -> 158381 | AT37: 8615 | AU37: 74880 | AV37: 90544 | AW37: 64704 | AX37: 68607 | AY37: 157589 | AZ37: 64704 | BA37: 44888 | BB37: 3866 | BC37: 74880 | BD37: 0 | BE37: 75159 | BF37: 158381
A38: Kharkivska | B38: UA63 | C38: 21-50 km (w/o Kharkiv) | D38: 20-50km | E38: UA63_U50X | F38: 83462 | G38: 88204.956 | H38: 171666.96 | I38: =idp_SP1[[#This Row],[sp1_idp_pin_ed]]+ndp_SP1[[#This Row],[sp1_ndp_pin_ed]] -> 12472 | J38: =idp_SP1[[#This Row],[sp1_idp_pin_fl]]+ndp_SP1[[#This Row],[sp1_ndp_pin_fl]] -> 40217 | K38: =idp_SP1[[#This Row],[sp1_idp_pin_he]]+ndp_SP1[[#This Row],[sp1_ndp_pin_he]] -> 133175 | L38: =idp_SP1[[#This Row],[sp1_idp_pin_pr]]+ndp_SP1[[#This Row],[sp1_ndp_pin_pr]] -> 123714 | M38: =idp_SP1[[#This Row],[sp1_idp_pin_sn]]+ndp_SP1[[#This Row],[sp1_ndp_pin_sn]] -> 119952 | N38: =idp_SP1[[#This Row],[sp1_idp_pin_wa]]+ndp_SP1[[#This Row],[sp1_ndp_pin_wa]] -> 110707 | O38: =idp_SP1[[#This Row],[sp1_idp_pin_gp]]+ndp_SP1[[#This Row],[sp1_ndp_pin_gp]] -> 123714 | P38: =idp_SP1[[#This Row],[sp1_idp_pin_cp]]+ndp_SP1[[#This Row],[sp1_ndp_pin_cp]] -> 59386 | Q38: =idp_SP1[[#This Row],[sp1_idp_pin_gb]]+ndp_SP1[[#This Row],[sp1_ndp_pin_gb]] -> 55192 | R38: =idp_SP1[[#This Row],[sp1_idp_pin_fs]]+ndp_SP1[[#This Row],[sp1_ndp_pin_fs]] -> 40217 | S38: =idp_SP1[[#This Row],[sp1_idp_pin_li]]+ndp_SP1[[#This Row],[sp1_ndp_pin_li]] -> 0 | T38: =idp_SP1[[#This Row],[sp1_idp_pin_adopted]]+ndp_SP1[[#This Row],[sp1_ndp_pin_adopted]] -> 133175 | U38: 4 | V38: 4 | W38: 4 | X38: =MAX(idp_SP1[[#This Row],[sp1_idp_sev_pr]],ndp_SP1[[#This Row],[sp1_ndp_sev_pr]]) -> 4 | Y38: 4 | Z38: 4 | AA38: 4 | AB38: 4 | AC38: 4 | AD38: 4 | AE38: 4 | AF38: 4 | AG38: =idp_SP1[[#This Row],[sp1_idp_target_ed]]+ndp_SP1[[#This Row],[sp1_ndp_target_ed]] -> 11225 | AH38: =idp_SP1[[#This Row],[sp1_idp_target_fl]]+ndp_SP1[[#This Row],[sp1_ndp_target_fl]] -> 40217 | AI38: =idp_SP1[[#This Row],[sp1_idp_target_he]]+ndp_SP1[[#This Row],[sp1_ndp_target_he]] -> 83951 | AJ38: =idp_SP1[[#This Row],[sp1_idp_target_pr]]+ndp_SP1[[#This Row],[sp1_ndp_target_pr]] -> 66324 | AK38: =idp_SP1[[#This Row],[sp1_idp_target_sn]]+ndp_SP1[[#This Row],[sp1_ndp_target_sn]] -> 68721 | AL38: =idp_SP1[[#This Row],[sp1_idp_target_wa]]+ndp_SP1[[#This Row],[sp1_ndp_target_wa]] -> 110707 | AM38: =idp_SP1[[#This Row],[sp1_idp_target_gp]]+ndp_SP1[[#This Row],[sp1_ndp_target_gp]] -> 66324 | AN38: =idp_SP1[[#This Row],[sp1_idp_target_cp]]+ndp_SP1[[#This Row],[sp1_ndp_target_cp]] -> 40783 | AO38: =idp_SP1[[#This Row],[sp1_idp_target_gb]]+ndp_SP1[[#This Row],[sp1_ndp_target_gb]] -> 27596 | AP38: =idp_SP1[[#This Row],[sp1_idp_target_fs]]+ndp_SP1[[#This Row],[sp1_ndp_target_fs]] -> 40217 | AQ38: =idp_SP1[[#This Row],[sp1_idp_target_li]]+ndp_SP1[[#This Row],[sp1_ndp_target_li]] -> 0 | AR38: =idp_SP1[[#This Row],[sp1_idp_target_cw]]+ndp_SP1[[#This Row],[sp1_ndp_target_cw]] -> 30078 | AS38: =idp_SP1[[#This Row],[sp1_idp_target_joint]]+ndp_SP1[[#This Row],[sp1_ndp_target_joint]] -> 110707 | AT38: 11225 | AU38: 40217 | AV38: 83951 | AW38: 66324 | AX38: 68721 | AY38: 110707 | AZ38: 66324 | BA38: 40783 | BB38: 27596 | BC38: 40217 | BD38: 0 | BE38: 30078 | BF38: 110707
A39: Kharkivska | B39: UA63 | C39: 51+ km | D39: 50+ | E39: UA63_U51P | F39: 0 | G39: 0 | I39: =idp_SP1[[#This Row],[sp1_idp_pin_ed]]+ndp_SP1[[#This Row],[sp1_ndp_pin_ed]] -> 0 | J39: =idp_SP1[[#This Row],[sp1_idp_pin_fl]]+ndp_SP1[[#This Row],[sp1_ndp_pin_fl]] -> 0 | K39: =idp_SP1[[#This Row],[sp1_idp_pin_he]]+ndp_SP1[[#This Row],[sp1_ndp_pin_he]] -> 0 | L39: =idp_SP1[[#This Row],[sp1_idp_pin_pr]]+ndp_SP1[[#This Row],[sp1_ndp_pin_pr]] -> 0 | M39: =idp_SP1[[#This Row],[sp1_idp_pin_sn]]+ndp_SP1[[#This Row],[sp1_ndp_pin_sn]] -> 0 | N39: =idp_SP1[[#This Row],[sp1_idp_pin_wa]]+ndp_SP1[[#This Row],[sp1_ndp_pin_wa]] -> 0 | O39: =idp_SP1[[#This Row],[sp1_idp_pin_gp]]+ndp_SP1[[#This Row],[sp1_ndp_pin_gp]] -> 0 | P39: =idp_SP1[[#This Row],[sp1_idp_pin_cp]]+ndp_SP1[[#This Row],[sp1_ndp_pin_cp]] -> 0 | Q39: =idp_SP1[[#This Row],[sp1_idp_pin_gb]]+ndp_SP1[[#This Row],[sp1_ndp_pin_gb]] -> 0 | R39: =idp_SP1[[#This Row],[sp1_idp_pin_fs]]+ndp_SP1[[#This Row],[sp1_ndp_pin_fs]] -> 0 | S39: =idp_SP1[[#This Row],[sp1_idp_pin_li]]+ndp_SP1[[#This Row],[sp1_ndp_pin_li]] -> 0 | T39: =idp_SP1[[#This Row],[sp1_idp_pin_adopted]]+ndp_SP1[[#This Row],[sp1_ndp_pin_adopted]] -> 0 | X39: =MAX(idp_SP1[[#This Row],[sp1_idp_sev_pr]],ndp_SP1[[#This Row],[sp1_ndp_sev_pr]]) -> 0 | Y39: 0 | AG39: =idp_SP1[[#This Row],[sp1_idp_target_ed]]+ndp_SP1[[#This Row],[sp1_ndp_target_ed]] -> 0 | AH39: =idp_SP1[[#This Row],[sp1_idp_target_fl]]+ndp_SP1[[#This Row],[sp1_ndp_target_fl]] -> 0 | AI39: =idp_SP1[[#This Row],[sp1_idp_target_he]]+ndp_SP1[[#This Row],[sp1_ndp_target_he]] -> 0 | AJ39: =idp_SP1[[#This Row],[sp1_idp_target_pr]]+ndp_SP1[[#This Row],[sp1_ndp_target_pr]] -> 0 | AK39: =idp_SP1[[#This Row],[sp1_idp_target_sn]]+ndp_SP1[[#This Row],[sp1_ndp_target_sn]] -> 0 | AL39: =idp_SP1[[#This Row],[sp1_idp_target_wa]]+ndp_SP1[[#This Row],[sp1_ndp_target_wa]] -> 0 | AM39: =idp_SP1[[#This Row],[sp1_idp_target_gp]]+ndp_SP1[[#This Row],[sp1_ndp_target_gp]] -> 0 | AN39: =idp_SP1[[#This Row],[sp1_idp_target_cp]]+ndp_SP1[[#This Row],[sp1_ndp_target_cp]] -> 0 | AO39: =idp_SP1[[#This Row],[sp1_idp_target_gb]]+ndp_SP1[[#This Row],[sp1_ndp_target_gb]] -> 0 | AP39: =idp_SP1[[#This Row],[sp1_idp_target_fs]]+ndp_SP1[[#This Row],[sp1_ndp_target_fs]] -> 0 | AQ39: =idp_SP1[[#This Row],[sp1_idp_target_li]]+ndp_SP1[[#This Row],[sp1_ndp_target_li]] -> 0 | AR39: =idp_SP1[[#This Row],[sp1_idp_target_cw]]+ndp_SP1[[#This Row],[sp1_ndp_target_cw]] -> 0 | AS39: =idp_SP1[[#This Row],[sp1_idp_target_joint]]+ndp_SP1[[#This Row],[sp1_ndp_target_joint]] -> 0 | AT39: 0 | AU39: 0 | AV39: 0 | AW39: 0 | AX39: 0 | AY39: 0 | AZ39: 0 | BA39: 0 | BB39: 0 | BC39: 0 | BD39: 0 | BE39: 0 | BF39: 0
A40: Kharkivska | B40: UA63 | C40: Kharkiv city | D40: 20-50km | E40: UA63_UCAP | F40: 133606 | G40: 511154.69 | H40: 644760.69 | I40: =idp_SP1[[#This Row],[sp1_idp_pin_ed]]+ndp_SP1[[#This Row],[sp1_ndp_pin_ed]] -> 50087 | J40: =idp_SP1[[#This Row],[sp1_idp_pin_fl]]+ndp_SP1[[#This Row],[sp1_ndp_pin_fl]] -> 135269 | K40: =idp_SP1[[#This Row],[sp1_idp_pin_he]]+ndp_SP1[[#This Row],[sp1_ndp_pin_he]] -> 500189 | L40: =idp_SP1[[#This Row],[sp1_idp_pin_pr]]+ndp_SP1[[#This Row],[sp1_ndp_pin_pr]] -> 460755 | M40: =idp_SP1[[#This Row],[sp1_idp_pin_sn]]+ndp_SP1[[#This Row],[sp1_ndp_pin_sn]] -> 332916 | N40: =idp_SP1[[#This Row],[sp1_idp_pin_wa]]+ndp_SP1[[#This Row],[sp1_ndp_pin_wa]] -> 573837 | O40: =idp_SP1[[#This Row],[sp1_idp_pin_gp]]+ndp_SP1[[#This Row],[sp1_ndp_pin_gp]] -> 460755 | P40: =idp_SP1[[#This Row],[sp1_idp_pin_cp]]+ndp_SP1[[#This Row],[sp1_ndp_pin_cp]] -> 198748 | Q40: =idp_SP1[[#This Row],[sp1_idp_pin_gb]]+ndp_SP1[[#This Row],[sp1_ndp_pin_gb]] -> 152560 | R40: =idp_SP1[[#This Row],[sp1_idp_pin_fs]]+ndp_SP1[[#This Row],[sp1_ndp_pin_fs]] -> 135269 | S40: =idp_SP1[[#This Row],[sp1_idp_pin_li]]+ndp_SP1[[#This Row],[sp1_ndp_pin_li]] -> 0 | T40: =idp_SP1[[#This Row],[sp1_idp_pin_adopted]]+ndp_SP1[[#This Row],[sp1_ndp_pin_adopted]] -> 573837 | U40: 4 | V40: 4 | W40: 4 | X40: =MAX(idp_SP1[[#This Row],[sp1_idp_sev_pr]],ndp_SP1[[#This Row],[sp1_ndp_sev_pr]]) -> 4 | Y40: 4 | Z40: 4 | AA40: 4 | AB40: 4 | AC40: 4 | AD40: 4 | AE40: 4 | AF40: 4 | AG40: =idp_SP1[[#This Row],[sp1_idp_target_ed]]+ndp_SP1[[#This Row],[sp1_ndp_target_ed]] -> 45078 | AH40: =idp_SP1[[#This Row],[sp1_idp_target_fl]]+ndp_SP1[[#This Row],[sp1_ndp_target_fl]] -> 135269 | AI40: =idp_SP1[[#This Row],[sp1_idp_target_he]]+ndp_SP1[[#This Row],[sp1_ndp_target_he]] -> 152680 | AJ40: =idp_SP1[[#This Row],[sp1_idp_target_pr]]+ndp_SP1[[#This Row],[sp1_ndp_target_pr]] -> 206451 | AK40: =idp_SP1[[#This Row],[sp1_idp_target_sn]]+ndp_SP1[[#This Row],[sp1_ndp_target_sn]] -> 145446 | AL40: =idp_SP1[[#This Row],[sp1_idp_target_wa]]+ndp_SP1[[#This Row],[sp1_ndp_target_wa]] -> 573837 | AM40: =idp_SP1[[#This Row],[sp1_idp_target_gp]]+ndp_SP1[[#This Row],[sp1_ndp_target_gp]] -> 206451 | AN40: =idp_SP1[[#This Row],[sp1_idp_target_cp]]+ndp_SP1[[#This Row],[sp1_ndp_target_cp]] -> 157784 | AO40: =idp_SP1[[#This Row],[sp1_idp_target_gb]]+ndp_SP1[[#This Row],[sp1_ndp_target_gb]] -> 76280 | AP40: =idp_SP1[[#This Row],[sp1_idp_target_fs]]+ndp_SP1[[#This Row],[sp1_ndp_target_fs]] -> 135269 | AQ40: =idp_SP1[[#This Row],[sp1_idp_target_li]]+ndp_SP1[[#This Row],[sp1_ndp_target_li]] -> 0 | AR40: =idp_SP1[[#This Row],[sp1_idp_target_cw]]+ndp_SP1[[#This Row],[sp1_ndp_target_cw]] -> 91412 | AS40: =idp_SP1[[#This Row],[sp1_idp_target_joint]]+ndp_SP1[[#This Row],[sp1_ndp_target_joint]] -> 573837 | AT40: 45078 | AU40: 135269 | AV40: 107243 | AW40: 206451 | AX40: 145446 | AY40: 573837 | AZ40: 206451 | BA40: 157784 | BB40: 76280 | BC40: 135269 | BD40: 0 | BE40: 91412 | BF40: 573837
A41: Khersonska | B41: UA65 | C41: 0-20 km (w/o Kherson) | D41: 0-20km | E41: UA65_U20X | F41: 5315 | G41: 18255 | H41: 23570 | I41: =idp_SP1[[#This Row],[sp1_idp_pin_ed]]+ndp_SP1[[#This Row],[sp1_ndp_pin_ed]] -> 2387 | J41: =idp_SP1[[#This Row],[sp1_idp_pin_fl]]+ndp_SP1[[#This Row],[sp1_ndp_pin_fl]] -> 7812 | K41: =idp_SP1[[#This Row],[sp1_idp_pin_he]]+ndp_SP1[[#This Row],[sp1_ndp_pin_he]] -> 18285 | L41: =idp_SP1[[#This Row],[sp1_idp_pin_pr]]+ndp_SP1[[#This Row],[sp1_ndp_pin_pr]] -> 21638 | M41: =idp_SP1[[#This Row],[sp1_idp_pin_sn]]+ndp_SP1[[#This Row],[sp1_ndp_pin_sn]] -> 22627 | N41: =idp_SP1[[#This Row],[sp1_idp_pin_wa]]+ndp_SP1[[#This Row],[sp1_ndp_pin_wa]] -> 20624 | O41: =idp_SP1[[#This Row],[sp1_idp_pin_gp]]+ndp_SP1[[#This Row],[sp1_ndp_pin_gp]] -> 21638 | P41: =idp_SP1[[#This Row],[sp1_idp_pin_cp]]+ndp_SP1[[#This Row],[sp1_ndp_pin_cp]] -> 7267 | Q41: =idp_SP1[[#This Row],[sp1_idp_pin_gb]]+ndp_SP1[[#This Row],[sp1_ndp_pin_gb]] -> 11880 | R41: =idp_SP1[[#This Row],[sp1_idp_pin_fs]]+ndp_SP1[[#This Row],[sp1_ndp_pin_fs]] -> 7812 | S41: =idp_SP1[[#This Row],[sp1_idp_pin_li]]+ndp_SP1[[#This Row],[sp1_ndp_pin_li]] -> 0 | T41: =idp_SP1[[#This Row],[sp1_idp_pin_adopted]]+ndp_SP1[[#This Row],[sp1_ndp_pin_adopted]] -> 22627 | U41: 5 | V41: 4 | W41: 4 | X41: =MAX(idp_SP1[[#This Row],[sp1_idp_sev_pr]],ndp_SP1[[#This Row],[sp1_ndp_sev_pr]]) -> 5 | Y41: 5 | Z41: 5 | AA41: 5 | AB41: 5 | AC41: 5 | AD41: 4 | AE41: 4 | AF41: 5 | AG41: =idp_SP1[[#This Row],[sp1_idp_target_ed]]+ndp_SP1[[#This Row],[sp1_ndp_target_ed]] -> 2148 | AH41: =idp_SP1[[#This Row],[sp1_idp_target_fl]]+ndp_SP1[[#This Row],[sp1_ndp_target_fl]] -> 7812 | AI41: =idp_SP1[[#This Row],[sp1_idp_target_he]]+ndp_SP1[[#This Row],[sp1_ndp_target_he]] -> 10814 | AJ41: =idp_SP1[[#This Row],[sp1_idp_target_pr]]+ndp_SP1[[#This Row],[sp1_ndp_target_pr]] -> 9274 | AK41: =idp_SP1[[#This Row],[sp1_idp_target_sn]]+ndp_SP1[[#This Row],[sp1_ndp_target_sn]] -> 13554 | AL41: =idp_SP1[[#This Row],[sp1_idp_target_wa]]+ndp_SP1[[#This Row],[sp1_ndp_target_wa]] -> 20624 | AM41: =idp_SP1[[#This Row],[sp1_idp_target_gp]]+ndp_SP1[[#This Row],[sp1_ndp_target_gp]] -> 9274 | AN41: =idp_SP1[[#This Row],[sp1_idp_target_cp]]+ndp_SP1[[#This Row],[sp1_ndp_target_cp]] -> 5791 | AO41: =idp_SP1[[#This Row],[sp1_idp_target_gb]]+ndp_SP1[[#This Row],[sp1_ndp_target_gb]] -> 594 | AP41: =idp_SP1[[#This Row],[sp1_idp_target_fs]]+ndp_SP1[[#This Row],[sp1_ndp_target_fs]] -> 7812 | AQ41: =idp_SP1[[#This Row],[sp1_idp_target_li]]+ndp_SP1[[#This Row],[sp1_ndp_target_li]] -> 0 | AR41: =idp_SP1[[#This Row],[sp1_idp_target_cw]]+ndp_SP1[[#This Row],[sp1_ndp_target_cw]] -> 19796 | AS41: =idp_SP1[[#This Row],[sp1_idp_target_joint]]+ndp_SP1[[#This Row],[sp1_ndp_target_joint]] -> 22176 | AT41: 2148 | AU41: 7812 | AV41: 10814 | AW41: 9274 | AX41: 13554 | AY41: 20624 | AZ41: 9274 | BA41: 5791 | BB41: 594 | BC41: 7812 | BD41: 0 | BE41: 19796 | BF41: 22176
A42: Khersonska | B42: UA65 | C42: 21-50 km | D42: 20-50km | E42: UA65_U50A | F42: 1930 | G42: 3343.7299 | H42: 5273.7299 | I42: =idp_SP1[[#This Row],[sp1_idp_pin_ed]]+ndp_SP1[[#This Row],[sp1_ndp_pin_ed]] -> 455 | J42: =idp_SP1[[#This Row],[sp1_idp_pin_fl]]+ndp_SP1[[#This Row],[sp1_ndp_pin_fl]] -> 1732 | K42: =idp_SP1[[#This Row],[sp1_idp_pin_he]]+ndp_SP1[[#This Row],[sp1_ndp_pin_he]] -> 4091 | L42: =idp_SP1[[#This Row],[sp1_idp_pin_pr]]+ndp_SP1[[#This Row],[sp1_ndp_pin_pr]] -> 4746 | M42: =idp_SP1[[#This Row],[sp1_idp_pin_sn]]+ndp_SP1[[#This Row],[sp1_ndp_pin_sn]] -> 4235 | N42: =idp_SP1[[#This Row],[sp1_idp_pin_wa]]+ndp_SP1[[#This Row],[sp1_ndp_pin_wa]] -> 4394 | O42: =idp_SP1[[#This Row],[sp1_idp_pin_gp]]+ndp_SP1[[#This Row],[sp1_ndp_pin_gp]] -> 4746 | P42: =idp_SP1[[#This Row],[sp1_idp_pin_cp]]+ndp_SP1[[#This Row],[sp1_ndp_pin_cp]] -> 1543 | Q42: =idp_SP1[[#This Row],[sp1_idp_pin_gb]]+ndp_SP1[[#This Row],[sp1_ndp_pin_gb]] -> 2068 | R42: =idp_SP1[[#This Row],[sp1_idp_pin_fs]]+ndp_SP1[[#This Row],[sp1_ndp_pin_fs]] -> 1732 | S42: =idp_SP1[[#This Row],[sp1_idp_pin_li]]+ndp_SP1[[#This Row],[sp1_ndp_pin_li]] -> 0 | T42: =idp_SP1[[#This Row],[sp1_idp_pin_adopted]]+ndp_SP1[[#This Row],[sp1_ndp_pin_adopted]] -> 4746 | U42: 4 | V42: 4 | W42: 4 | X42: =MAX(idp_SP1[[#This Row],[sp1_idp_sev_pr]],ndp_SP1[[#This Row],[sp1_ndp_sev_pr]]) -> 4 | Y42: 4 | Z42: 4 | AA42: 4 | AB42: 4 | AC42: 4 | AD42: 4 | AE42: 4 | AF42: 4 | AG42: =idp_SP1[[#This Row],[sp1_idp_target_ed]]+ndp_SP1[[#This Row],[sp1_ndp_target_ed]] -> 410 | AH42: =idp_SP1[[#This Row],[sp1_idp_target_fl]]+ndp_SP1[[#This Row],[sp1_ndp_target_fl]] -> 1732 | AI42: =idp_SP1[[#This Row],[sp1_idp_target_he]]+ndp_SP1[[#This Row],[sp1_ndp_target_he]] -> 2845 | AJ42: =idp_SP1[[#This Row],[sp1_idp_target_pr]]+ndp_SP1[[#This Row],[sp1_ndp_target_pr]] -> 2356 | AK42: =idp_SP1[[#This Row],[sp1_idp_target_sn]]+ndp_SP1[[#This Row],[sp1_ndp_target_sn]] -> 2501 | AL42: =idp_SP1[[#This Row],[sp1_idp_target_wa]]+ndp_SP1[[#This Row],[sp1_ndp_target_wa]] -> 4394 | AM42: =idp_SP1[[#This Row],[sp1_idp_target_gp]]+ndp_SP1[[#This Row],[sp1_ndp_target_gp]] -> 2356 | AN42: =idp_SP1[[#This Row],[sp1_idp_target_cp]]+ndp_SP1[[#This Row],[sp1_ndp_target_cp]] -> 1147 | AO42: =idp_SP1[[#This Row],[sp1_idp_target_gb]]+ndp_SP1[[#This Row],[sp1_ndp_target_gb]] -> 1033 | AP42: =idp_SP1[[#This Row],[sp1_idp_target_fs]]+ndp_SP1[[#This Row],[sp1_ndp_target_fs]] -> 1732 | AQ42: =idp_SP1[[#This Row],[sp1_idp_target_li]]+ndp_SP1[[#This Row],[sp1_ndp_target_li]] -> 0 | AR42: =idp_SP1[[#This Row],[sp1_idp_target_cw]]+ndp_SP1[[#This Row],[sp1_ndp_target_cw]] -> 1119 | AS42: =idp_SP1[[#This Row],[sp1_idp_target_joint]]+ndp_SP1[[#This Row],[sp1_ndp_target_joint]] -> 4394 | AT42: 410 | AU42: 1732 | AV42: 2845 | AW42: 2356 | AX42: 2501 | AY42: 4394 | AZ42: 2356 | BA42: 1147 | BB42: 1033 | BC42: 1732 | BD42: 0 | BE42: 1119 | BF42: 4394
A43: Khersonska | B43: UA65 | C43: 51+ km | D43: 50+ | E43: UA65_U51P | F43: 0 | G43: 0 | I43: =idp_SP1[[#This Row],[sp1_idp_pin_ed]]+ndp_SP1[[#This Row],[sp1_ndp_pin_ed]] -> 0 | J43: =idp_SP1[[#This Row],[sp1_idp_pin_fl]]+ndp_SP1[[#This Row],[sp1_ndp_pin_fl]] -> 0 | K43: =idp_SP1[[#This Row],[sp1_idp_pin_he]]+ndp_SP1[[#This Row],[sp1_ndp_pin_he]] -> 0 | L43: =idp_SP1[[#This Row],[sp1_idp_pin_pr]]+ndp_SP1[[#This Row],[sp1_ndp_pin_pr]] -> 0 | M43: =idp_SP1[[#This Row],[sp1_idp_pin_sn]]+ndp_SP1[[#This Row],[sp1_ndp_pin_sn]] -> 0 | N43: =idp_SP1[[#This Row],[sp1_idp_pin_wa]]+ndp_SP1[[#This Row],[sp1_ndp_pin_wa]] -> 0 | O43: =idp_SP1[[#This Row],[sp1_idp_pin_gp]]+ndp_SP1[[#This Row],[sp1_ndp_pin_gp]] -> 0 | P43: =idp_SP1[[#This Row],[sp1_idp_pin_cp]]+ndp_SP1[[#This Row],[sp1_ndp_pin_cp]] -> 0 | Q43: =idp_SP1[[#This Row],[sp1_idp_pin_gb]]+ndp_SP1[[#This Row],[sp1_ndp_pin_gb]] -> 0 | R43: =idp_SP1[[#This Row],[sp1_idp_pin_fs]]+ndp_SP1[[#This Row],[sp1_ndp_pin_fs]] -> 0 | S43: =idp_SP1[[#This Row],[sp1_idp_pin_li]]+ndp_SP1[[#This Row],[sp1_ndp_pin_li]] -> 0 | T43: =idp_SP1[[#This Row],[sp1_idp_pin_adopted]]+ndp_SP1[[#This Row],[sp1_ndp_pin_adopted]] -> 0 | X43: =MAX(idp_SP1[[#This Row],[sp1_idp_sev_pr]],ndp_SP1[[#This Row],[sp1_ndp_sev_pr]]) -> 0 | Y43: 0 | AG43: =idp_SP1[[#This Row],[sp1_idp_target_ed]]+ndp_SP1[[#This Row],[sp1_ndp_target_ed]] -> 0 | AH43: =idp_SP1[[#This Row],[sp1_idp_target_fl]]+ndp_SP1[[#This Row],[sp1_ndp_target_fl]] -> 0 | AI43: =idp_SP1[[#This Row],[sp1_idp_target_he]]+ndp_SP1[[#This Row],[sp1_ndp_target_he]] -> 0 | AJ43: =idp_SP1[[#This Row],[sp1_idp_target_pr]]+ndp_SP1[[#This Row],[sp1_ndp_target_pr]] -> 0 | AK43: =idp_SP1[[#This Row],[sp1_idp_target_sn]]+ndp_SP1[[#This Row],[sp1_ndp_target_sn]] -> 0 | AL43: =idp_SP1[[#This Row],[sp1_idp_target_wa]]+ndp_SP1[[#This Row],[sp1_ndp_target_wa]] -> 0 | AM43: =idp_SP1[[#This Row],[sp1_idp_target_gp]]+ndp_SP1[[#This Row],[sp1_ndp_target_gp]] -> 0 | AN43: =idp_SP1[[#This Row],[sp1_idp_target_cp]]+ndp_SP1[[#This Row],[sp1_ndp_target_cp]] -> 0 | AO43: =idp_SP1[[#This Row],[sp1_idp_target_gb]]+ndp_SP1[[#This Row],[sp1_ndp_target_gb]] -> 0 | AP43: =idp_SP1[[#This Row],[sp1_idp_target_fs]]+ndp_SP1[[#This Row],[sp1_ndp_target_fs]] -> 0 | AQ43: =idp_SP1[[#This Row],[sp1_idp_target_li]]+ndp_SP1[[#This Row],[sp1_ndp_target_li]] -> 0 | AR43: =idp_SP1[[#This Row],[sp1_idp_target_cw]]+ndp_SP1[[#This Row],[sp1_ndp_target_cw]] -> 0 | AS43: =idp_SP1[[#This Row],[sp1_idp_target_joint]]+ndp_SP1[[#This Row],[sp1_ndp_target_joint]] -> 0 | AT43: 0 | AU43: 0 | AV43: 0 | AW43: 0 | AX43: 0 | AY43: 0 | AZ43: 0 | BA43: 0 | BB43: 0 | BC43: 0 | BD43: 0 | BE43: 0 | BF43: 0
A44: Khersonska | B44: UA65 | C44: Kherson city | D44: 0-20km | E44: UA65_UCAP | F44: 9908 | G44: 67022 | H44: 76930 | I44: =idp_SP1[[#This Row],[sp1_idp_pin_ed]]+ndp_SP1[[#This Row],[sp1_ndp_pin_ed]] -> 7476 | J44: =idp_SP1[[#This Row],[sp1_idp_pin_fl]]+ndp_SP1[[#This Row],[sp1_ndp_pin_fl]] -> 25798 | K44: =idp_SP1[[#This Row],[sp1_idp_pin_he]]+ndp_SP1[[#This Row],[sp1_ndp_pin_he]] -> 59680 | L44: =idp_SP1[[#This Row],[sp1_idp_pin_pr]]+ndp_SP1[[#This Row],[sp1_ndp_pin_pr]] -> 66063 | M44: =idp_SP1[[#This Row],[sp1_idp_pin_sn]]+ndp_SP1[[#This Row],[sp1_ndp_pin_sn]] -> 64522 | N44: =idp_SP1[[#This Row],[sp1_idp_pin_wa]]+ndp_SP1[[#This Row],[sp1_ndp_pin_wa]] -> 76930 | O44: =idp_SP1[[#This Row],[sp1_idp_pin_gp]]+ndp_SP1[[#This Row],[sp1_ndp_pin_gp]] -> 66063 | P44: =idp_SP1[[#This Row],[sp1_idp_pin_cp]]+ndp_SP1[[#This Row],[sp1_ndp_pin_cp]] -> 22479 | Q44: =idp_SP1[[#This Row],[sp1_idp_pin_gb]]+ndp_SP1[[#This Row],[sp1_ndp_pin_gb]] -> 30157 | R44: =idp_SP1[[#This Row],[sp1_idp_pin_fs]]+ndp_SP1[[#This Row],[sp1_ndp_pin_fs]] -> 25798 | S44: =idp_SP1[[#This Row],[sp1_idp_pin_li]]+ndp_SP1[[#This Row],[sp1_ndp_pin_li]] -> 0 | T44: =idp_SP1[[#This Row],[sp1_idp_pin_adopted]]+ndp_SP1[[#This Row],[sp1_ndp_pin_adopted]] -> 76930 | U44: 4 | V44: 4 | W44: 5 | X44: =MAX(idp_SP1[[#This Row],[sp1_idp_sev_pr]],ndp_SP1[[#This Row],[sp1_ndp_sev_pr]]) -> 5 | Y44: 5 | Z44: 4 | AA44: 5 | AB44: 5 | AC44: 4 | AD44: 4 | AE44: 4 | AF44: 5 | AG44: =idp_SP1[[#This Row],[sp1_idp_target_ed]]+ndp_SP1[[#This Row],[sp1_ndp_target_ed]] -> 6728 | AH44: =idp_SP1[[#This Row],[sp1_idp_target_fl]]+ndp_SP1[[#This Row],[sp1_ndp_target_fl]] -> 25798 | AI44: =idp_SP1[[#This Row],[sp1_idp_target_he]]+ndp_SP1[[#This Row],[sp1_ndp_target_he]] -> 34170 | AJ44: =idp_SP1[[#This Row],[sp1_idp_target_pr]]+ndp_SP1[[#This Row],[sp1_ndp_target_pr]] -> 26520 | AK44: =idp_SP1[[#This Row],[sp1_idp_target_sn]]+ndp_SP1[[#This Row],[sp1_ndp_target_sn]] -> 41403 | AL44: =idp_SP1[[#This Row],[sp1_idp_target_wa]]+ndp_SP1[[#This Row],[sp1_ndp_target_wa]] -> 76930 | AM44: =idp_SP1[[#This Row],[sp1_idp_target_gp]]+ndp_SP1[[#This Row],[sp1_ndp_target_gp]] -> 26520 | AN44: =idp_SP1[[#This Row],[sp1_idp_target_cp]]+ndp_SP1[[#This Row],[sp1_ndp_target_cp]] -> 18861 | AO44: =idp_SP1[[#This Row],[sp1_idp_target_gb]]+ndp_SP1[[#This Row],[sp1_ndp_target_gb]] -> 1508 | AP44: =idp_SP1[[#This Row],[sp1_idp_target_fs]]+ndp_SP1[[#This Row],[sp1_ndp_target_fs]] -> 25798 | AQ44: =idp_SP1[[#This Row],[sp1_idp_target_li]]+ndp_SP1[[#This Row],[sp1_ndp_target_li]] -> 0 | AR44: =idp_SP1[[#This Row],[sp1_idp_target_cw]]+ndp_SP1[[#This Row],[sp1_ndp_target_cw]] -> 39706 | AS44: =idp_SP1[[#This Row],[sp1_idp_target_joint]]+ndp_SP1[[#This Row],[sp1_ndp_target_joint]] -> 76930 | AT44: 6728 | AU44: 25798 | AV44: 34170 | AW44: 26520 | AX44: 41403 | AY44: 76930 | AZ44: 26520 | BA44: 18861 | BB44: 1508 | BC44: 25798 | BD44: 0 | BE44: 39706 | BF44: 76930
A45: Khmelnytska | B45: UA68 | C45: All oblast | D45: 50+ | E45: UA68_UALL | F45: 0 | G45: 0 | I45: =idp_SP1[[#This Row],[sp1_idp_pin_ed]]+ndp_SP1[[#This Row],[sp1_ndp_pin_ed]] -> 0 | J45: =idp_SP1[[#This Row],[sp1_idp_pin_fl]]+ndp_SP1[[#This Row],[sp1_ndp_pin_fl]] -> 0 | K45: =idp_SP1[[#This Row],[sp1_idp_pin_he]]+ndp_SP1[[#This Row],[sp1_ndp_pin_he]] -> 0 | L45: =idp_SP1[[#This Row],[sp1_idp_pin_pr]]+ndp_SP1[[#This Row],[sp1_ndp_pin_pr]] -> 0 | M45: =idp_SP1[[#This Row],[sp1_idp_pin_sn]]+ndp_SP1[[#This Row],[sp1_ndp_pin_sn]] -> 0 | N45: =idp_SP1[[#This Row],[sp1_idp_pin_wa]]+ndp_SP1[[#This Row],[sp1_ndp_pin_wa]] -> 0 | O45: =idp_SP1[[#This Row],[sp1_idp_pin_gp]]+ndp_SP1[[#This Row],[sp1_ndp_pin_gp]] -> 0 | P45: =idp_SP1[[#This Row],[sp1_idp_pin_cp]]+ndp_SP1[[#This Row],[sp1_ndp_pin_cp]] -> 0 | Q45: =idp_SP1[[#This Row],[sp1_idp_pin_gb]]+ndp_SP1[[#This Row],[sp1_ndp_pin_gb]] -> 0 | R45: =idp_SP1[[#This Row],[sp1_idp_pin_fs]]+ndp_SP1[[#This Row],[sp1_ndp_pin_fs]] -> 0 | S45: =idp_SP1[[#This Row],[sp1_idp_pin_li]]+ndp_SP1[[#This Row],[sp1_ndp_pin_li]] -> 0 | T45: =idp_SP1[[#This Row],[sp1_idp_pin_adopted]]+ndp_SP1[[#This Row],[sp1_ndp_pin_adopted]] -> 0 | X45: =MAX(idp_SP1[[#This Row],[sp1_idp_sev_pr]],ndp_SP1[[#This Row],[sp1_ndp_sev_pr]]) -> 0 | Y45: 0 | AG45: =idp_SP1[[#This Row],[sp1_idp_target_ed]]+ndp_SP1[[#This Row],[sp1_ndp_target_ed]] -> 0 | AH45: =idp_SP1[[#This Row],[sp1_idp_target_fl]]+ndp_SP1[[#This Row],[sp1_ndp_target_fl]] -> 0 | AI45: =idp_SP1[[#This Row],[sp1_idp_target_he]]+ndp_SP1[[#This Row],[sp1_ndp_target_he]] -> 0 | AJ45: =idp_SP1[[#This Row],[sp1_idp_target_pr]]+ndp_SP1[[#This Row],[sp1_ndp_target_pr]] -> 0 | AK45: =idp_SP1[[#This Row],[sp1_idp_target_sn]]+ndp_SP1[[#This Row],[sp1_ndp_target_sn]] -> 0 | AL45: =idp_SP1[[#This Row],[sp1_idp_target_wa]]+ndp_SP1[[#This Row],[sp1_ndp_target_wa]] -> 0 | AM45: =idp_SP1[[#This Row],[sp1_idp_target_gp]]+ndp_SP1[[#This Row],[sp1_ndp_target_gp]] -> 0 | AN45: =idp_SP1[[#This Row],[sp1_idp_target_cp]]+ndp_SP1[[#This Row],[sp1_ndp_target_cp]] -> 0 | AO45: =idp_SP1[[#This Row],[sp1_idp_target_gb]]+ndp_SP1[[#This Row],[sp1_ndp_target_gb]] -> 0 | AP45: =idp_SP1[[#This Row],[sp1_idp_target_fs]]+ndp_SP1[[#This Row],[sp1_ndp_target_fs]] -> 0 | AQ45: =idp_SP1[[#This Row],[sp1_idp_target_li]]+ndp_SP1[[#This Row],[sp1_ndp_target_li]] -> 0 | AR45: =idp_SP1[[#This Row],[sp1_idp_target_cw]]+ndp_SP1[[#This Row],[sp1_ndp_target_cw]] -> 0 | AS45: =idp_SP1[[#This Row],[sp1_idp_target_joint]]+ndp_SP1[[#This Row],[sp1_ndp_target_joint]] -> 0 | AT45: 0 | AU45: 0 | AV45: 0 | AW45: 0 | AX45: 0 | AY45: 0 | AZ45: 0 | BA45: 0 | BB45: 0 | BC45: 0 | BD45: 0 | BE45: 0 | BF45: 0
A46: Cherkaska | B46: UA71 | C46: All oblast | D46: 50+ | E46: UA71_UALL | F46: 0 | G46: 0 | I46: =idp_SP1[[#This Row],[sp1_idp_pin_ed]]+ndp_SP1[[#This Row],[sp1_ndp_pin_ed]] -> 0 | J46: =idp_SP1[[#This Row],[sp1_idp_pin_fl]]+ndp_SP1[[#This Row],[sp1_ndp_pin_fl]] -> 0 | K46: =idp_SP1[[#This Row],[sp1_idp_pin_he]]+ndp_SP1[[#This Row],[sp1_ndp_pin_he]] -> 0 | L46: =idp_SP1[[#This Row],[sp1_idp_pin_pr]]+ndp_SP1[[#This Row],[sp1_ndp_pin_pr]] -> 0 | M46: =idp_SP1[[#This Row],[sp1_idp_pin_sn]]+ndp_SP1[[#This Row],[sp1_ndp_pin_sn]] -> 0 | N46: =idp_SP1[[#This Row],[sp1_idp_pin_wa]]+ndp_SP1[[#This Row],[sp1_ndp_pin_wa]] -> 0 | O46: =idp_SP1[[#This Row],[sp1_idp_pin_gp]]+ndp_SP1[[#This Row],[sp1_ndp_pin_gp]] -> 0 | P46: =idp_SP1[[#This Row],[sp1_idp_pin_cp]]+ndp_SP1[[#This Row],[sp1_ndp_pin_cp]] -> 0 | Q46: =idp_SP1[[#This Row],[sp1_idp_pin_gb]]+ndp_SP1[[#This Row],[sp1_ndp_pin_gb]] -> 0 | R46: =idp_SP1[[#This Row],[sp1_idp_pin_fs]]+ndp_SP1[[#This Row],[sp1_ndp_pin_fs]] -> 0 | S46: =idp_SP1[[#This Row],[sp1_idp_pin_li]]+ndp_SP1[[#This Row],[sp1_ndp_pin_li]] -> 0 | T46: =idp_SP1[[#This Row],[sp1_idp_pin_adopted]]+ndp_SP1[[#This Row],[sp1_ndp_pin_adopted]] -> 0 | X46: =MAX(idp_SP1[[#This Row],[sp1_idp_sev_pr]],ndp_SP1[[#This Row],[sp1_ndp_sev_pr]]) -> 0 | Y46: 0 | AG46: =idp_SP1[[#This Row],[sp1_idp_target_ed]]+ndp_SP1[[#This Row],[sp1_ndp_target_ed]] -> 0 | AH46: =idp_SP1[[#This Row],[sp1_idp_target_fl]]+ndp_SP1[[#This Row],[sp1_ndp_target_fl]] -> 0 | AI46: =idp_SP1[[#This Row],[sp1_idp_target_he]]+ndp_SP1[[#This Row],[sp1_ndp_target_he]] -> 0 | AJ46: =idp_SP1[[#This Row],[sp1_idp_target_pr]]+ndp_SP1[[#This Row],[sp1_ndp_target_pr]] -> 0 | AK46: =idp_SP1[[#This Row],[sp1_idp_target_sn]]+ndp_SP1[[#This Row],[sp1_ndp_target_sn]] -> 0 | AL46: =idp_SP1[[#This Row],[sp1_idp_target_wa]]+ndp_SP1[[#This Row],[sp1_ndp_target_wa]] -> 0 | AM46: =idp_SP1[[#This Row],[sp1_idp_target_gp]]+ndp_SP1[[#This Row],[sp1_ndp_target_gp]] -> 0 | AN46: =idp_SP1[[#This Row],[sp1_idp_target_cp]]+ndp_SP1[[#This Row],[sp1_ndp_target_cp]] -> 0 | AO46: =idp_SP1[[#This Row],[sp1_idp_target_gb]]+ndp_SP1[[#This Row],[sp1_ndp_target_gb]] -> 0 | AP46: =idp_SP1[[#This Row],[sp1_idp_target_fs]]+ndp_SP1[[#This Row],[sp1_ndp_target_fs]] -> 0 | AQ46: =idp_SP1[[#This Row],[sp1_idp_target_li]]+ndp_SP1[[#This Row],[sp1_ndp_target_li]] -> 0 | AR46: =idp_SP1[[#This Row],[sp1_idp_target_cw]]+ndp_SP1[[#This Row],[sp1_ndp_target_cw]] -> 0 | AS46: =idp_SP1[[#This Row],[sp1_idp_target_joint]]+ndp_SP1[[#This Row],[sp1_ndp_target_joint]] -> 0 | AT46: 0 | AU46: 0 | AV46: 0 | AW46: 0 | AX46: 0 | AY46: 0 | AZ46: 0 | BA46: 0 | BB46: 0 | BC46: 0 | BD46: 0 | BE46: 0 | BF46: 0
A47: Chernivetska | B47: UA73 | C47: All oblast | D47: 50+ | E47: UA73_UALL | F47: 0 | G47: 0 | I47: =idp_SP1[[#This Row],[sp1_idp_pin_ed]]+ndp_SP1[[#This Row],[sp1_ndp_pin_ed]] -> 0 | J47: =idp_SP1[[#This Row],[sp1_idp_pin_fl]]+ndp_SP1[[#This Row],[sp1_ndp_pin_fl]] -> 0 | K47: =idp_SP1[[#This Row],[sp1_idp_pin_he]]+ndp_SP1[[#This Row],[sp1_ndp_pin_he]] -> 0 | L47: =idp_SP1[[#This Row],[sp1_idp_pin_pr]]+ndp_SP1[[#This Row],[sp1_ndp_pin_pr]] -> 0 | M47: =idp_SP1[[#This Row],[sp1_idp_pin_sn]]+ndp_SP1[[#This Row],[sp1_ndp_pin_sn]] -> 0 | N47: =idp_SP1[[#This Row],[sp1_idp_pin_wa]]+ndp_SP1[[#This Row],[sp1_ndp_pin_wa]] -> 0 | O47: =idp_SP1[[#This Row],[sp1_idp_pin_gp]]+ndp_SP1[[#This Row],[sp1_ndp_pin_gp]] -> 0 | P47: =idp_SP1[[#This Row],[sp1_idp_pin_cp]]+ndp_SP1[[#This Row],[sp1_ndp_pin_cp]] -> 0 | Q47: =idp_SP1[[#This Row],[sp1_idp_pin_gb]]+ndp_SP1[[#This Row],[sp1_ndp_pin_gb]] -> 0 | R47: =idp_SP1[[#This Row],[sp1_idp_pin_fs]]+ndp_SP1[[#This Row],[sp1_ndp_pin_fs]] -> 0 | S47: =idp_SP1[[#This Row],[sp1_idp_pin_li]]+ndp_SP1[[#This Row],[sp1_ndp_pin_li]] -> 0 | T47: =idp_SP1[[#This Row],[sp1_idp_pin_adopted]]+ndp_SP1[[#This Row],[sp1_ndp_pin_adopted]] -> 0 | X47: =MAX(idp_SP1[[#This Row],[sp1_idp_sev_pr]],ndp_SP1[[#This Row],[sp1_ndp_sev_pr]]) -> 0 | Y47: 0 | AG47: =idp_SP1[[#This Row],[sp1_idp_target_ed]]+ndp_SP1[[#This Row],[sp1_ndp_target_ed]] -> 0 | AH47: =idp_SP1[[#This Row],[sp1_idp_target_fl]]+ndp_SP1[[#This Row],[sp1_ndp_target_fl]] -> 0 | AI47: =idp_SP1[[#This Row],[sp1_idp_target_he]]+ndp_SP1[[#This Row],[sp1_ndp_target_he]] -> 0 | AJ47: =idp_SP1[[#This Row],[sp1_idp_target_pr]]+ndp_SP1[[#This Row],[sp1_ndp_target_pr]] -> 0 | AK47: =idp_SP1[[#This Row],[sp1_idp_target_sn]]+ndp_SP1[[#This Row],[sp1_ndp_target_sn]] -> 0 | AL47: =idp_SP1[[#This Row],[sp1_idp_target_wa]]+ndp_SP1[[#This Row],[sp1_ndp_target_wa]] -> 0 | AM47: =idp_SP1[[#This Row],[sp1_idp_target_gp]]+ndp_SP1[[#This Row],[sp1_ndp_target_gp]] -> 0 | AN47: =idp_SP1[[#This Row],[sp1_idp_target_cp]]+ndp_SP1[[#This Row],[sp1_ndp_target_cp]] -> 0 | AO47: =idp_SP1[[#This Row],[sp1_idp_target_gb]]+ndp_SP1[[#This Row],[sp1_ndp_target_gb]] -> 0 | AP47: =idp_SP1[[#This Row],[sp1_idp_target_fs]]+ndp_SP1[[#This Row],[sp1_ndp_target_fs]] -> 0 | AQ47: =idp_SP1[[#This Row],[sp1_idp_target_li]]+ndp_SP1[[#This Row],[sp1_ndp_target_li]] -> 0 | AR47: =idp_SP1[[#This Row],[sp1_idp_target_cw]]+ndp_SP1[[#This Row],[sp1_ndp_target_cw]] -> 0 | AS47: =idp_SP1[[#This Row],[sp1_idp_target_joint]]+ndp_SP1[[#This Row],[sp1_ndp_target_joint]] -> 0 | AT47: 0 | AU47: 0 | AV47: 0 | AW47: 0 | AX47: 0 | AY47: 0 | AZ47: 0 | BA47: 0 | BB47: 0 | BC47: 0 | BD47: 0 | BE47: 0 | BF47: 0
A48: Chernihivska | B48: UA74 | C48: 0-20 km | D48: 0-20km | E48: UA74_U20A | F48: 4864 | G48: 79652 | H48: 84516 | I48: =idp_SP1[[#This Row],[sp1_idp_pin_ed]]+ndp_SP1[[#This Row],[sp1_ndp_pin_ed]] -> 7678 | J48: =idp_SP1[[#This Row],[sp1_idp_pin_fl]]+ndp_SP1[[#This Row],[sp1_ndp_pin_fl]] -> 11991 | K48: =idp_SP1[[#This Row],[sp1_idp_pin_he]]+ndp_SP1[[#This Row],[sp1_ndp_pin_he]] -> 65565 | L48: =idp_SP1[[#This Row],[sp1_idp_pin_pr]]+ndp_SP1[[#This Row],[sp1_ndp_pin_pr]] -> 45534 | M48: =idp_SP1[[#This Row],[sp1_idp_pin_sn]]+ndp_SP1[[#This Row],[sp1_ndp_pin_sn]] -> 70576 | N48: =idp_SP1[[#This Row],[sp1_idp_pin_wa]]+ndp_SP1[[#This Row],[sp1_ndp_pin_wa]] -> 70576 | O48: =idp_SP1[[#This Row],[sp1_idp_pin_gp]]+ndp_SP1[[#This Row],[sp1_ndp_pin_gp]] -> 45534 | P48: =idp_SP1[[#This Row],[sp1_idp_pin_cp]]+ndp_SP1[[#This Row],[sp1_ndp_pin_cp]] -> 20885 | Q48: =idp_SP1[[#This Row],[sp1_idp_pin_gb]]+ndp_SP1[[#This Row],[sp1_ndp_pin_gb]] -> 33131 | R48: =idp_SP1[[#This Row],[sp1_idp_pin_fs]]+ndp_SP1[[#This Row],[sp1_ndp_pin_fs]] -> 11991 | S48: =idp_SP1[[#This Row],[sp1_idp_pin_li]]+ndp_SP1[[#This Row],[sp1_ndp_pin_li]] -> 0 | T48: =idp_SP1[[#This Row],[sp1_idp_pin_adopted]]+ndp_SP1[[#This Row],[sp1_ndp_pin_adopted]] -> 70892 | U48: 4 | V48: 4 | W48: 4 | X48: =MAX(idp_SP1[[#This Row],[sp1_idp_sev_pr]],ndp_SP1[[#This Row],[sp1_ndp_sev_pr]]) -> 4 | Y48: 5 | Z48: 5 | AA48: 4 | AB48: 5 | AC48: 4 | AD48: 4 | AE48: 4 | AF48: 5 | AG48: =idp_SP1[[#This Row],[sp1_idp_target_ed]]+ndp_SP1[[#This Row],[sp1_ndp_target_ed]] -> 6910 | AH48: =idp_SP1[[#This Row],[sp1_idp_target_fl]]+ndp_SP1[[#This Row],[sp1_ndp_target_fl]] -> 11991 | AI48: =idp_SP1[[#This Row],[sp1_idp_target_he]]+ndp_SP1[[#This Row],[sp1_ndp_target_he]] -> 36627 | AJ48: =idp_SP1[[#This Row],[sp1_idp_target_pr]]+ndp_SP1[[#This Row],[sp1_ndp_target_pr]] -> 20095 | AK48: =idp_SP1[[#This Row],[sp1_idp_target_sn]]+ndp_SP1[[#This Row],[sp1_ndp_target_sn]] -> 63411 | AL48: =idp_SP1[[#This Row],[sp1_idp_target_wa]]+ndp_SP1[[#This Row],[sp1_ndp_target_wa]] -> 70576 | AM48: =idp_SP1[[#This Row],[sp1_idp_target_gp]]+ndp_SP1[[#This Row],[sp1_ndp_target_gp]] -> 17689 | AN48: =idp_SP1[[#This Row],[sp1_idp_target_cp]]+ndp_SP1[[#This Row],[sp1_ndp_target_cp]] -> 18024 | AO48: =idp_SP1[[#This Row],[sp1_idp_target_gb]]+ndp_SP1[[#This Row],[sp1_ndp_target_gb]] -> 1656 | AP48: =idp_SP1[[#This Row],[sp1_idp_target_fs]]+ndp_SP1[[#This Row],[sp1_ndp_target_fs]] -> 11991 | AQ48: =idp_SP1[[#This Row],[sp1_idp_target_li]]+ndp_SP1[[#This Row],[sp1_ndp_target_li]] -> 0 | AR48: =idp_SP1[[#This Row],[sp1_idp_target_cw]]+ndp_SP1[[#This Row],[sp1_ndp_target_cw]] -> 40951 | AS48: =idp_SP1[[#This Row],[sp1_idp_target_joint]]+ndp_SP1[[#This Row],[sp1_ndp_target_joint]] -> 70576 | AT48: 6910 | AU48: 11991 | AV48: 36627 | AW48: 20095 | AX48: 63411 | AY48: 70576 | AZ48: 17689 | BA48: 18024 | BB48: 1656 | BC48: 11991 | BD48: 0 | BE48: 40951 | BF48: 70576
A49: Chernihivska | B49: UA74 | C49: 21-50 km | D49: 20-50km | E49: UA74_U50A | F49: 704 | G49: 5332.4751 | H49: 6036.4751 | I49: =idp_SP1[[#This Row],[sp1_idp_pin_ed]]+ndp_SP1[[#This Row],[sp1_ndp_pin_ed]] -> 501 | J49: =idp_SP1[[#This Row],[sp1_idp_pin_fl]]+ndp_SP1[[#This Row],[sp1_ndp_pin_fl]] -> 505 | K49: =idp_SP1[[#This Row],[sp1_idp_pin_he]]+ndp_SP1[[#This Row],[sp1_ndp_pin_he]] -> 4683 | L49: =idp_SP1[[#This Row],[sp1_idp_pin_pr]]+ndp_SP1[[#This Row],[sp1_ndp_pin_pr]] -> 4648 | M49: =idp_SP1[[#This Row],[sp1_idp_pin_sn]]+ndp_SP1[[#This Row],[sp1_ndp_pin_sn]] -> 4471 | N49: =idp_SP1[[#This Row],[sp1_idp_pin_wa]]+ndp_SP1[[#This Row],[sp1_ndp_pin_wa]] -> 4312 | O49: =idp_SP1[[#This Row],[sp1_idp_pin_gp]]+ndp_SP1[[#This Row],[sp1_ndp_pin_gp]] -> 4648 | P49: =idp_SP1[[#This Row],[sp1_idp_pin_cp]]+ndp_SP1[[#This Row],[sp1_ndp_pin_cp]] -> 948 | Q49: =idp_SP1[[#This Row],[sp1_idp_pin_gb]]+ndp_SP1[[#This Row],[sp1_ndp_pin_gb]] -> 1690 | R49: =idp_SP1[[#This Row],[sp1_idp_pin_fs]]+ndp_SP1[[#This Row],[sp1_ndp_pin_fs]] -> 505 | S49: =idp_SP1[[#This Row],[sp1_idp_pin_li]]+ndp_SP1[[#This Row],[sp1_ndp_pin_li]] -> 0 | T49: =idp_SP1[[#This Row],[sp1_idp_pin_adopted]]+ndp_SP1[[#This Row],[sp1_ndp_pin_adopted]] -> 4771 | U49: 4 | V49: 3 | W49: 4 | X49: =MAX(idp_SP1[[#This Row],[sp1_idp_sev_pr]],ndp_SP1[[#This Row],[sp1_ndp_sev_pr]]) -> 4 | Y49: 3 | Z49: 3 | AA49: 4 | AB49: 4 | AC49: 3 | AD49: 3 | AE49: 3 | AF49: 3 | AG49: =idp_SP1[[#This Row],[sp1_idp_target_ed]]+ndp_SP1[[#This Row],[sp1_ndp_target_ed]] -> 451 | AH49: =idp_SP1[[#This Row],[sp1_idp_target_fl]]+ndp_SP1[[#This Row],[sp1_ndp_target_fl]] -> 505 | AI49: =idp_SP1[[#This Row],[sp1_idp_target_he]]+ndp_SP1[[#This Row],[sp1_ndp_target_he]] -> 3221 | AJ49: =idp_SP1[[#This Row],[sp1_idp_target_pr]]+ndp_SP1[[#This Row],[sp1_ndp_target_pr]] -> 1881 | AK49: =idp_SP1[[#This Row],[sp1_idp_target_sn]]+ndp_SP1[[#This Row],[sp1_ndp_target_sn]] -> 1224 | AL49: =idp_SP1[[#This Row],[sp1_idp_target_wa]]+ndp_SP1[[#This Row],[sp1_ndp_target_wa]] -> 2156 | AM49: =idp_SP1[[#This Row],[sp1_idp_target_gp]]+ndp_SP1[[#This Row],[sp1_ndp_target_gp]] -> 1881 | AN49: =idp_SP1[[#This Row],[sp1_idp_target_cp]]+ndp_SP1[[#This Row],[sp1_ndp_target_cp]] -> 412 | AO49: =idp_SP1[[#This Row],[sp1_idp_target_gb]]+ndp_SP1[[#This Row],[sp1_ndp_target_gb]] -> 507 | AP49: =idp_SP1[[#This Row],[sp1_idp_target_fs]]+ndp_SP1[[#This Row],[sp1_ndp_target_fs]] -> 505 | AQ49: =idp_SP1[[#This Row],[sp1_idp_target_li]]+ndp_SP1[[#This Row],[sp1_ndp_target_li]] -> 0 | AR49: =idp_SP1[[#This Row],[sp1_idp_target_cw]]+ndp_SP1[[#This Row],[sp1_ndp_target_cw]] -> 2109 | AS49: =idp_SP1[[#This Row],[sp1_idp_target_joint]]+ndp_SP1[[#This Row],[sp1_ndp_target_joint]] -> 3260 | AT49: 451 | AU49: 101 | AV49: 3221 | AW49: 1881 | AX49: 245 | AY49: 431 | AZ49: 1881 | BA49: 242 | BB49: 102 | BC49: 101 | BD49: 0 | BE49: 421 | BF49: 3260
A50: Chernihivska | B50: UA74 | C50: 51+ km | D50: 50+ | E50: UA74_U51P | F50: 0 | G50: 0 | I50: =idp_SP1[[#This Row],[sp1_idp_pin_ed]]+ndp_SP1[[#This Row],[sp1_ndp_pin_ed]] -> 0 | J50: =idp_SP1[[#This Row],[sp1_idp_pin_fl]]+ndp_SP1[[#This Row],[sp1_ndp_pin_fl]] -> 0 | K50: =idp_SP1[[#This Row],[sp1_idp_pin_he]]+ndp_SP1[[#This Row],[sp1_ndp_pin_he]] -> 0 | L50: =idp_SP1[[#This Row],[sp1_idp_pin_pr]]+ndp_SP1[[#This Row],[sp1_ndp_pin_pr]] -> 0 | M50: =idp_SP1[[#This Row],[sp1_idp_pin_sn]]+ndp_SP1[[#This Row],[sp1_ndp_pin_sn]] -> 0 | N50: =idp_SP1[[#This Row],[sp1_idp_pin_wa]]+ndp_SP1[[#This Row],[sp1_ndp_pin_wa]] -> 0 | O50: =idp_SP1[[#This Row],[sp1_idp_pin_gp]]+ndp_SP1[[#This Row],[sp1_ndp_pin_gp]] -> 0 | P50: =idp_SP1[[#This Row],[sp1_idp_pin_cp]]+ndp_SP1[[#This Row],[sp1_ndp_pin_cp]] -> 0 | Q50: =idp_SP1[[#This Row],[sp1_idp_pin_gb]]+ndp_SP1[[#This Row],[sp1_ndp_pin_gb]] -> 0 | R50: =idp_SP1[[#This Row],[sp1_idp_pin_fs]]+ndp_SP1[[#This Row],[sp1_ndp_pin_fs]] -> 0 | S50: =idp_SP1[[#This Row],[sp1_idp_pin_li]]+ndp_SP1[[#This Row],[sp1_ndp_pin_li]] -> 0 | T50: =idp_SP1[[#This Row],[sp1_idp_pin_adopted]]+ndp_SP1[[#This Row],[sp1_ndp_pin_adopted]] -> 0 | X50: =MAX(idp_SP1[[#This Row],[sp1_idp_sev_pr]],ndp_SP1[[#This Row],[sp1_ndp_sev_pr]]) -> 0 | Y50: 0 | AG50: =idp_SP1[[#This Row],[sp1_idp_target_ed]]+ndp_SP1[[#This Row],[sp1_ndp_target_ed]] -> 0 | AH50: =idp_SP1[[#This Row],[sp1_idp_target_fl]]+ndp_SP1[[#This Row],[sp1_ndp_target_fl]] -> 0 | AI50: =idp_SP1[[#This Row],[sp1_idp_target_he]]+ndp_SP1[[#This Row],[sp1_ndp_target_he]] -> 0 | AJ50: =idp_SP1[[#This Row],[sp1_idp_target_pr]]+ndp_SP1[[#This Row],[sp1_ndp_target_pr]] -> 0 | AK50: =idp_SP1[[#This Row],[sp1_idp_target_sn]]+ndp_SP1[[#This Row],[sp1_ndp_target_sn]] -> 0 | AL50: =idp_SP1[[#This Row],[sp1_idp_target_wa]]+ndp_SP1[[#This Row],[sp1_ndp_target_wa]] -> 0 | AM50: =idp_SP1[[#This Row],[sp1_idp_target_gp]]+ndp_SP1[[#This Row],[sp1_ndp_target_gp]] -> 0 | AN50: =idp_SP1[[#This Row],[sp1_idp_target_cp]]+ndp_SP1[[#This Row],[sp1_ndp_target_cp]] -> 0 | AO50: =idp_SP1[[#This Row],[sp1_idp_target_gb]]+ndp_SP1[[#This Row],[sp1_ndp_target_gb]] -> 0 | AP50: =idp_SP1[[#This Row],[sp1_idp_target_fs]]+ndp_SP1[[#This Row],[sp1_ndp_target_fs]] -> 0 | AQ50: =idp_SP1[[#This Row],[sp1_idp_target_li]]+ndp_SP1[[#This Row],[sp1_ndp_target_li]] -> 0 | AR50: =idp_SP1[[#This Row],[sp1_idp_target_cw]]+ndp_SP1[[#This Row],[sp1_ndp_target_cw]] -> 0 | AS50: =idp_SP1[[#This Row],[sp1_idp_target_joint]]+ndp_SP1[[#This Row],[sp1_ndp_target_joint]] -> 0 | AT50: 0 | AU50: 0 | AV50: 0 | AW50: 0 | AX50: 0 | AY50: 0 | AZ50: 0 | BA50: 0 | BB50: 0 | BC50: 0 | BD50: 0 | BE50: 0 | BF50: 0
A51: Kyiv | B51: UA80 | C51: All oblast | D51: 50+ | E51: UA80_UALL | F51: 0 | G51: 0 | I51: =idp_SP1[[#This Row],[sp1_idp_pin_ed]]+ndp_SP1[[#This Row],[sp1_ndp_pin_ed]] -> 0 | J51: =idp_SP1[[#This Row],[sp1_idp_pin_fl]]+ndp_SP1[[#This Row],[sp1_ndp_pin_fl]] -> 0 | K51: =idp_SP1[[#This Row],[sp1_idp_pin_he]]+ndp_SP1[[#This Row],[sp1_ndp_pin_he]] -> 0 | L51: =idp_SP1[[#This Row],[sp1_idp_pin_pr]]+ndp_SP1[[#This Row],[sp1_ndp_pin_pr]] -> 0 | M51: =idp_SP1[[#This Row],[sp1_idp_pin_sn]]+ndp_SP1[[#This Row],[sp1_ndp_pin_sn]] -> 0 | N51: =idp_SP1[[#This Row],[sp1_idp_pin_wa]]+ndp_SP1[[#This Row],[sp1_ndp_pin_wa]] -> 0 | O51: =idp_SP1[[#This Row],[sp1_idp_pin_gp]]+ndp_SP1[[#This Row],[sp1_ndp_pin_gp]] -> 0 | P51: =idp_SP1[[#This Row],[sp1_idp_pin_cp]]+ndp_SP1[[#This Row],[sp1_ndp_pin_cp]] -> 0 | Q51: =idp_SP1[[#This Row],[sp1_idp_pin_gb]]+ndp_SP1[[#This Row],[sp1_ndp_pin_gb]] -> 0 | R51: =idp_SP1[[#This Row],[sp1_idp_pin_fs]]+ndp_SP1[[#This Row],[sp1_ndp_pin_fs]] -> 0 | S51: =idp_SP1[[#This Row],[sp1_idp_pin_li]]+ndp_SP1[[#This Row],[sp1_ndp_pin_li]] -> 0 | T51: =idp_SP1[[#This Row],[sp1_idp_pin_adopted]]+ndp_SP1[[#This Row],[sp1_ndp_pin_adopted]] -> 0 | X51: =MAX(idp_SP1[[#This Row],[sp1_idp_sev_pr]],ndp_SP1[[#This Row],[sp1_ndp_sev_pr]]) -> 0 | Y51: 0 | AG51: =idp_SP1[[#This Row],[sp1_idp_target_ed]]+ndp_SP1[[#This Row],[sp1_ndp_target_ed]] -> 0 | AH51: =idp_SP1[[#This Row],[sp1_idp_target_fl]]+ndp_SP1[[#This Row],[sp1_ndp_target_fl]] -> 0 | AI51: =idp_SP1[[#This Row],[sp1_idp_target_he]]+ndp_SP1[[#This Row],[sp1_ndp_target_he]] -> 0 | AJ51: =idp_SP1[[#This Row],[sp1_idp_target_pr]]+ndp_SP1[[#This Row],[sp1_ndp_target_pr]] -> 0 | AK51: =idp_SP1[[#This Row],[sp1_idp_target_sn]]+ndp_SP1[[#This Row],[sp1_ndp_target_sn]] -> 0 | AL51: =idp_SP1[[#This Row],[sp1_idp_target_wa]]+ndp_SP1[[#This Row],[sp1_ndp_target_wa]] -> 0 | AM51: =idp_SP1[[#This Row],[sp1_idp_target_gp]]+ndp_SP1[[#This Row],[sp1_ndp_target_gp]] -> 0 | AN51: =idp_SP1[[#This Row],[sp1_idp_target_cp]]+ndp_SP1[[#This Row],[sp1_ndp_target_cp]] -> 0 | AO51: =idp_SP1[[#This Row],[sp1_idp_target_gb]]+ndp_SP1[[#This Row],[sp1_ndp_target_gb]] -> 0 | AP51: =idp_SP1[[#This Row],[sp1_idp_target_fs]]+ndp_SP1[[#This Row],[sp1_ndp_target_fs]] -> 0 | AQ51: =idp_SP1[[#This Row],[sp1_idp_target_li]]+ndp_SP1[[#This Row],[sp1_ndp_target_li]] -> 0 | AR51: =idp_SP1[[#This Row],[sp1_idp_target_cw]]+ndp_SP1[[#This Row],[sp1_ndp_target_cw]] -> 0 | AS51: =idp_SP1[[#This Row],[sp1_idp_target_joint]]+ndp_SP1[[#This Row],[sp1_ndp_target_joint]] -> 0 | AT51: 0 | AU51: 0 | AV51: 0 | AW51: 0 | AX51: 0 | AY51: 0 | AZ51: 0 | BA51: 0 | BB51: 0 | BC51: 0 | BD51: 0 | BE51: 0 | BF51: 0
A52: OT | B52: UAOT | C52: OT 0-20 km | D52: 0-20km | E52: UAOT_O20A | F52: 7414 | G52: 224914 | H52: 232328 | T52: =idp_SP1[[#This Row],[sp1_idp_pin_adopted]]+ndp_SP1[[#This Row],[sp1_ndp_pin_adopted]] -> 232328 | AF52: 5 | AS52: =idp_SP1[[#This Row],[sp1_idp_target_joint]]+ndp_SP1[[#This Row],[sp1_ndp_target_joint]] -> 132696 | BF52: 132696
